Workbook

Sheet Global
A1: Parameter | B1: Value | C1: Comments
A2: Environment | B2: UAT
A3: ResultFileLocation | B3: ="L:\Regression\Test Results\Temp_Results\AEM Regression\Travelex\"&B2&"\"&B9&""&TEXT(NOW(),"ddmmmyyhhmmss")&"\" -> L:\Regression\Test Results\Temp_Results\AEM Regression\Travelex\UAT\Travel EX Migration_AEM Regression_UAT01Sep26101238\ | C3: =SUBSTITUTE(RIGHT(B3,7),"\","") -> 101238
A4: ResultFilename | B4: =B9&"_"&DAY(NOW())&TEXT(MONTH(NOW()),"MMM")&YEAR(NOW())&MINUTE(NOW())&SECOND(NOW())&".xlsx" -> Travel EX Migration_AEM Regression_UAT_1Jan20261238.xlsx | C4: =TEXT(NOW(),"YYMMDDHHMM") -> 2609011012
A5: isHTMLParsing | B5: N | C5: Default is False. XML parsing will be used for default
A6: removeNamespacesInResponse | B6: N | C6: Default is False
A7: sendOutlookMail | B7: N | C7: Default is True
A8: CreateHtmlReport | B8: Y | C8: Used for reporting. If this parameter is missing or blank, default behavior is True (html report will be generated)
A9: ResultTitle | B9: ="Travel EX Migration_AEM Regression_"&B2 -> Travel EX Migration_AEM Regression_UAT | C9: Used for reporting. If this parameter is missing or blank, default value is used "Test Run Result".
A10: Notes | B10: 01 | C10: Used for reporting. If this parameter is missing or blank, default value is used "N/A".
A11: TC_Name_Column | B11: DT_Scenario | C11: Used for reporting. This is required. If this is missing, result summary table of the report will be empty.
A12: TC_ID_Column | B12: TCID
A13: EmailSubject | B13: ="Automated Test Result - " & B9 & "-" & B2 -> Automated Test Result - Travel EX Migration_AEM Regression_UAT-UAT
A14: SendEmailTO | B14: qa@travelguard.com
A15: SendEmailCC
A16: EmailRunTimeDatasheet | B16: N
A17: QuitBreakOnFailure | B17: N
A18: PauseOnFail | B18: N
A19: Application | B19: NA
A20: WorkItemNumber | B20: NA
A21: WorkItemDescription | B21: NA
A22: Cycle | B22: 1
A23: isOfficial | B23: N
A24: ManualTestHours | B24: 1
A25: HeadlessMode | B25: N

Sheet DataSheets
A1: SheetsToExecute | B1: blnExecute | C1: ParameterSheet | D1: Comments
A2: Owner_AZ | B2: N | C2: Params_1 | D2: Comprehensive Coverage - Owner Advantange Plan | E2: w/ captcha
A3: Owner_CRVD | B3: Y | C3: Params_2 | D3: Comprehensive Coverage - Rental Car Damage Plan | E3: w/ captcha
A4: Owner_RVD | B4: N | C4: Params_3 | D4: Rental Car Coverage - Rental Car Damage Plan | E4: w/ captcha
A5: PostDeparture | B5: N | C5: Params_4 | D5: Post Departure Plan | E5: w/ captcha
A6: Preview | B6: N | C6: Params_5 | D6: Preview Plan | E6: w/ captcha
A7: Travelkore | B7: Y | C7: Params_6 | D7: Travel Med Go
A8: ANZ | B8: N | C8: Params_7 | D8: Travel Protection Plan
A9: CW | B9: Y | C9: Params_8 | D9: Travel Protection Plan
A10: WM | B10: N | C10: Params_9 | D10: Travel Protection Plan

Sheet Owner_AZ
A1: blnExecute | B1: Step_Number | C1: Step_Name | D1: Status | E1: Error_Check | F1: breakpoint | G1: Test_Case | H1: Page | I1: FindBy | J1: FindBy_Value | K1: Index | L1: Method | M1: Value | N1: Output_Property | O1: Ignore_not_existing_object | P1: isDisabled | Q1: Timeout | R1: Expected_Value | S1: Output_Value | T1: Exact_Match | U1: Contains | V1: ITERATION_NO | W1: Notes | X1: Start_Time | Y1: End_Time | Z1: Duration
A2: Open Owner Advantage URL
A3: =IF(OR(Global!B25="N"),"N","bln677971") -> N | B3: =COUNTA($B$1:B2) -> 1 | C3: Open Browser | G3: Owner Advantage | L3: Wait | M3: 1 | O3: Y | R3: DT_URL
A4: =IF(OR(Global!B25="N"),"N","bln677971") -> N | B4: =COUNTA($B$1:B3) -> 2 | C4: Headless | G4: Owner Advantage | H4: DT_BrowserType | L4: Open | M4: ="URL:="&R3&";;HEADLESS:=TRUE" -> URL:=DT_URL;;HEADLESS:=TRUE | Q4: 60
A5: =IF(OR(Global!B25="Y"),"N","bln677971") -> bln677971 | B5: =COUNTA($B$1:B4) -> 3 | C5: Open Browser | G5: Owner Advantage | H5: DT_BrowserType | L5: Open | M5: DT_URL | Q5: 60
A6: N | B6: =COUNTA($B$1:B5) -> 4 | C6: Wait | G6: Owner Advantage | L6: Wait | M6: 5
A7: N | B7: =COUNTA($B$1:B6) -> 5 | C7: Zscaler Sign in Email | G7: Owner Advantage | I7: xpath | J7: //input[@id='okta-signin-username'] | K7: 0 | L7: Set | M7: DT_ZScalerUser | O7: Y | Q7: 5
A8: N | B8: =COUNTA($B$1:B7) -> 6 | C8: Zscaler Password | G8: Owner Advantage | I8: xpath | J8: //input[@id='okta-signin-password'] | K8: 0 | L8: Set | M8: DT_ZScalerPassword | O8: Y
A9: N | B9: =COUNTA($B$1:B8) -> 7 | C9: Click Sign in | G9: Owner Advantage | I9: xpath | J9: //input[@id='okta-signin-submit'] | K9: 0 | L9: Click | O9: Y
A10: N | B10: =COUNTA($B$1:B9) -> 8 | C10: Wait | G10: Owner Advantage | L10: Wait | M10: 5
A11: Quote - Home Page
A12: bln677971 | B12: =COUNTA($B$1:B11) -> 9 | C12: Switch to Frame | G12: Owner Advantage | L12: SWITCHTOFRAME | M12: aemFormFrame | W12: tripType
A13: bln677971 | B13: =COUNTA($B$1:B12) -> 10 | C13: Check Exist | G13: Owner Advantage | I13: xpath | J13: //button[text()='Accept All Cookies'] | L13: Exist | O13: Y
A14: bln677971 | B14: =COUNTA($B$1:B13) -> 11 | C14: Output Cookie | G14: Owner Advantage | I14: xpath | J14: //button[text()='Accept All Cookies'] | L14: Output | N14: innertext | O14: Y | R14: Accept All Cookies
A15: bln677971 | B15: =COUNTA($B$1:B14) -> 12 | C15: Cookies | G15: Owner Advantage | I15: xpath | J15: //button[@id='onetrust-accept-btn-handler'] | L15: js_click | O15: Y
A16: bln677971 | B16: =COUNTA($B$1:B15) -> 13 | C16: Select Trip Type | G16: Owner Advantage | I16: xpath | J16: ="//label[contains(.,'"&W12&"')]" -> //label[contains(.,'tripType')] | K16: 0 | L16: js_click
A17: bln677971 | B17: =COUNTA($B$1:B16) -> 14 | C17: Click Destination | G17: Owner Advantage | I17: xpath | J17: //input[@id='cmp-Input' and @placeholder='Select a country or region'] | K17: 0 | L17: Click
A18: bln677971 | B18: =COUNTA($B$1:B17) -> 15 | C18: Wait | G18: Owner Advantage | L18: Wait | M18: 2
A19: bln677971 | B19: =COUNTA($B$1:B18) -> 16 | C19: Write Destination | G19: Owner Advantage | I19: xpath | J19: //input[@id='cmp-Input' and @placeholder='Select a country or region'] | K19: 0 | L19: Write | M19: Destination
A20: bln677971 | B20: =COUNTA($B$1:B19) -> 17 | C20: Wait | G20: Owner Advantage | L20: Wait | M20: 2
A21: bln677971 | B21: =COUNTA($B$1:B20) -> 18 | C21: Click Destination | G21: Owner Advantage | I21: xpath | J21: ="//a[contains(.,'"&M19&"')]" -> //a[contains(.,'Destination')] | K21: 0 | L21: js_click
A22: bln677971 | B22: =COUNTA($B$1:B21) -> 19 | C22: Departure Date | G22: Owner Advantage | I22: xpath | J22: //input[@name='tripDepartureDate'] | K22: 0 | L22: Set | M22: DepDate
A23: bln677971 | B23: =COUNTA($B$1:B22) -> 20 | C23: Return Date | G23: Owner Advantage | I23: xpath | J23: //input[@name='tripReturnDate'] | K23: 0 | L23: Set | M23: RetDate
A24: bln677971 | B24: =COUNTA($B$1:B23) -> 21 | C24: Deposit Date | G24: Owner Advantage | I24: xpath | J24: //input[@name='tripDepositDate'] | K24: 0 | L24: Set | M24: DepoDate
A25: bln677971 | B25: =COUNTA($B$1:B24) -> 22 | C25: Click State | G25: Owner Advantage | I25: xpath | J25: //input[@id='cmp-Input' and @placeholder='Select your state'] | K25: 0 | L25: Click
A26: bln677971 | B26: =COUNTA($B$1:B25) -> 23 | C26: Wait | G26: Owner Advantage | L26: Wait | M26: 2
A27: bln677971 | B27: =COUNTA($B$1:B26) -> 24 | C27: Write State | G27: Owner Advantage | I27: xpath | J27: //input[@id='cmp-Input' and @placeholder='Select your state'] | K27: 0 | L27: Write | M27: Residence
A28: bln677971 | B28: =COUNTA($B$1:B27) -> 25 | C28: Wait | G28: Owner Advantage | L28: Wait | M28: 2
A29: bln677971 | B29: =COUNTA($B$1:B28) -> 26 | C29: Click Destination | G29: Owner Advantage | I29: xpath | J29: ="//a[contains(.,'"&M27&"')]" -> //a[contains(.,'Residence')] | K29: 0 | L29: js_click
A30: =IF($W$12="Comprehensive Coverage","Y","N") -> N | B30: =COUNTA($B$1:B29) -> 27 | C30: Enter Age | G30: Owner Advantage | I30: xpath | J30: (//input[@name='insuredAge'])[1] | K30: 0 | L30: Set | M30: Age
A31: =A30 -> N | B31: =COUNTA($B$1:B30) -> 28 | C31: Enter Trip Cost | G31: Owner Advantage | I31: xpath | J31: (//input[@name='display_tripCost'])[1] | K31: 0 | L31: Set | M31: Cost
A32: N | B32: =COUNTA($B$1:B31) -> 29 | C32: Click Add | G32: Owner Advantage | I32: xpath | J32: //button[@id='add-container-button__1'] | K32: 0 | L32: js_click
A33: N | B33: =COUNTA($B$1:B32) -> 30 | C33: Enter Age1 | G33: Owner Advantage | I33: xpath | J33: (//input[@name='insuredAge'])[2] | K33: 0 | L33: Set | M33: Age1
A34: N | B34: =COUNTA($B$1:B33) -> 31 | C34: Enter Trip Cost1 | G34: Owner Advantage | I34: xpath | J34: (//input[@name='display_tripCost'])[2] | K34: 0 | L34: Set | M34: Cost1
A35: N | B35: =COUNTA($B$1:B34) -> 32 | C35: Click Add | G35: Owner Advantage | I35: xpath | J35: //button[@id='add-container-button__2'] | K35: 0 | L35: js_click
A36: N | B36: =COUNTA($B$1:B35) -> 33 | C36: Enter Age2 | G36: Owner Advantage | I36: xpath | J36: (//input[@name='insuredAge'])[3] | K36: 0 | L36: Set | M36: Age2
A37: N | B37: =COUNTA($B$1:B36) -> 34 | C37: Enter Trip Cost2 | G37: Owner Advantage | I37: xpath | J37: (//input[@name='display_tripCost'])[3] | K37: 0 | L37: Set | M37: Cost2
A38: N | B38: =COUNTA($B$1:B37) -> 35 | C38: Click Add | G38: Owner Advantage | I38: xpath | J38: //button[@id='add-container-button__3'] | K38: 0 | L38: js_click
A39: N | B39: =COUNTA($B$1:B38) -> 36 | C39: Enter Age3 | G39: Owner Advantage | I39: xpath | J39: (//input[@name='insuredAge'])[4] | K39: 0 | L39: Set | M39: Age3
A40: N | B40: =COUNTA($B$1:B39) -> 37 | C40: Enter Trip Cost3 | G40: Owner Advantage | I40: xpath | J40: (//input[@name='display_tripCost'])[4] | K40: 0 | L40: Set | M40: Cost3
A41: bln677971 | B41: =COUNTA($B$1:B40) -> 38 | C41: Click Submit button | G41: Owner Advantage | I41: xpath | J41: //button[@type='SUBMIT'] | K41: 0 | L41: js_click
A42: bln677971 | B42: =COUNTA($B$1:B41) -> 39 | C42: Wait | G42: Owner Advantage | L42: Wait | M42: 10
A43: Plan Option and Upgrades
A44: bln677971 | B44: =COUNTA($B$1:B43) -> 40 | C44: Check Exist | G44: Owner Advantage | I44: xpath | J44: //button[text()='Accept All Cookies'] | L44: Exist | O44: Y
A45: bln677971 | B45: =COUNTA($B$1:B44) -> 41 | C45: Output Cookie | G45: Owner Advantage | I45: xpath | J45: //button[text()='Accept All Cookies'] | L45: Output | N45: innertext | O45: Y | R45: Accept All Cookies
A46: bln677971 | B46: =COUNTA($B$1:B45) -> 42 | C46: Cookies | G46: Owner Advantage | I46: xpath | J46: //button[@id='onetrust-accept-btn-handler'] | L46: js_click | O46: Y
A47: bln677971 | B47: =COUNTA($B$1:B46) -> 43 | C47: Comprehensive Coverage | G47: Owner Advantage | I47: xpath | J47: //button[@name='selectPlan' and @value='MRZ-0925'] | K47: 0 | L47: js_click
A48: =IF(AND($W$12="Rental Car Coverage",$W$16="None"),"Y","N") -> N | B48: =COUNTA($B$1:B47) -> 44 | C48: Rental Car Coverage | G48: Owner Advantage | I48: xpath | J48: //button[@name='selectPlan' and @value='MRCDZ-0925'] | K48: 0 | L48: js_click
A49: =IF(AND($W$12="Comprehensive Coverage",$W$16="Rental Car Damage Plan"),"Y","N") -> N | B49: =COUNTA($B$1:B48) -> 45 | C49: Rental Car Damage Plan | G49: Owner Advantage | I49: xpath | J49: //button[@name='selectPlan' and @value='MRCDZ-0925'] | K49: 0 | L49: js_click
A50: bln677971 | B50: =COUNTA($B$1:B49) -> 46 | C50: Wait | G50: Owner Advantage | L50: Wait | M50: 2
A51: bln677971 | B51: =COUNTA($B$1:B50) -> 47 | C51: Check Exist | G51: Owner Advantage | I51: xpath | J51: //button[text()='Accept All Cookies'] | L51: Exist | O51: Y
A52: bln677971 | B52: =COUNTA($B$1:B51) -> 48 | C52: Output Cookie | G52: Owner Advantage | I52: xpath | J52: //button[text()='Accept All Cookies'] | L52: Output | N52: innertext | O52: Y | R52: Accept All Cookies
A53: bln677971 | B53: =COUNTA($B$1:B52) -> 49 | C53: Cookies | G53: Owner Advantage | I53: xpath | J53: //button[@id='onetrust-accept-btn-handler'] | L53: js_click | O53: Y
A54: bln677971 | B54: =COUNTA($B$1:B53) -> 50 | C54: Pet Care | G54: Owner Advantage | I54: xpath | J54: //input[@name='PCU_addOn' and @value='Yes'] | K54: 0 | L54: js_click
A55: bln677971 | B55: =COUNTA($B$1:B54) -> 51 | C55: Rental Car Damage | G55: Owner Advantage | I55: xpath | J55: //input[@name='RVD_addOn' and @value='Yes'] | K55: 0 | L55: js_click
A56: bln677971 | B56: =COUNTA($B$1:B55) -> 52 | C56: Pick Up Date | G56: Owner Advantage | I56: xpath | J56: //input[@name='pickupDate'] | K56: 0 | L56: Set | M56: PickUpDate
A57: bln677971 | B57: =COUNTA($B$1:B56) -> 53 | C57: Drop Off Date | G57: Owner Advantage | I57: xpath | J57: //input[@name='dropoffDate'] | K57: 0 | L57: Set | M57: DropOffDate
A58: bln677971 | B58: =COUNTA($B$1:B57) -> 54 | C58: Click Add Dates | G58: Owner Advantage | I58: xpath | J58: //button[@id='RVD_addDates'] | K58: 0 | L58: js_click
A59: bln677971 | B59: =COUNTA($B$1:B58) -> 55 | C59: Verify Date added | G59: Owner Advantage | I59: xpath | J59: (//div[@id='text-eca6e55636'])[2] | L59: Output | N59: innertext | R59: =TEXT(M56,"mm/dd/yyyy") & " - " & TEXT(M57,"mm/dd/yyyy") -> PickUpDate - DropOffDate | T59: Y
A60: bln677971 | B60: =COUNTA($B$1:B59) -> 56 | C60: Pick Up Date | G60: Owner Advantage | I60: xpath | J60: //input[@name='pickupDate'] | K60: 0 | L60: Set | M60: PickUpDate1
A61: bln677971 | B61: =COUNTA($B$1:B60) -> 57 | C61: Drop Off Date | G61: Owner Advantage | I61: xpath | J61: //input[@name='dropoffDate'] | K61: 0 | L61: Set | M61: DropOffDate1
A62: bln677971 | B62: =COUNTA($B$1:B61) -> 58 | C62: Click Add Dates | G62: Owner Advantage | I62: xpath | J62: //button[@id='RVD_addDates'] | K62: 0 | L62: js_click
A63: bln677971 | B63: =COUNTA($B$1:B62) -> 59 | C63: Verify Date added | G63: Owner Advantage | I63: xpath | J63: (//div[@id='text-eca6e55636'])[3] | L63: Output | N63: innertext | R63: =TEXT(M60,"mm/dd/yyyy") & " - " & TEXT(M61,"mm/dd/yyyy") -> PickUpDate1 - DropOffDate1 | T63: Y
A64: bln677971 | B64: =COUNTA($B$1:B63) -> 60 | C64: Pick Up Date | G64: Owner Advantage | I64: xpath | J64: //input[@name='pickupDate'] | K64: 0 | L64: Set | M64: PickUpDate2
A65: bln677971 | B65: =COUNTA($B$1:B64) -> 61 | C65: Drop Off Date | G65: Owner Advantage | I65: xpath | J65: //input[@name='dropoffDate'] | K65: 0 | L65: Set | M65: DropOffDate2
A66: bln677971 | B66: =COUNTA($B$1:B65) -> 62 | C66: Click Add Dates | G66: Owner Advantage | I66: xpath | J66: //button[@id='RVD_addDates'] | K66: 0 | L66: js_click
A67: bln677971 | B67: =COUNTA($B$1:B66) -> 63 | C67: Verify Date added | G67: Owner Advantage | I67: xpath | J67: (//div[@id='text-eca6e55636'])[4] | L67: Output | N67: innertext | R67: =TEXT(M64,"mm/dd/yyyy") & " - " & TEXT(M65,"mm/dd/yyyy") -> PickUpDate2 - DropOffDate2 | T67: Y
A68: bln677971 | B68: =COUNTA($B$1:B67) -> 64 | C68: Additional Baggage Lost | G68: Owner Advantage | I68: xpath | J68: //input[@name='BL_addOn' and @value='Yes'] | K68: 0 | L68: js_click
A69: bln677971 | B69: =COUNTA($B$1:B68) -> 65 | C69: Click Submit button | G69: Owner Advantage | I69: xpath | J69: //button[@type='SUBMIT'] | K69: 0 | L69: js_click
A70: bln677971 | B70: =COUNTA($B$1:B69) -> 66 | C70: Wait | G70: Owner Advantage | L70: Wait | M70: 10
A71: Travelers Information
A72: bln677971 | B72: =COUNTA($B$1:B71) -> 67 | C72: Check Exist | G72: Owner Advantage | I72: xpath | J72: //button[text()='Accept All Cookies'] | L72: Exist | O72: Y
A73: bln677971 | B73: =COUNTA($B$1:B72) -> 68 | C73: Output Cookie | G73: Owner Advantage | I73: xpath | J73: //button[text()='Accept All Cookies'] | L73: Output | N73: innertext | O73: Y | R73: Accept All Cookies
A74: bln677971 | B74: =COUNTA($B$1:B73) -> 69 | C74: Cookies | G74: Owner Advantage | I74: xpath | J74: //button[@id='onetrust-accept-btn-handler'] | L74: js_click | O74: Y
A75: bln677971 | B75: =COUNTA($B$1:B74) -> 70 | C75: Enter First Name | G75: Owner Advantage | I75: xpath | J75: //input[@name='firstName'] | K75: 0 | L75: Set | M75: FirstName
A76: bln677971 | B76: =COUNTA($B$1:B75) -> 71 | C76: Enter Last Name | G76: Owner Advantage | I76: xpath | J76: //input[@name='lastName'] | K76: 0 | L76: Set | M76: LastName
A77: bln677971 | B77: =COUNTA($B$1:B76) -> 72 | C77: Enter Birth Date | G77: Owner Advantage | I77: xpath | J77: //input[@name='dateOfBirth'] | K77: 0 | L77: Set | M77: BirthDate
A78: bln677971 | B78: =COUNTA($B$1:B77) -> 73 | C78: Click tab | G78: Owner Advantage | L78: SendKeys | M78: {TAB}
A79: bln677971 | B79: =COUNTA($B$1:B78) -> 74 | C79: Wait | G79: Owner Advantage | L79: Wait | M79: 2
A80: bln677971 | B80: =COUNTA($B$1:B79) -> 75 | C80: Enter Address | G80: Owner Advantage | I80: xpath | J80: //input[@name='address1'] | K80: 0 | L80: Set | M80: Address
A81: bln677971 | B81: =COUNTA($B$1:B80) -> 76 | C81: Enter City | G81: Owner Advantage | I81: xpath | J81: //input[@name='city'] | K81: 0 | L81: Set | M81: City
A82: bln677971 | B82: =COUNTA($B$1:B81) -> 77 | C82: Enter Zip Code | G82: Owner Advantage | I82: xpath | J82: //input[@name='postalCode'] | K82: 0 | L82: Set | M82: Zip
A83: bln677971 | B83: =COUNTA($B$1:B82) -> 78 | C83: Enter Phone | G83: Owner Advantage | I83: xpath | J83: //input[@name='dayPhone'] | K83: 0 | L83: Set | M83: Phone
A84: bln677971 | B84: =COUNTA($B$1:B83) -> 79 | C84: Enter Email | G84: Owner Advantage | I84: xpath | J84: //input[@name='email'] | K84: 0 | L84: Set | M84: Email
A85: bln677971 | B85: =COUNTA($B$1:B84) -> 80 | C85: Enter Owner Number | G85: Owner Advantage | I85: xpath | J85: //input[@name='ownerNumber'] | K85: 0 | L85: Set | M85: OwnerPhone
A86: N | B86: =COUNTA($B$1:B85) -> 81 | C86: Enter First Name 2 | G86: Owner Advantage | I86: xpath | J86: (//input[@name='firstName'])[3] | K86: 0 | L86: Set | M86: Trav_FirstName2
A87: N | B87: =COUNTA($B$1:B86) -> 82 | C87: Enter Last Name 2 | G87: Owner Advantage | I87: xpath | J87: (//input[@name='lastName'])[3] | K87: 0 | L87: Set | M87: Trav_LastName2
A88: N | B88: =COUNTA($B$1:B87) -> 83 | C88: Enter Birth Date 2 | G88: Owner Advantage | I88: xpath | J88: (//input[@name='dateOfBirth'])[3] | K88: 0 | L88: Set | M88: Trav_BirthDate2
A89: N | B89: =COUNTA($B$1:B88) -> 84 | C89: Enter First Name 3 | G89: Owner Advantage | I89: xpath | J89: (//input[@name='firstName'])[4] | K89: 0 | L89: Set | M89: Trav_FirstName3
A90: N | B90: =COUNTA($B$1:B89) -> 85 | C90: Enter Last Name 3 | G90: Owner Advantage | I90: xpath | J90: (//input[@name='lastName'])[4] | K90: 0 | L90: Set | M90: Trav_LastName3
A91: N | B91: =COUNTA($B$1:B90) -> 86 | C91: Enter Birth Date 3 | G91: Owner Advantage | I91: xpath | J91: (//input[@name='dateOfBirth'])[4] | K91: 0 | L91: Set | M91: Trav_BirthDate3
A92: bln677971 | B92: =COUNTA($B$1:B91) -> 87 | C92: Click Submit button | G92: Owner Advantage | I92: xpath | J92: //button[@type='SUBMIT'] | K92: 0 | L92: js_click
A93: bln677971 | B93: =COUNTA($B$1:B92) -> 88 | C93: Wait | G93: Owner Advantage | L93: Wait | M93: 10
A94: Payment
A95: bln677971 | B95: =COUNTA($B$1:B94) -> 89 | C95: Check Exist | G95: Owner Advantage | I95: xpath | J95: //button[text()='Accept All Cookies'] | L95: Exist | O95: Y
A96: bln677971 | B96: =COUNTA($B$1:B95) -> 90 | C96: Output Cookie | G96: Owner Advantage | I96: xpath | J96: //button[text()='Accept All Cookies'] | L96: Output | N96: innertext | O96: Y | R96: Accept All Cookies
A97: bln677971 | B97: =COUNTA($B$1:B96) -> 91 | C97: Cookies | G97: Owner Advantage | I97: xpath | J97: //button[@id='onetrust-accept-btn-handler'] | L97: js_click | O97: Y
A98: bln677971 | B98: =COUNTA($B$1:B97) -> 92 | C98: Enter Card Name | G98: Owner Advantage | I98: xpath | J98: //input[@name='cardName'] | K98: 0 | L98: Set | M98: CardName
A99: bln677971 | B99: =COUNTA($B$1:B98) -> 93 | C99: Change iFrame | G99: Owner Advantage | K99: 2 | L99: switchtoframe
A100: bln677971 | B100: =COUNTA($B$1:B99) -> 94 | C100: Enter Card Number | G100: Owner Advantage | I100: xpath | J100: //input[@name='tsep-cardNum'] | K100: 0 | L100: Set | M100: CardNumber
...

Sheet Params_1
A1: Scenario | B1: blnExecute | C1: bln_TG | D1: blnQuit | E1: bln677971 | F1: DT_BrowserType | G1: Notes | H1: DT_URL | I1: DateToday | J1: PolicyNumber_OUT | K1: tripType | L1: Plan | M1: Destination | N1: Restricted | O1: Destination1 | P1: Destination2 | Q1: Destination3 | R1: Destination4 | S1: Destination5 | T1: Destination6 | U1: Destination7 | V1: Destination8 | W1: Destination9 | X1: Destination10 | Y1: Destination11 | Z1: Destination12 | AA1: Destination13 | AB1: Destination14 | AC1: Destination15 | AD1: Destination16 | AE1: Destination17 | AF1: Destination18 | AG1: Destination19 | AH1: Destination20 | AI1: Destination21 | AJ1: Destination22 | AK1: Destination23 | AL1: Destination24 | AM1: Destination25 | AN1: Destination26 | AO1: Destination27 | AP1: Destination28 | AQ1: Destination29 | AR1: Destination30 | AS1: Destination31 | AT1: Destination32 | AU1: Destination33 | AV1: DepDate | AW1: DepDate1 | AX1: DepDateValid | AY1: RetDate | AZ1: RetDate1 | BA1: RetDateValid | BB1: DepoDate | BC1: DepoYearInvalid | BD1: DepoYearValid | BE1: DepoMonthInvalid | BF1: DepoMonthValid | BG1: DepoDayInvalid | BH1: DepoDayValid | BI1: Residence | BJ1: Residence1 | BK1: Residence2 | BL1: Residence3 | BM1: Residence4 | BN1: Residence5 | BO1: Residence6 | BP1: Residence7 | BQ1: Residence8 | BR1: Residence9 | BS1: Residence10 | BT1: Residence11 | BU1: Residence12 | BV1: Residence13 | BW1: Residence14 | BX1: Residence15 | BY1: Residence16 | BZ1: Residence17 | CA1: Residence18 | CB1: Residence19 | CC1: Residence20 | CD1: Residence21 | CE1: Residence22 | CF1: Residence23 | CG1: Residence24 | CH1: Residence25 | CI1: Residence26 | CJ1: Residence27 | CK1: Residence28 | CL1: Residence29 | CM1: Residence30 | CN1: Residence31 | CO1: Residence32 | CP1: Residence33 | CQ1: Residence34 | CR1: Residence35 | CS1: Residence36 | CT1: Residence37 | CU1: Residence38 | CV1: Residence39 | CW1: Residence40 | CX1: Residence41 | CY1: Residence42 | CZ1: Residence43 | DA1: Residence44 | DB1: Residence45 | DC1: Residence46 | DD1: Residence47 | DE1: Residence48 | DF1: Residence49 | DG1: Residence50 | DH1: Residence51 | DI1: Residence52 | DJ1: Residence53 | DK1: Age | DL1: Cost | DM1: CostAllowed | DN1: Age1 | DO1: Cost1 | DP1: Trav_FirstName1 | DQ1: Trav_LastName1 | DR1: Trav_BirthDate1 | DS1: Age2 | DT1: Cost2 | DU1: Trav_FirstName2 | DV1: Trav_LastName2 | DW1: Trav_BirthDate2 | DX1: Age3 | DY1: Cost3 | DZ1: Trav_FirstName3 | EA1: Trav_LastName3 | EB1: Trav_BirthDate3 | EC1: Age4 | ED1: Cost4 | EE1: Trav_FirstName4 | EF1: Trav_LastName4 | EG1: Trav_BirthDate4 | EH1: Age5 | EI1: Cost5 | EJ1: Trav_FirstName5 | EK1: Trav_LastName5 | EL1: Trav_BirthDate5 | EM1: Age6 | EN1: Cost6 | EO1: Trav_FirstName6 | EP1: Trav_LastName6 | EQ1: Trav_BirthDate6 | ER1: Age7 | ES1: Cost7 | ET1: Trav_FirstName7 | EU1: Trav_LastName7 | EV1: Trav_BirthDate7 | EW1: Age8 | EX1: Cost8 | EY1: Trav_FirstName8 | EZ1: Trav_LastName8 | FA1: Trav_BirthDate8 | FB1: Age9 | FC1: Cost9 | FD1: Trav_FirstName9 | FE1: Trav_LastName9 | FF1: Trav_BirthDate9 | FG1: PickUpDate | FH1: DropOffDate | FI1: PickUpDate1 | FJ1: DropOffDate1 | FK1: PickUpDate2 | FL1: DropOffDate2 | FM1: PickUpDate3 | FN1: DropOffDate3 | FO1: PickUpDate4 | FP1: DropOffDate4 | FQ1: FirstName | FR1: LastName | FS1: BirthDate | FT1: BirthDateInvalid | FU1: BirthDate1 | FV1: Address | FW1: City | FX1: Zip | FY1: ZipX | FZ1: City1 | GA1: Zip1 | GB1: Phone | GC1: Phone1 | GD1: Email | GE1: Email1 | GF1: OwnerPhone | GG1: CardName | GH1: CardNumber | GI1: CardNumber1 | GJ1: ExpiryMonth | GK1: ExpiryYear | GL1: Cost_OUT | GM1: Cost_RES | GN1: Destination_OUT | GO1: Destination_RES | GP1: Plan | GQ1: Plan_OUT | GR1: Plan_RES | GS1: Plan1 | GT1: Plan1_OUT | GU1: Plan_RES | GV1: Plan2 | GW1: Plan2_OUT | GX1: Plan_RES | GY1: ErrorMessage | GZ1: ErrorMessage_OUT | HA1: ErrorMessage_RES | HB1: ErrorMessage1 | HC1: ErrorMessage1_OUT | HD1: ErrorMessage_RES | HE1: ErrorMessage2 | HF1: ErrorMessage2_OUT | HG1: ErrorMessage_RES | HH1: ErrorMessage3 | HI1: ErrorMessage3_OUT | HJ1: ErrorMessage_RES | HK1: Tooltip | HL1: Tooltip_OUT | HM1: Tooltip_RES | HN1: Tooltip1 | HO1: Tooltip1_OUT | HP1: Tooltip1_RES | HQ1: Tooltip2 | HR1: Tooltip2_OUT | HS1: Tooltip2_RES | HT1: FAQ1 | HU1: FAQ1_OUT | HV1: FAQ1_RES | HW1: FAQ2 | HX1: FAQ2_OUT | HY1: FAQ2_RES | HZ1: FAQ3 | IA1: FAQ3_OUT | IB1: FAQ3_RES | IC1: FAQ4 | ID1: FAQ4_OUT | IE1: FAQ4_RES | IF1: FAQ5 | IG1: FAQ5_OUT | IH1: FAQ5_RES | II1: OwnerAdvantagePlan_OUT | IJ1: RentalCarDamagePlan_OUT | IK1: OwnerAdvantagePlan_VERIFY | IL1: RentalCarDamage_VERIFY
A2: bln677971 | B2: Y | C2: Y | D2: Y | E2: Y | F2: Chrome | G2: TC_677971 | H2: {=_xlfn.IFS(Global!B2="QA","https://owneradvantage.qa.insurancebytravelex.com/",Global!B2="UAT","https://owneradvantage.uat.insurancebytravelex.com/",Global!B2="PROD","https://owneradvantage.insurancebytravelex.com/")} -> https://owneradvantage.uat.insurancebytravelex.com/ | I2: =TODAY() -> 46266 | K2: Comprehensive Coverage | L2: Advantage Plan | M2: Singapore | O2: Australia | AV2: =TEXT(I2+1,"mm/dd/yyyy") -> 09/02/2026 | AW2: =TEXT(I2+7,"mm/dd/yyyy") -> 09/08/2026 | AX2: =TEXT(I2+7,"mm/dd/yyyy") -> 09/08/2026 | AY2: =TEXT(AV2+89,"mm/dd/yyyy") -> 11/30/2026 | AZ2: =TEXT(AW2+14,"mm/dd/yyyy") -> 09/22/2026 | BA2: =TEXT(AV2+14,"mm/dd/yyyy") -> 09/16/2026 | BB2: =TEXT(I2-1,"mm/dd/yyyy") -> 08/31/2026 | BI2: California | BJ2: Nebraska | BK2: New York | DK2: 110 | DL2: 1000 | DM2: 100 | DN2: 18 | DO2: 1500 | DP2: ="QAFIRSTNAME"&CHAR(RANDBETWEEN(65,90))&CHAR(RANDBETWEEN(65,90)) -> QAFIRSTNAMEKV | DQ2: ="QALASTNAME"&CHAR(RANDBETWEEN(65,90))&CHAR(RANDBETWEEN(65,90)) -> QALASTNAMESD | DR2: =TEXT(DATE(YEAR(TODAY())-DS2,MONTH(TODAY()),DAY(TODAY())),"MM/DD/YYYY") -> 09/01/2000 | DS2: 26 | DT2: 1500 | DU2: ="QAFIRSTNAME"&CHAR(RANDBETWEEN(65,90))&CHAR(RANDBETWEEN(65,90)) -> QAFIRSTNAMEJE | DV2: ="QALASTNAME"&CHAR(RANDBETWEEN(65,90))&CHAR(RANDBETWEEN(65,90)) -> QALASTNAMEFT | DW2: 01/01/2000 | FG2: =TEXT(AX2,"mm/dd/yyyy") -> 09/08/2026 | FH2: =TEXT(AX2+1,"mm/dd/yyyy") -> 09/09/2026 | FI2: =TEXT(FH2+1,"mm/dd/yyyy") -> 09/10/2026 | FJ2: =TEXT(FI2+1,"mm/dd/yyyy") -> 09/11/2026 | FK2: =TEXT(FJ2+1,"mm/dd/yyyy") -> 09/12/2026 | FL2: =TEXT(FK2+1,"mm/dd/yyyy") -> 09/13/2026 | FM2: =TEXT(FL2+7,"mm/dd/yyyy") -> 09/20/2026 | FN2: =TEXT(FM2+1,"mm/dd/yyyy") -> 09/21/2026 | FO2: =TEXT(FN2+1,"mm/dd/yyyy") -> 09/22/2026 | FP2: =TEXT(FO2+1,"mm/dd/yyyy") -> 09/23/2026 | FQ2: ="QAFIRSTNAME"&CHAR(RANDBETWEEN(65,90))&CHAR(RANDBETWEEN(65,90)) -> QAFIRSTNAMEQB | FR2: ="QALASTNAME"&CHAR(RANDBETWEEN(65,90))&CHAR(RANDBETWEEN(65,90)) -> QALASTNAMEDA | FS2: =TEXT(DATE(YEAR(TODAY())-DK2,MONTH(TODAY()),DAY(TODAY())),"MM/DD/YYYY") -> 09/01/1916 | FU2: =TEXT(DATE(YEAR(TODAY())-DN2,MONTH(TODAY()),DAY(TODAY())),"MM/DD/YYYY") -> 09/01/2008 | FV2: QA213 COR246 | FW2: Los Angeles | FX2: 90001 | FY2: 12345 | FZ2: Omaha | GA2: 68102 | GB2: 1234567897 | GC2: 2222222222 | GD2: qa@travelexinsurance.com | GE2: qa@travelguard.com | GF2: qwertyuiopasdfgh | GG2: QA Test | GH2: 4111111111111111 | GJ2: 12 | GK2: 2030

Sheet Owner_CRVD
A1: blnExecute | B1: Step_Number | C1: Step_Name | D1: Status | E1: Error_Check | F1: breakpoint | G1: Test_Case | H1: Page | I1: FindBy | J1: FindBy_Value | K1: Index | L1: Method | M1: Value | N1: Output_Property | O1: Ignore_not_existing_object | P1: isDisabled | Q1: Timeout | R1: Expected_Value | S1: Output_Value | T1: Exact_Match | U1: Contains | V1: ITERATION_NO | W1: Notes | X1: Start_Time | Y1: End_Time | Z1: Duration
A2: Open Owner Advantage URL
A3: =IF(OR(Global!B25="N"),"N","bln680505") -> N | B3: =COUNTA($B$1:B2) -> 1 | C3: Open Browser | G3: Owner Advantage | L3: Wait | M3: 1 | O3: Y | R3: DT_URL
A4: =IF(OR(Global!B25="N"),"N","bln680505") -> N | B4: =COUNTA($B$1:B3) -> 2 | C4: Headless | G4: Owner Advantage | H4: DT_BrowserType | L4: Open | M4: ="URL:="&R3&";;HEADLESS:=TRUE" -> URL:=DT_URL;;HEADLESS:=TRUE | Q4: 60
A5: =IF(OR(Global!B25="Y"),"N","bln680505") -> bln680505 | B5: =COUNTA($B$1:B4) -> 3 | C5: Open Browser | G5: Owner Advantage | H5: DT_BrowserType | L5: Open | M5: DT_URL | Q5: 60
A6: N | B6: =COUNTA($B$1:B5) -> 4 | C6: Wait | G6: Owner Advantage | L6: Wait | M6: 5
A7: N | B7: =COUNTA($B$1:B6) -> 5 | C7: Zscaler Sign in Email | G7: Owner Advantage | I7: xpath | J7: //input[@id='okta-signin-username'] | K7: 0 | L7: Set | M7: DT_ZScalerUser | O7: Y | Q7: 5
A8: N | B8: =COUNTA($B$1:B7) -> 6 | C8: Zscaler Password | G8: Owner Advantage | I8: xpath | J8: //input[@id='okta-signin-password'] | K8: 0 | L8: Set | M8: DT_ZScalerPassword | O8: Y
A9: N | B9: =COUNTA($B$1:B8) -> 7 | C9: Click Sign in | G9: Owner Advantage | I9: xpath | J9: //input[@id='okta-signin-submit'] | K9: 0 | L9: Click | O9: Y
A10: N | B10: =COUNTA($B$1:B9) -> 8 | C10: Wait | G10: Owner Advantage | L10: Wait | M10: 5
A11: Quote - Home Page
A12: bln680505 | B12: =COUNTA($B$1:B11) -> 9 | C12: Switch to Frame | G12: Owner Advantage | L12: SWITCHTOFRAME | M12: aemFormFrame | W12: tripType
A13: bln680505 | B13: =COUNTA($B$1:B12) -> 10 | C13: Check Exist | G13: Owner Advantage | I13: xpath | J13: //button[text()='Accept All Cookies'] | L13: Exist | O13: Y
A14: bln680505 | B14: =COUNTA($B$1:B13) -> 11 | C14: Output Cookie | G14: Owner Advantage | I14: xpath | J14: //button[text()='Accept All Cookies'] | L14: Output | N14: innertext | O14: Y | R14: Accept All Cookies
A15: bln680505 | B15: =COUNTA($B$1:B14) -> 12 | C15: Cookies | G15: Owner Advantage | I15: xpath | J15: //button[@id='onetrust-accept-btn-handler'] | L15: js_click | O15: Y
A16: bln680505 | B16: =COUNTA($B$1:B15) -> 13 | C16: Select Trip Type | G16: Owner Advantage | I16: xpath | J16: ="//label[contains(.,'"&W12&"')]" -> //label[contains(.,'tripType')] | K16: 0 | L16: js_click
A17: bln680505 | B17: =COUNTA($B$1:B16) -> 14 | C17: Click Destination | G17: Owner Advantage | I17: xpath | J17: //input[@id='cmp-Input' and @placeholder='Select a country or region'] | K17: 0 | L17: Click
A18: bln680505 | B18: =COUNTA($B$1:B17) -> 15 | C18: Wait | G18: Owner Advantage | L18: Wait | M18: 2
A19: bln680505 | B19: =COUNTA($B$1:B18) -> 16 | C19: Write Destination | G19: Owner Advantage | I19: xpath | J19: //input[@id='cmp-Input' and @placeholder='Select a country or region'] | K19: 0 | L19: Write | M19: Destination
A20: bln680505 | B20: =COUNTA($B$1:B19) -> 17 | C20: Wait | G20: Owner Advantage | L20: Wait | M20: 2
A21: bln680505 | B21: =COUNTA($B$1:B20) -> 18 | C21: Click Destination | G21: Owner Advantage | I21: xpath | J21: ="//a[contains(.,'"&M19&"')]" -> //a[contains(.,'Destination')] | K21: 0 | L21: js_click
A22: bln680505 | B22: =COUNTA($B$1:B21) -> 19 | C22: Departure Date | G22: Owner Advantage | I22: xpath | J22: //input[@name='tripDepartureDate'] | K22: 0 | L22: Set | M22: DepDate
A23: bln680505 | B23: =COUNTA($B$1:B22) -> 20 | C23: Return Date | G23: Owner Advantage | I23: xpath | J23: //input[@name='tripReturnDate'] | K23: 0 | L23: Set | M23: RetDate
A24: bln680505 | B24: =COUNTA($B$1:B23) -> 21 | C24: Deposit Date | G24: Owner Advantage | I24: xpath | J24: //input[@name='tripDepositDate'] | K24: 0 | L24: Set | M24: DepoDate
A25: bln680505 | B25: =COUNTA($B$1:B24) -> 22 | C25: Click State | G25: Owner Advantage | I25: xpath | J25: //input[@id='cmp-Input' and @placeholder='Select your state'] | K25: 0 | L25: Click
A26: bln680505 | B26: =COUNTA($B$1:B25) -> 23 | C26: Wait | G26: Owner Advantage | L26: Wait | M26: 2
A27: bln680505 | B27: =COUNTA($B$1:B26) -> 24 | C27: Write State | G27: Owner Advantage | I27: xpath | J27: //input[@id='cmp-Input' and @placeholder='Select your state'] | K27: 0 | L27: Write | M27: Residence
A28: bln680505 | B28: =COUNTA($B$1:B27) -> 25 | C28: Wait | G28: Owner Advantage | L28: Wait | M28: 2
A29: bln680505 | B29: =COUNTA($B$1:B28) -> 26 | C29: Click Destination | G29: Owner Advantage | I29: xpath | J29: ="//a[contains(.,'"&M27&"')]" -> //a[contains(.,'Residence')] | K29: 0 | L29: js_click
A30: bln680505 | B30: =COUNTA($B$1:B29) -> 27 | C30: Enter Age | G30: Owner Advantage | I30: xpath | J30: (//input[@name='insuredAge'])[1] | K30: 0 | L30: Set | M30: Age
A31: bln680505 | B31: =COUNTA($B$1:B30) -> 28 | C31: Enter Trip Cost | G31: Owner Advantage | I31: xpath | J31: (//input[@name='display_tripCost'])[1] | K31: 0 | L31: Set | M31: Cost
A32: N | B32: =COUNTA($B$1:B31) -> 29 | C32: Click Add | G32: Owner Advantage | I32: xpath | J32: //button[@id='add-container-button__1'] | K32: 0 | L32: js_click
A33: N | B33: =COUNTA($B$1:B32) -> 30 | C33: Enter Age1 | G33: Owner Advantage | I33: xpath | J33: (//input[@name='insuredAge'])[2] | K33: 0 | L33: Set | M33: Age1
A34: N | B34: =COUNTA($B$1:B33) -> 31 | C34: Enter Trip Cost1 | G34: Owner Advantage | I34: xpath | J34: (//input[@name='display_tripCost'])[2] | K34: 0 | L34: Set | M34: Cost1
A35: N | B35: =COUNTA($B$1:B34) -> 32 | C35: Click Add | G35: Owner Advantage | I35: xpath | J35: //button[@id='add-container-button__2'] | K35: 0 | L35: js_click
A36: N | B36: =COUNTA($B$1:B35) -> 33 | C36: Enter Age2 | G36: Owner Advantage | I36: xpath | J36: (//input[@name='insuredAge'])[3] | K36: 0 | L36: Set | M36: Age2
A37: N | B37: =COUNTA($B$1:B36) -> 34 | C37: Enter Trip Cost2 | G37: Owner Advantage | I37: xpath | J37: (//input[@name='display_tripCost'])[3] | K37: 0 | L37: Set | M37: Cost2
A38: N | B38: =COUNTA($B$1:B37) -> 35 | C38: Click Add | G38: Owner Advantage | I38: xpath | J38: //button[@id='add-container-button__3'] | K38: 0 | L38: js_click
A39: N | B39: =COUNTA($B$1:B38) -> 36 | C39: Enter Age3 | G39: Owner Advantage | I39: xpath | J39: (//input[@name='insuredAge'])[4] | K39: 0 | L39: Set | M39: Age3
A40: N | B40: =COUNTA($B$1:B39) -> 37 | C40: Enter Trip Cost3 | G40: Owner Advantage | I40: xpath | J40: (//input[@name='display_tripCost'])[4] | K40: 0 | L40: Set | M40: Cost3
A41: bln680505 | B41: =COUNTA($B$1:B40) -> 38 | C41: Click Submit button | G41: Owner Advantage | I41: xpath | J41: //button[@type='SUBMIT'] | K41: 0 | L41: js_click
A42: bln680505 | B42: =COUNTA($B$1:B41) -> 39 | C42: Wait | G42: Owner Advantage | L42: Wait | M42: 10
A43: Plan Option and Upgrades
A44: bln680505 | B44: =COUNTA($B$1:B43) -> 40 | C44: Check Exist | G44: Owner Advantage | I44: xpath | J44: //button[text()='Accept All Cookies'] | L44: Exist | O44: Y
A45: bln680505 | B45: =COUNTA($B$1:B44) -> 41 | C45: Output Cookie | G45: Owner Advantage | I45: xpath | J45: //button[text()='Accept All Cookies'] | L45: Output | N45: innertext | O45: Y | R45: Accept All Cookies
A46: bln680505 | B46: =COUNTA($B$1:B45) -> 42 | C46: Cookies | G46: Owner Advantage | I46: xpath | J46: //button[@id='onetrust-accept-btn-handler'] | L46: js_click | O46: Y
A47: bln680505 | B47: =COUNTA($B$1:B46) -> 43 | C47: Click Summary DropDown | G47: Owner Advantage | I47: xpath | J47: //button[@id='my-trip-accordion-item-85f740dcaf-button'] | L47: Click
A48: bln680505 | B48: =COUNTA($B$1:B47) -> 44 | C48: Rental Car Damage Plan | G48: Owner Advantage | I48: xpath | J48: //button[@name='selectPlan' and @value='MRCDZ-0925'] | K48: 0 | L48: js_click
A49: bln680505 | B49: =COUNTA($B$1:B48) -> 45 | C49: Wait | G49: Owner Advantage | L49: Wait | M49: 10
A50: Travelers Information
A51: bln680505 | B51: =COUNTA($B$1:B50) -> 46 | C51: Check Exist | G51: Owner Advantage | I51: xpath | J51: //button[text()='Accept All Cookies'] | L51: Exist | O51: Y
A52: bln680505 | B52: =COUNTA($B$1:B51) -> 47 | C52: Output Cookie | G52: Owner Advantage | I52: xpath | J52: //button[text()='Accept All Cookies'] | L52: Output | N52: innertext | O52: Y | R52: Accept All Cookies
A53: bln680505 | B53: =COUNTA($B$1:B52) -> 48 | C53: Cookies | G53: Owner Advantage | I53: xpath | J53: //button[@id='onetrust-accept-btn-handler'] | L53: js_click | O53: Y
A54: bln680505 | B54: =COUNTA($B$1:B53) -> 49 | C54: Enter First Name | G54: Owner Advantage | I54: xpath | J54: //input[@name='firstName'] | K54: 0 | L54: Set | M54: FirstName
A55: bln680505 | B55: =COUNTA($B$1:B54) -> 50 | C55: Enter Last Name | G55: Owner Advantage | I55: xpath | J55: //input[@name='lastName'] | K55: 0 | L55: Set | M55: LastName
A56: bln680505 | B56: =COUNTA($B$1:B55) -> 51 | C56: Enter Birth Date | G56: Owner Advantage | I56: xpath | J56: //input[@name='dateOfBirth'] | K56: 0 | L56: Set | M56: BirthDate
A57: bln680505 | B57: =COUNTA($B$1:B56) -> 52 | C57: Click tab | G57: Owner Advantage | L57: SendKeys | M57: {TAB}
A58: bln680505 | B58: =COUNTA($B$1:B57) -> 53 | C58: Wait | G58: Owner Advantage | L58: Wait | M58: 3
A59: bln680505 | B59: =COUNTA($B$1:B58) -> 54 | C59: Enter Address | G59: Owner Advantage | I59: xpath | J59: //input[@name='address1'] | K59: 0 | L59: Set | M59: Address
A60: bln680505 | B60: =COUNTA($B$1:B59) -> 55 | C60: Enter City | G60: Owner Advantage | I60: xpath | J60: //input[@name='city'] | K60: 0 | L60: Set | M60: City
A61: bln680505 | B61: =COUNTA($B$1:B60) -> 56 | C61: Enter Zip Code | G61: Owner Advantage | I61: xpath | J61: //input[@name='postalCode'] | K61: 0 | L61: Set | M61: Zip
A62: bln680505 | B62: =COUNTA($B$1:B61) -> 57 | C62: Enter Phone | G62: Owner Advantage | I62: xpath | J62: //input[@name='dayPhone'] | K62: 0 | L62: Set | M62: Phone
A63: bln680505 | B63: =COUNTA($B$1:B62) -> 58 | C63: Enter Email | G63: Owner Advantage | I63: xpath | J63: //input[@name='email'] | K63: 0 | L63: Set | M63: Email
A64: bln680505 | B64: =COUNTA($B$1:B63) -> 59 | C64: Enter Owner Number | G64: Owner Advantage | I64: xpath | J64: //input[@name='ownerNumber'] | K64: 0 | L64: Set | M64: OwnerPhone
A65: bln680505 | B65: =COUNTA($B$1:B64) -> 60 | C65: Click Submit button | G65: Owner Advantage | I65: xpath | J65: //button[@type='SUBMIT'] | K65: 0 | L65: js_click
A66: bln680505 | B66: =COUNTA($B$1:B65) -> 61 | C66: Wait | G66: Owner Advantage | L66: Wait | M66: 10
A67: Payment
A68: bln680505 | B68: =COUNTA($B$1:B67) -> 62 | C68: Check Exist | G68: Owner Advantage | I68: xpath | J68: //button[text()='Accept All Cookies'] | L68: Exist | O68: Y
A69: bln680505 | B69: =COUNTA($B$1:B68) -> 63 | C69: Output Cookie | G69: Owner Advantage | I69: xpath | J69: //button[text()='Accept All Cookies'] | L69: Output | N69: innertext | O69: Y | R69: Accept All Cookies
A70: bln680505 | B70: =COUNTA($B$1:B69) -> 64 | C70: Cookies | G70: Owner Advantage | I70: xpath | J70: //button[@id='onetrust-accept-btn-handler'] | L70: js_click | O70: Y
A71: bln680505 | B71: =COUNTA($B$1:B70) -> 65 | C71: Enter Card Name | G71: Owner Advantage | I71: xpath | J71: //input[@name='cardName'] | K71: 0 | L71: Set | M71: CardName
A72: bln680505 | B72: =COUNTA($B$1:B71) -> 66 | C72: Change iFrame | G72: Owner Advantage | K72: 2 | L72: switchtoframe
A73: bln680505 | B73: =COUNTA($B$1:B72) -> 67 | C73: Enter Card Number | G73: Owner Advantage | I73: xpath | J73: //input[@name='tsep-cardNum'] | K73: 0 | L73: Set | M73: CardNumber
A74: bln680505 | B74: =COUNTA($B$1:B73) -> 68 | C74: Change iFrame | G74: Owner Advantage | K74: 0 | L74: switchtodefault
A75: bln680505 | B75: =COUNTA($B$1:B74) -> 69 | C75: Change iFrame | G75: Owner Advantage | K75: 2 | L75: switchtoframe
A76: N | B76: =COUNTA($B$1:B75) -> 70 | C76: Click tab | G76: Owner Advantage | L76: SendKeys | M76: {TAB}
A77: N | B77: =COUNTA($B$1:B76) -> 71 | C77: Enter Card Expiry Month | G77: Owner Advantage | L77: SendKeys | M77: ExpiryMonth
A78: N | B78: =COUNTA($B$1:B77) -> 72 | C78: Enter Card Expiry Year | G78: Owner Advantage | L78: SendKeys | M78: ExpiryYear
A79: N | B79: =COUNTA($B$1:B78) -> 73 | C79: Click tab | G79: Owner Advantage | L79: SendKeys | M79: {TAB}
A80: bln680505 | B80: =COUNTA($B$1:B79) -> 74 | C80: Click Expiry Date | G80: Owner Advantage | I80: xpath | J80: //input[@name='tsep-datepicker'] | K80: 0 | L80: Click
A81: bln680505 | B81: =COUNTA($B$1:B80) -> 75 | C81: Wait | G81: Owner Advantage | L81: Wait | M81: 2
A82: bln680505 | B82: =COUNTA($B$1:B81) -> 76 | C82: Input Expiry Month | G82: Owner Advantage | I82: xpath | J82: //input[@name='tsep-datepicker'] | K82: 0 | L82: Type | M82: ExpiryMonth
A83: bln680505 | B83: =COUNTA($B$1:B82) -> 77 | C83: Input Expiry Year | G83: Owner Advantage | I83: xpath | J83: //input[@name='tsep-datepicker'] | K83: 0 | L83: Type | M83: ExpiryYear
A84: bln680505 | B84: =COUNTA($B$1:B83) -> 78 | C84: Wait | G84: Owner Advantage | L84: Wait | M84: 2
A85: bln680505 | B85: =COUNTA($B$1:B84) -> 79 | C85: Change iFrame | G85: Owner Advantage | K85: 0 | L85: switchtodefault
A86: bln680505 | B86: =COUNTA($B$1:B85) -> 80 | C86: Wait | G86: Owner Advantage | L86: Wait | M86: 10
A87: Edit Quote/Restart
A88: bln680505 | B88: =COUNTA($B$1:B87) -> 81 | C88: Click Get Quote | G88: Owner Advantage | I88: xpath | J88: //a[contains(.,'Get Quote')] | K88: 0 | L88: js_click
A89: bln680505 | B89: =COUNTA($B$1:B88) -> 82 | C89: Click Destination | G89: Owner Advantage | I89: xpath | J89: (//input[@id='cmp-Input' and @class='inputField'])[1] | K89: 0 | L89: Click
A90: bln680505 | B90: =COUNTA($B$1:B89) -> 83 | C90: Wait | G90: Owner Advantage | L90: Wait | M90: 2
A91: bln680505 | B91: =COUNTA($B$1:B90) -> 84 | C91: Write Destination | G91: Owner Advantage | I91: xpath | J91: (//input[@id='cmp-Input' and @class='inputField'])[1] | K91: 0 | L91: Write | M91: Destination1
A92: bln680505 | B92: =COUNTA($B$1:B91) -> 85 | C92: Wait | G92: Owner Advantage | L92: Wait | M92: 2
A93: bln680505 | B93: =COUNTA($B$1:B92) -> 86 | C93: Click Destination | G93: Owner Advantage | I93: xpath | J93: ="//a[contains(.,'"&M91&"')]" -> //a[contains(.,'Destination1')] | K93: 0 | L93: js_click
A94: bln680505 | B94: =COUNTA($B$1:B93) -> 87 | C94: Departure Date | G94: Owner Advantage | I94: xpath | J94: //input[@name='tripDepartureDate'] | K94: 0 | L94: Set | M94: DepDateValid
A95: bln680505 | B95: =COUNTA($B$1:B94) -> 88 | C95: Return Date | G95: Owner Advantage | I95: xpath | J95: //input[@name='tripReturnDate'] | K95: 0 | L95: Set | M95: RetDateValid
A96: bln680505 | B96: =COUNTA($B$1:B95) -> 89 | C96: Deposit Date | G96: Owner Advantage | I96: xpath | J96: //input[@name='tripDepositDate'] | K96: 0 | L96: Set | M96: DepoDate
A97: bln680505 | B97: =COUNTA($B$1:B96) -> 90 | C97: Click State | G97: Owner Advantage | I97: xpath | J97: (//input[@id='cmp-Input' and @class='inputField'])[2] | K97: 0 | L97: Click
A98: bln680505 | B98: =COUNTA($B$1:B97) -> 91 | C98: Wait | G98: Owner Advantage | L98: Wait | M98: 2
A99: bln680505 | B99: =COUNTA($B$1:B98) -> 92 | C99: Write State | G99: Owner Advantage | I99: xpath | J99: (//input[@id='cmp-Input' and @class='inputField'])[2] | K99: 0 | L99: Write | M99: Residence1
A100: bln680505 | B100: =COUNTA($B$1:B99) -> 93 | C100: Wait | G100: Owner Advantage | L100: Wait | M100: 2
...

Sheet Params_2
A1: Scenario | B1: blnExecute | C1: bln_TG | D1: blnQuit | E1: bln680505 | F1: DT_BrowserType | G1: Notes | H1: DT_URL | I1: DateToday | J1: PolicyNumber_OUT | K1: tripType | L1: Plan | M1: Destination | N1: Restricted | O1: Destination1 | P1: Destination2 | Q1: Destination3 | R1: Destination4 | S1: Destination5 | T1: Destination6 | U1: Destination7 | V1: Destination8 | W1: Destination9 | X1: Destination10 | Y1: Destination11 | Z1: Destination12 | AA1: Destination13 | AB1: Destination14 | AC1: Destination15 | AD1: Destination16 | AE1: Destination17 | AF1: Destination18 | AG1: Destination19 | AH1: Destination20 | AI1: Destination21 | AJ1: Destination22 | AK1: Destination23 | AL1: Destination24 | AM1: Destination25 | AN1: Destination26 | AO1: Destination27 | AP1: Destination28 | AQ1: Destination29 | AR1: Destination30 | AS1: Destination31 | AT1: Destination32 | AU1: Destination33 | AV1: DepDate | AW1: DepDate1 | AX1: DepDateValid | AY1: RetDate | AZ1: RetDate1 | BA1: RetDateValid | BB1: DepoDate | BC1: DepoYearInvalid | BD1: DepoYearValid | BE1: DepoMonthInvalid | BF1: DepoMonthValid | BG1: DepoDayInvalid | BH1: DepoDayValid | BI1: Residence | BJ1: Residence1 | BK1: Residence2 | BL1: Residence3 | BM1: Residence4 | BN1: Residence5 | BO1: Residence6 | BP1: Residence7 | BQ1: Residence8 | BR1: Residence9 | BS1: Residence10 | BT1: Residence11 | BU1: Residence12 | BV1: Residence13 | BW1: Residence14 | BX1: Residence15 | BY1: Residence16 | BZ1: Residence17 | CA1: Residence18 | CB1: Residence19 | CC1: Residence20 | CD1: Residence21 | CE1: Residence22 | CF1: Residence23 | CG1: Residence24 | CH1: Residence25 | CI1: Residence26 | CJ1: Residence27 | CK1: Residence28 | CL1: Residence29 | CM1: Residence30 | CN1: Residence31 | CO1: Residence32 | CP1: Residence33 | CQ1: Residence34 | CR1: Residence35 | CS1: Residence36 | CT1: Residence37 | CU1: Residence38 | CV1: Residence39 | CW1: Residence40 | CX1: Residence41 | CY1: Residence42 | CZ1: Residence43 | DA1: Residence44 | DB1: Residence45 | DC1: Residence46 | DD1: Residence47 | DE1: Residence48 | DF1: Residence49 | DG1: Residence50 | DH1: Residence51 | DI1: Residence52 | DJ1: Residence53 | DK1: Age | DL1: Cost | DM1: CostAllowed | DN1: Age1 | DO1: Cost1 | DP1: Trav_FirstName1 | DQ1: Trav_LastName1 | DR1: Trav_BirthDate1 | DS1: Age2 | DT1: Cost2 | DU1: Trav_FirstName2 | DV1: Trav_LastName2 | DW1: Trav_BirthDate2 | DX1: Age3 | DY1: Cost3 | DZ1: Trav_FirstName3 | EA1: Trav_LastName3 | EB1: Trav_BirthDate3 | EC1: Age4 | ED1: Cost4 | EE1: Trav_FirstName4 | EF1: Trav_LastName4 | EG1: Trav_BirthDate4 | EH1: Age5 | EI1: Cost5 | EJ1: Trav_FirstName5 | EK1: Trav_LastName5 | EL1: Trav_BirthDate5 | EM1: Age6 | EN1: Cost6 | EO1: Trav_FirstName6 | EP1: Trav_LastName6 | EQ1: Trav_BirthDate6 | ER1: Age7 | ES1: Cost7 | ET1: Trav_FirstName7 | EU1: Trav_LastName7 | EV1: Trav_BirthDate7 | EW1: Age8 | EX1: Cost8 | EY1: Trav_FirstName8 | EZ1: Trav_LastName8 | FA1: Trav_BirthDate8 | FB1: Age9 | FC1: Cost9 | FD1: Trav_FirstName9 | FE1: Trav_LastName9 | FF1: Trav_BirthDate9 | FG1: PickUpDate | FH1: DropOffDate | FI1: PickUpDate1 | FJ1: DropOffDate1 | FK1: PickUpDate2 | FL1: DropOffDate2 | FM1: PickUpDate3 | FN1: DropOffDate3 | FO1: PickUpDate4 | FP1: DropOffDate4 | FQ1: FirstName | FR1: LastName | FS1: BirthDate | FT1: BirthDateInvalid | FU1: BirthDate1 | FV1: Address | FW1: City | FX1: Zip | FY1: ZipX | FZ1: City1 | GA1: Zip1 | GB1: Phone | GC1: Phone1 | GD1: Email | GE1: Email1 | GF1: OwnerPhone | GG1: CardName | GH1: CardNumber | GI1: CardNumber1 | GJ1: ExpiryMonth | GK1: ExpiryYear | GL1: Cost_OUT | GM1: Cost_RES | GN1: Destination_OUT | GO1: Destination_RES | GP1: Plan | GQ1: Plan_OUT | GR1: Plan_RES | GS1: Plan1 | GT1: Plan1_OUT | GU1: Plan_RES | GV1: Plan2 | GW1: Plan2_OUT | GX1: Plan_RES | GY1: ErrorMessage | GZ1: ErrorMessage_OUT | HA1: ErrorMessage_RES | HB1: ErrorMessage1 | HC1: ErrorMessage1_OUT | HD1: ErrorMessage_RES | HE1: ErrorMessage2 | HF1: ErrorMessage2_OUT | HG1: ErrorMessage_RES | HH1: ErrorMessage3 | HI1: ErrorMessage3_OUT | HJ1: ErrorMessage_RES | HK1: Tooltip | HL1: Tooltip_OUT | HM1: Tooltip_RES | HN1: Tooltip1 | HO1: Tooltip1_OUT | HP1: Tooltip1_RES | HQ1: Tooltip2 | HR1: Tooltip2_OUT | HS1: Tooltip2_RES | HT1: FAQ1 | HU1: FAQ1_OUT | HV1: FAQ1_RES | HW1: FAQ2 | HX1: FAQ2_OUT | HY1: FAQ2_RES | HZ1: FAQ3 | IA1: FAQ3_OUT | IB1: FAQ3_RES | IC1: FAQ4 | ID1: FAQ4_OUT | IE1: FAQ4_RES | IF1: FAQ5 | IG1: FAQ5_OUT | IH1: FAQ5_RES | II1: OwnerAdvantagePlan_OUT | IJ1: RentalCarDamagePlan_OUT | IK1: OwnerAdvantagePlan_VERIFY | IL1: RentalCarDamage_VERIFY
A2: bln680505 | B2: Y | C2: Y | D2: Y | E2: Y | F2: Chrome | G2: TC_680505 | H2: {=_xlfn.IFS(Global!B2="QA","https://owneradvantage.qa.insurancebytravelex.com/",Global!B2="UAT","https://owneradvantage.uat.insurancebytravelex.com/",Global!B2="PROD","https://owneradvantage.insurancebytravelex.com/")} -> https://owneradvantage.uat.insurancebytravelex.com/ | I2: =TODAY() -> 46266 | K2: Comprehensive Coverage | L2: Rental Car Damage Plan | M2: Singapore | O2: Australia | AV2: =TEXT(I2+1,"mm/dd/yyyy") -> 09/02/2026 | AW2: =TEXT(I2+7,"mm/dd/yyyy") -> 09/08/2026 | AX2: =TEXT(I2+7,"mm/dd/yyyy") -> 09/08/2026 | AY2: =TEXT(AV2+89,"mm/dd/yyyy") -> 11/30/2026 | AZ2: =TEXT(AW2+15,"mm/dd/yyyy") -> 09/23/2026 | BA2: =TEXT(AV2+21,"mm/dd/yyyy") -> 09/23/2026 | BB2: =TEXT(I2-1,"mm/dd/yyyy") -> 08/31/2026 | BI2: California | BJ2: Nebraska | BK2: New York | DK2: 110 | DL2: 1000 | DM2: 100 | DN2: 18 | DO2: 1500 | DP2: ="QAFIRSTNAME"&CHAR(RANDBETWEEN(65,90))&CHAR(RANDBETWEEN(65,90)) -> QAFIRSTNAMEFS | DQ2: ="QALASTNAME"&CHAR(RANDBETWEEN(65,90))&CHAR(RANDBETWEEN(65,90)) -> QALASTNAMEHD | DR2: =TEXT(DATE(YEAR(TODAY())-DS2,MONTH(TODAY()),DAY(TODAY())),"MM/DD/YYYY") -> 09/01/2026 | FG2: =TEXT(AV2,"mm/dd/yyyy") -> 09/02/2026 | FH2: =TEXT(AV2+1,"mm/dd/yyyy") -> 09/03/2026 | FI2: =TEXT(FH2+1,"mm/dd/yyyy") -> 09/04/2026 | FJ2: =TEXT(FI2+1,"mm/dd/yyyy") -> 09/05/2026 | FK2: =TEXT(FJ2+1,"mm/dd/yyyy") -> 09/06/2026 | FL2: =TEXT(FK2+1,"mm/dd/yyyy") -> 09/07/2026 | FM2: =TEXT(FL2+7,"mm/dd/yyyy") -> 09/14/2026 | FN2: =TEXT(FM2+1,"mm/dd/yyyy") -> 09/15/2026 | FO2: =TEXT(FN2+1,"mm/dd/yyyy") -> 09/16/2026 | FP2: =TEXT(FO2+1,"mm/dd/yyyy") -> 09/17/2026 | FQ2: ="QAFIRSTNAME"&CHAR(RANDBETWEEN(65,90))&CHAR(RANDBETWEEN(65,90)) -> QAFIRSTNAMEBL | FR2: ="QALASTNAME"&CHAR(RANDBETWEEN(65,90))&CHAR(RANDBETWEEN(65,90)) -> QALASTNAMEJA | FS2: =TEXT(DATE(YEAR(TODAY())-DK2,MONTH(TODAY()),DAY(TODAY())),"MM/DD/YYYY") -> 09/01/1916 | FU2: =TEXT(DATE(YEAR(TODAY())-DN2,MONTH(TODAY()),DAY(TODAY())),"MM/DD/YYYY") -> 09/01/2008 | FV2: QA213 COR246 | FW2: Los Angeles | FX2: 90001 | FY2: 12345 | FZ2: Omaha | GA2: 68102 | GB2: 1234567897 | GC2: 2222222222 | GD2: qa@travelexinsurance.com | GE2: qa@travelguard.com | GF2: qwertyuiopasdfgh | GG2: QA Test | GH2: 4111111111111111 | GJ2: 12 | GK2: 2030 | GM2: =IF(DL2=GL2,"PASSED","FAILED") -> FAILED

Sheet Owner_RVD
A1: blnExecute | B1: Step_Number | C1: Step_Name | D1: Status | E1: Error_Check | F1: breakpoint | G1: Test_Case | H1: Page | I1: FindBy | J1: FindBy_Value | K1: Index | L1: Method | M1: Value | N1: Output_Property | O1: Ignore_not_existing_object | P1: isDisabled | Q1: Timeout | R1: Expected_Value | S1: Output_Value | T1: Exact_Match | U1: Contains | V1: ITERATION_NO | W1: Notes | X1: Start_Time | Y1: End_Time | Z1: Duration
A2: Open Owner Advantage URL
A3: =IF(OR(Global!B25="N"),"N","bln678042") -> N | B3: =COUNTA($B$1:B2) -> 1 | C3: Open Browser | G3: Owner Advantage | L3: Wait | M3: 1 | O3: Y | R3: DT_URL
A4: =IF(OR(Global!B25="N"),"N","bln678042") -> N | B4: =COUNTA($B$1:B3) -> 2 | C4: Headless | G4: Owner Advantage | H4: DT_BrowserType | L4: Open | M4: ="URL:="&R3&";;HEADLESS:=TRUE" -> URL:=DT_URL;;HEADLESS:=TRUE | Q4: 60
A5: =IF(OR(Global!B25="Y"),"N","bln678042") -> bln678042 | B5: =COUNTA($B$1:B4) -> 3 | C5: Open Browser | G5: Owner Advantage | H5: DT_BrowserType | L5: Open | M5: DT_URL | Q5: 60
A6: N | B6: =COUNTA($B$1:B5) -> 4 | C6: Wait | G6: Owner Advantage | L6: Wait | M6: 5
A7: N | B7: =COUNTA($B$1:B6) -> 5 | C7: Zscaler Sign in Email | G7: Owner Advantage | I7: xpath | J7: //input[@id='okta-signin-username'] | K7: 0 | L7: Set | M7: DT_ZScalerUser | O7: Y | Q7: 5
A8: N | B8: =COUNTA($B$1:B7) -> 6 | C8: Zscaler Password | G8: Owner Advantage | I8: xpath | J8: //input[@id='okta-signin-password'] | K8: 0 | L8: Set | M8: DT_ZScalerPassword | O8: Y
A9: N | B9: =COUNTA($B$1:B8) -> 7 | C9: Click Sign in | G9: Owner Advantage | I9: xpath | J9: //input[@id='okta-signin-submit'] | K9: 0 | L9: Click | O9: Y
A10: N | B10: =COUNTA($B$1:B9) -> 8 | C10: Wait | G10: Owner Advantage | L10: Wait | M10: 5
A11: Quote - Home Page
A12: bln678042 | B12: =COUNTA($B$1:B11) -> 9 | C12: Switch to Frame | G12: Owner Advantage | L12: SWITCHTOFRAME | M12: aemFormFrame | W12: tripType
A13: bln678042 | B13: =COUNTA($B$1:B12) -> 10 | C13: Check Exist | G13: Owner Advantage | I13: xpath | J13: //button[text()='Accept All Cookies'] | L13: Exist | O13: Y
A14: =IF($D$13="PASSED","bln678042","N") -> N | B14: =COUNTA($B$1:B13) -> 11 | C14: Output Cookie | G14: Owner Advantage | I14: xpath | J14: //button[text()='Accept All Cookies'] | K14: 0 | L14: Output | N14: innertext | O14: Y | R14: Accept All Cookies
A15: =A14 -> N | B15: =COUNTA($B$1:B14) -> 12 | C15: Cookies | G15: Owner Advantage | I15: xpath | J15: //button[@id='onetrust-accept-btn-handler'] | K15: 0 | L15: js_click | O15: Y
A16: bln678042 | B16: =COUNTA($B$1:B15) -> 13 | C16: Select Trip Type | G16: Owner Advantage | I16: xpath | J16: ="//label[contains(.,'"&W12&"')]" -> //label[contains(.,'tripType')] | K16: 0 | L16: js_click
A17: bln678042 | B17: =COUNTA($B$1:B16) -> 14 | C17: Click Destination | G17: Owner Advantage | I17: xpath | J17: //input[@id='cmp-Input' and @placeholder='Select a country or region'] | K17: 0 | L17: Click
A18: bln678042 | B18: =COUNTA($B$1:B17) -> 15 | C18: Wait | G18: Owner Advantage | L18: Wait | M18: 2
A19: bln678042 | B19: =COUNTA($B$1:B18) -> 16 | C19: Write Destination | G19: Owner Advantage | I19: xpath | J19: //input[@id='cmp-Input' and @placeholder='Select a country or region'] | K19: 0 | L19: Write | M19: Destination
A20: bln678042 | B20: =COUNTA($B$1:B19) -> 17 | C20: Wait | G20: Owner Advantage | L20: Wait | M20: 2
A21: bln678042 | B21: =COUNTA($B$1:B20) -> 18 | C21: Click Destination | G21: Owner Advantage | I21: xpath | J21: ="//a[contains(.,'"&M19&"')]" -> //a[contains(.,'Destination')] | K21: 0 | L21: js_click
A22: bln678042 | B22: =COUNTA($B$1:B21) -> 19 | C22: Departure Date | G22: Owner Advantage | I22: xpath | J22: //input[@name='tripDepartureDate'] | K22: 0 | L22: Set | M22: DepDate
A23: bln678042 | B23: =COUNTA($B$1:B22) -> 20 | C23: Return Date | G23: Owner Advantage | I23: xpath | J23: //input[@name='tripReturnDate'] | K23: 0 | L23: Set | M23: RetDate
A24: bln678042 | B24: =COUNTA($B$1:B23) -> 21 | C24: Deposit Date | G24: Owner Advantage | I24: xpath | J24: //input[@name='tripDepositDate'] | K24: 0 | L24: Set | M24: DepoDate
A25: bln678042 | B25: =COUNTA($B$1:B24) -> 22 | C25: Click State | G25: Owner Advantage | I25: xpath | J25: //input[@id='cmp-Input' and @placeholder='Select your state'] | K25: 0 | L25: Click
A26: bln678042 | B26: =COUNTA($B$1:B25) -> 23 | C26: Wait | G26: Owner Advantage | L26: Wait | M26: 2
A27: bln678042 | B27: =COUNTA($B$1:B26) -> 24 | C27: Write State | G27: Owner Advantage | I27: xpath | J27: //input[@id='cmp-Input' and @placeholder='Select your state'] | K27: 0 | L27: Write | M27: Residence
A28: bln678042 | B28: =COUNTA($B$1:B27) -> 25 | C28: Wait | G28: Owner Advantage | L28: Wait | M28: 2
A29: bln678042 | B29: =COUNTA($B$1:B28) -> 26 | C29: Click Destination | G29: Owner Advantage | I29: xpath | J29: ="//a[contains(.,'"&M27&"')]" -> //a[contains(.,'Residence')] | K29: 0 | L29: js_click
A30: bln678042 | B30: =COUNTA($B$1:B29) -> 27 | C30: Click Submit button | G30: Owner Advantage | I30: xpath | J30: //button[@type='SUBMIT'] | K30: 0 | L30: js_click
A31: bln678042 | B31: =COUNTA($B$1:B30) -> 28 | C31: Wait | G31: Owner Advantage | L31: Wait | M31: 10
A32: Plan Option and Upgrades
A33: bln678042 | B33: =COUNTA($B$1:B32) -> 29 | C33: Check Exist | G33: Owner Advantage | I33: xpath | J33: //button[text()='Accept All Cookies'] | L33: Exist | O33: Y
A34: =IF($D$33="PASSED","bln678042","N") -> N | B34: =COUNTA($B$1:B33) -> 30 | C34: Output Cookie | G34: Owner Advantage | I34: xpath | J34: //button[text()='Accept All Cookies'] | K34: 0 | L34: Output | N34: innertext | O34: Y | R34: Accept All Cookies
A35: =A34 -> N | B35: =COUNTA($B$1:B34) -> 31 | C35: Cookies | G35: Owner Advantage | I35: xpath | J35: //button[@id='onetrust-accept-btn-handler'] | K35: 0 | L35: js_click | O35: Y
A36: bln678042 | B36: =COUNTA($B$1:B35) -> 32 | C36: Click the My Trip dropdown next to the total premium | G36: Owner Advantage | I36: xpath | J36: (//button[@type='button'])[2] | K36: 0 | L36: js_click
A37: =IF(Global!B2="QA","Y","N") -> N | B37: =COUNTA($B$1:B36) -> 33 | C37: Verify the displayed Destination | G37: Owner Advantage | I37: xpath | J37: //div[@class='cmp-text']//span[contains(@class,'destinationCountry_multi_display')] | K37: 0 | L37: Output | N37: innertext | R37: =TEXT(M19,"0") -> Destination | T37: Y
A38: =A37 -> N | B38: =COUNTA($B$1:B37) -> 34 | C38: Verify the displayed Trip Dates match the selected Departure Date | G38: Owner Advantage | I38: xpath | J38: (//div[@class='cmp-text']//span[contains(@class,'tripDepartureDate')])[1] | K38: 0 | L38: Output | N38: innertext | R38: =TEXT(M22,"mm/dd/yyyy") -> DepDate | T38: Y
A39: =A38 -> N | B39: =COUNTA($B$1:B38) -> 35 | C39: Verify the displayed Trip Dates match the selected Return Dates | G39: Owner Advantage | I39: xpath | J39: (//div[@class='cmp-text']//span[contains(@class,'tripReturnDate')])[1] | K39: 0 | L39: Output | N39: innertext | R39: =TEXT(M23,"mm/dd/yyyy") -> RetDate | T39: Y
A40: =A39 -> N | B40: =COUNTA($B$1:B39) -> 36 | C40: Select Rental Car Damage Plan | G40: Owner Advantage | I40: xpath | J40: //button[@name='selectPlan' and @value='MRCDZ-0925'] | K40: 0 | L40: js_click
A41: =IF(OR(Global!B2="UAT",Global!B2="PROD"),"Y","N") -> Y | B41: =COUNTA($B$1:B40) -> 37 | C41: Verify the displayed Destination | G41: Owner Advantage | I41: xpath | J41: //span[contains(@class,'destinationCountry_multi_display')] | K41: 0 | L41: Output | N41: innertext | R41: =TEXT(M19,"0") -> Destination | T41: Y
A42: =A41 -> Y | B42: =COUNTA($B$1:B41) -> 38 | C42: Verify the displayed Trip Dates match the selected Departure Date | G42: Owner Advantage | I42: xpath | J42: //span[contains(@class,'tripDepartureDate')] | K42: 0 | L42: Output | N42: innertext | R42: =TEXT(M22,"mm/dd/yyyy") -> DepDate | T42: Y
A43: =A42 -> Y | B43: =COUNTA($B$1:B42) -> 39 | C43: Verify the displayed Trip Dates match the selected Return Dates | G43: Owner Advantage | I43: xpath | J43: //span[contains(@class,'tripReturnDate')] | K43: 0 | L43: Output | N43: innertext | R43: =TEXT(M23,"mm/dd/yyyy") -> RetDate | T43: Y
A44: =A43 -> Y | B44: =COUNTA($B$1:B43) -> 40 | C44: Select Rental Car Damage Plan | G44: Owner Advantage | I44: xpath | J44: //button[@name='selectPlan' and @value='MRCDZ-0925'] | K44: 0 | L44: js_click
A45: bln678042 | B45: =COUNTA($B$1:B40) -> 37 | C45: Wait | G45: Owner Advantage | L45: Wait | M45: 5
A46: Travelers Information
A47: bln678042 | B47: =COUNTA($B$1:B46) -> 42 | C47: Wait | G47: Owner Advantage | L47: Wait | M47: 5
A48: bln678042 | B48: =COUNTA($B$1:B47) -> 43 | C48: Check Exist | G48: Owner Advantage | I48: xpath | J48: //button[text()='Accept All Cookies'] | L48: Exist | O48: Y
A49: =IF($D$33="PASSED","bln678042","N") -> N | B49: =COUNTA($B$1:B48) -> 44 | C49: Output Cookie | G49: Owner Advantage | I49: xpath | J49: //button[text()='Accept All Cookies'] | K49: 0 | L49: Output | N49: innertext | O49: Y | R49: Accept All Cookies
A50: =A49 -> N | B50: =COUNTA($B$1:B49) -> 45 | C50: Cookies | G50: Owner Advantage | I50: xpath | J50: //button[@id='onetrust-accept-btn-handler'] | K50: 0 | L50: js_click | O50: Y
A51: bln678042 | B51: =COUNTA($B$1:B50) -> 46 | C51: Click the My Trip dropdown next to the total premium | G51: Owner Advantage | I51: xpath | J51: (//button[@type='button'])[1] | K51: 0 | L51: js_click
A52: =IF(Global!B2="QA","Y","N") -> N | B52: =COUNTA($B$1:B51) -> 47 | C52: Verify the displayed Destination | G52: Owner Advantage | I52: xpath | J52: //div[@class='cmp-text']//span[contains(@class,'destinationCountry_multi_display')] | K52: 0 | L52: Output | N52: innertext | R52: =TEXT(M19,"0") -> Destination | T52: Y
A53: =A52 -> N | B53: =COUNTA($B$1:B52) -> 48 | C53: Verify the displayed Trip Dates match the selected Departure Date | G53: Owner Advantage | I53: xpath | J53: (//div[@class='cmp-text']//span[contains(@class,'tripDepartureDate')])[1] | K53: 0 | L53: Output | N53: innertext | R53: =TEXT(M22,"mm/dd/yyyy") -> DepDate | T53: Y
A54: =A53 -> N | B54: =COUNTA($B$1:B53) -> 49 | C54: Verify the displayed Trip Dates match the selected Return Dates | G54: Owner Advantage | I54: xpath | J54: (//div[@class='cmp-text']//span[contains(@class,'tripReturnDate')])[1] | K54: 0 | L54: Output | N54: innertext | R54: =TEXT(M23,"mm/dd/yyyy") -> RetDate | T54: Y
A55: =A54 -> N | B55: =COUNTA($B$1:B54) -> 50 | C55: Verify the Selected Plan (Rental Car Damage Plan) | G55: Owner Advantage | I55: xpath | J55: (//div[@class='cmp-text']//span[contains(@class,'productName')])[1] | K55: 0 | L55: Output | N55: innertext | R55: Rental Car Damage Plan | T55: Y
A56: =A55 -> N | B56: =COUNTA($B$1:B55) -> 51 | C56: Verify the Selected Plan Amount | G56: Owner Advantage | I56: xpath | J56: //span[contains(@class,'selectedBaseRate-2') and contains(ancestor::p,'$')] | K56: 0 | L56: Output | N56: innertext
A57: =A56 -> N | B57: =COUNTA($B$1:B56) -> 52 | C57: Verify the displayed Total Amount | G57: Owner Advantage | I57: xpath | J57: //span[contains(@class,'totalBaseRate-2') and contains(ancestor::p,'$')] | K57: 0 | L57: Output | N57: innertext
A58: =IF(OR(Global!B2="UAT",Global!B2="PROD"),"Y","N") -> Y | B58: =COUNTA($B$1:B57) -> 53 | C58: Verify the displayed Destination | G58: Owner Advantage | I58: xpath | J58: //span[contains(@class,'destinationCountry_multi_display')] | K58: 0 | L58: Output | N58: innertext | R58: =TEXT(M19,"0") -> Destination | T58: Y
A59: =A58 -> Y | B59: =COUNTA($B$1:B58) -> 54 | C59: Verify the displayed Trip Dates match the selected Departure Date | G59: Owner Advantage | I59: xpath | J59: //span[contains(@class,'tripDepartureDate')] | K59: 0 | L59: Output | N59: innertext | R59: =TEXT(M22,"mm/dd/yyyy") -> DepDate | T59: Y
A60: =A59 -> Y | B60: =COUNTA($B$1:B59) -> 55 | C60: Verify the displayed Trip Dates match the selected Return Dates | G60: Owner Advantage | I60: xpath | J60: //span[contains(@class,'tripReturnDate')] | K60: 0 | L60: Output | N60: innertext | R60: =TEXT(M23,"mm/dd/yyyy") -> RetDate | T60: Y
A61: =A60 -> Y | B61: =COUNTA($B$1:B60) -> 56 | C61: Verify the Selected Plan (Rental Car Damage Plan) | G61: Owner Advantage | I61: xpath | J61: //span[contains(@class,'productName')] | K61: 0 | L61: Output | N61: innertext | R61: Rental Car Damage Plan | T61: Y
A62: =A61 -> Y | B62: =COUNTA($B$1:B61) -> 57 | C62: Verify the Selected Plan Amount | G62: Owner Advantage | I62: xpath | J62: //span[contains(@class,'selectedBaseRate-2')] | K62: 0 | L62: Output | N62: innertext
A63: =A62 -> Y | B63: =COUNTA($B$1:B62) -> 58 | C63: Verify the displayed Total Amount | G63: Owner Advantage | I63: xpath | J63: //span[contains(@class,'totalBaseRate-2')] | K63: 0 | L63: Output | N63: innertext
A64: bln678042 | B64: =COUNTA($B$1:B63) -> 59 | C64: Close My Trip dropdown | G64: Owner Advantage | I64: xpath | J64: (//button[@type='button'])[1] | K64: 0 | L64: js_click
A65: bln678042 | B65: =COUNTA($B$1:B64) -> 60 | C65: Wait | G65: Owner Advantage | L65: Wait | M65: 2
A66: bln678042 | B66: =COUNTA($B$1:B65) -> 61 | C66: Enter First Name | G66: Owner Advantage | I66: xpath | J66: //input[@name='firstName'] | K66: 0 | L66: Set | M66: Trav_FirstName1
A67: bln678042 | B67: =COUNTA($B$1:B66) -> 62 | C67: Enter Last Name | G67: Owner Advantage | I67: xpath | J67: //input[@name='lastName'] | K67: 0 | L67: Set | M67: Trav_LastName1
A68: bln678042 | B68: =COUNTA($B$1:B67) -> 63 | C68: Enter Address | G68: Owner Advantage | I68: xpath | J68: //input[@name='address1'] | K68: 0 | L68: Set | M68: Address
A69: bln678042 | B69: =COUNTA($B$1:B68) -> 64 | C69: Enter City | G69: Owner Advantage | I69: xpath | J69: //input[@name='city'] | K69: 0 | L69: Set | M69: City
A70: bln678042 | B70: =COUNTA($B$1:B69) -> 65 | C70: Enter Zip Code | G70: Owner Advantage | I70: xpath | J70: //input[@name='postalCode'] | K70: 0 | L70: Set | M70: Zip
A71: bln678042 | B71: =COUNTA($B$1:B70) -> 66 | C71: Enter Phone | G71: Owner Advantage | I71: xpath | J71: //input[@name='dayPhone'] | K71: 0 | L71: Set | M71: Phone
A72: bln678042 | B72: =COUNTA($B$1:B71) -> 67 | C72: Enter Email | G72: Owner Advantage | I72: xpath | J72: //input[@name='email'] | K72: 0 | L72: Set | M72: Email1
A73: bln678042 | B73: =COUNTA($B$1:B72) -> 68 | C73: Enter Owner Number | G73: Owner Advantage | I73: xpath | J73: //input[@name='ownerNumber'] | K73: 0 | L73: Set | M73: OwnerPhone
A74: bln678042 | B74: =COUNTA($B$1:B73) -> 69 | C74: Click Submit button | G74: Owner Advantage | I74: xpath | J74: //button[@type='SUBMIT'] | K74: 0 | L74: js_click
A75: bln678042 | B75: =COUNTA($B$1:B74) -> 70 | C75: Wait | G75: Owner Advantage | L75: Wait | M75: 10
A76: Payment
A77: bln678042 | B77: =COUNTA($B$1:B76) -> 71 | C77: Enter Card Name | G77: Owner Advantage | I77: xpath | J77: //input[@name='cardName'] | K77: 0 | L77: Set | M77: CardName
A78: bln678042 | B78: =COUNTA($B$1:B77) -> 72 | C78: Change iFrame | G78: Owner Advantage | K78: 2 | L78: switchtoframe
A79: bln678042 | B79: =COUNTA($B$1:B78) -> 73 | C79: Enter Card Number | G79: Owner Advantage | I79: xpath | J79: //input[@name='tsep-cardNum'] | K79: 0 | L79: Set | M79: CardNumber
A80: bln678042 | B80: =COUNTA($B$1:B79) -> 74 | C80: Change iFrame | G80: Owner Advantage | K80: 0 | L80: switchtodefault
A81: bln678042 | B81: =COUNTA($B$1:B80) -> 75 | C81: Change iFrame | G81: Owner Advantage | K81: 2 | L81: switchtoframe
A82: N | B82: =COUNTA($B$1:B81) -> 76 | C82: Click tab | G82: Owner Advantage | L82: SendKeys | M82: {TAB}
A83: N | B83: =COUNTA($B$1:B82) -> 77 | C83: Enter Card Expiry Month | G83: Owner Advantage | L83: SendKeys | M83: ExpiryMonth
A84: N | B84: =COUNTA($B$1:B83) -> 78 | C84: Enter Card Expiry Year | G84: Owner Advantage | L84: SendKeys | M84: ExpiryYear
A85: bln678042 | B85: =COUNTA($B$1:B84) -> 79 | C85: Click Expiry Date | G85: Owner Advantage | I85: xpath | J85: //input[@name='tsep-datepicker'] | K85: 0 | L85: Click
A86: bln678042 | B86: =COUNTA($B$1:B85) -> 80 | C86: Wait | G86: Owner Advantage | L86: Wait | M86: 2
A87: bln678042 | B87: =COUNTA($B$1:B86) -> 81 | C87: Input Expiry Month | G87: Owner Advantage | I87: xpath | J87: //input[@name='tsep-datepicker'] | K87: 0 | L87: Type | M87: ExpiryMonth
A88: bln678042 | B88: =COUNTA($B$1:B87) -> 82 | C88: Input Expiry Year | G88: Owner Advantage | I88: xpath | J88: //input[@name='tsep-datepicker'] | K88: 0 | L88: Type | M88: ExpiryYear
A89: bln678042 | B89: =COUNTA($B$1:B88) -> 83 | C89: Wait | G89: Owner Advantage | L89: Wait | M89: 2
A90: bln678042 | B90: =COUNTA($B$1:B89) -> 84 | C90: Change iFrame | G90: Owner Advantage | K90: 0 | L90: switchtodefault
A91: bln678042 | B91: =COUNTA($B$1:B90) -> 85 | C91: Wait | G91: Owner Advantage | L91: Wait | M91: 2
A92: bln678042 | B92: =COUNTA($B$1:B91) -> 86 | C92: Click Get a Quote from the progress bar | G92: Owner Advantage | I92: xpath | J92: //a[text()='Get Quote'] | L92: js_click
B93: =COUNTA($B$1:B92) -> 87
B94: =COUNTA($B$1:B93) -> 88
A95: bln678042 - Update Traveler Details
A96: Quote - Home Page
A97: bln678042 | B97: =COUNTA($B$1:B96) -> 89 | C97: Switch to Frame | G97: Owner Advantage | L97: SWITCHTOFRAME | M97: aemFormFrame | W97: tripType
A98: bln678042 | B98: =COUNTA($B$1:B97) -> 90 | C98: Wait | G98: Owner Advantage | L98: Wait | M98: 3
A99: N | B99: =COUNTA($B$1:B98) -> 91 | C99: Select Trip Type | G99: Owner Advantage | I99: xpath | J99: ="//label[contains(.,'"&W97&"')]" -> //label[contains(.,'tripType')] | K99: 0 | L99: js_click
A100: bln678042 | B100: =COUNTA($B$1:B99) -> 92 | C100: Click Destination | G100: Owner Advantage | I100: xpath | J100: (//input[@id='cmp-Input'])[1] | K100: 0 | L100: Click
...

Sheet Params_3
A1: Scenario | B1: blnExecute | C1: bln_TG | D1: blnQuit | E1: bln678042 | F1: DT_BrowserType | G1: Notes | H1: DT_URL | I1: DateToday | J1: PolicyNumber_OUT | K1: tripType | L1: Plan | M1: Destination | N1: Restricted | O1: Destination1 | P1: Destination2 | Q1: Destination3 | R1: Destination4 | S1: Destination5 | T1: Destination6 | U1: Destination7 | V1: Destination8 | W1: Destination9 | X1: Destination10 | Y1: Destination11 | Z1: Destination12 | AA1: Destination13 | AB1: Destination14 | AC1: Destination15 | AD1: Destination16 | AE1: Destination17 | AF1: Destination18 | AG1: Destination19 | AH1: Destination20 | AI1: Destination21 | AJ1: Destination22 | AK1: Destination23 | AL1: Destination24 | AM1: Destination25 | AN1: Destination26 | AO1: Destination27 | AP1: Destination28 | AQ1: Destination29 | AR1: Destination30 | AS1: Destination31 | AT1: Destination32 | AU1: Destination33 | AV1: DepDate | AW1: DepDate1 | AX1: DepDateValid | AY1: RetDate | AZ1: RetDate1 | BA1: RetDateValid | BB1: DepoDate | BC1: DepoYearInvalid | BD1: DepoYearValid | BE1: DepoMonthInvalid | BF1: DepoMonthValid | BG1: DepoDayInvalid | BH1: DepoDayValid | BI1: Residence | BJ1: Residence1 | BK1: Residence2 | BL1: Residence3 | BM1: Residence4 | BN1: Residence5 | BO1: Residence6 | BP1: Residence7 | BQ1: Residence8 | BR1: Residence9 | BS1: Residence10 | BT1: Residence11 | BU1: Residence12 | BV1: Residence13 | BW1: Residence14 | BX1: Residence15 | BY1: Residence16 | BZ1: Residence17 | CA1: Residence18 | CB1: Residence19 | CC1: Residence20 | CD1: Residence21 | CE1: Residence22 | CF1: Residence23 | CG1: Residence24 | CH1: Residence25 | CI1: Residence26 | CJ1: Residence27 | CK1: Residence28 | CL1: Residence29 | CM1: Residence30 | CN1: Residence31 | CO1: Residence32 | CP1: Residence33 | CQ1: Residence34 | CR1: Residence35 | CS1: Residence36 | CT1: Residence37 | CU1: Residence38 | CV1: Residence39 | CW1: Residence40 | CX1: Residence41 | CY1: Residence42 | CZ1: Residence43 | DA1: Residence44 | DB1: Residence45 | DC1: Residence46 | DD1: Residence47 | DE1: Residence48 | DF1: Residence49 | DG1: Residence50 | DH1: Residence51 | DI1: Residence52 | DJ1: Residence53 | DK1: Age | DL1: Cost | DM1: CostAllowed | DN1: Age1 | DO1: Cost1 | DP1: Trav_FirstName1 | DQ1: Trav_LastName1 | DR1: Trav_BirthDate1 | DS1: Age2 | DT1: Cost2 | DU1: Trav_FirstName2 | DV1: Trav_LastName2 | DW1: Trav_BirthDate2 | DX1: Age3 | DY1: Cost3 | DZ1: Trav_FirstName3 | EA1: Trav_LastName3 | EB1: Trav_BirthDate3 | EC1: Age4 | ED1: Cost4 | EE1: Trav_FirstName4 | EF1: Trav_LastName4 | EG1: Trav_BirthDate4 | EH1: Age5 | EI1: Cost5 | EJ1: Trav_FirstName5 | EK1: Trav_LastName5 | EL1: Trav_BirthDate5 | EM1: Age6 | EN1: Cost6 | EO1: Trav_FirstName6 | EP1: Trav_LastName6 | EQ1: Trav_BirthDate6 | ER1: Age7 | ES1: Cost7 | ET1: Trav_FirstName7 | EU1: Trav_LastName7 | EV1: Trav_BirthDate7 | EW1: Age8 | EX1: Cost8 | EY1: Trav_FirstName8 | EZ1: Trav_LastName8 | FA1: Trav_BirthDate8 | FB1: Age9 | FC1: Cost9 | FD1: Trav_FirstName9 | FE1: Trav_LastName9 | FF1: Trav_BirthDate9 | FG1: PickUpDate | FH1: DropOffDate | FI1: PickUpDate1 | FJ1: DropOffDate1 | FK1: PickUpDate2 | FL1: DropOffDate2 | FM1: PickUpDate3 | FN1: DropOffDate3 | FO1: PickUpDate4 | FP1: DropOffDate4 | FQ1: FirstName | FR1: LastName | FS1: BirthDate | FT1: BirthDateInvalid | FU1: BirthDate1 | FV1: Address | FW1: City | FX1: Zip | FY1: ZipX | FZ1: City1 | GA1: Zip1 | GB1: Phone | GC1: Phone1 | GD1: Email | GE1: Email1 | GF1: OwnerPhone | GG1: CardName | GH1: CardNumber | GI1: CardNumber1 | GJ1: ExpiryMonth | GK1: ExpiryYear | GL1: Cost_OUT | GM1: Cost_RES | GN1: Destination_OUT | GO1: Destination_RES | GP1: Plan | GQ1: Plan_OUT | GR1: Plan_RES | GS1: Plan1 | GT1: Plan1_OUT | GU1: Plan_RES | GV1: Plan2 | GW1: Plan2_OUT | GX1: Plan_RES | GY1: ErrorMessage | GZ1: ErrorMessage_OUT | HA1: ErrorMessage_RES | HB1: ErrorMessage1 | HC1: ErrorMessage1_OUT | HD1: ErrorMessage_RES | HE1: ErrorMessage2 | HF1: ErrorMessage2_OUT | HG1: ErrorMessage_RES | HH1: ErrorMessage3 | HI1: ErrorMessage3_OUT | HJ1: ErrorMessage_RES | HK1: Tooltip | HL1: Tooltip_OUT | HM1: Tooltip_RES | HN1: Tooltip1 | HO1: Tooltip1_OUT | HP1: Tooltip1_RES | HQ1: Tooltip2 | HR1: Tooltip2_OUT | HS1: Tooltip2_RES | HT1: FAQ1 | HU1: FAQ1_OUT | HV1: FAQ1_RES | HW1: FAQ2 | HX1: FAQ2_OUT | HY1: FAQ2_RES | HZ1: FAQ3 | IA1: FAQ3_OUT | IB1: FAQ3_RES | IC1: FAQ4 | ID1: FAQ4_OUT | IE1: FAQ4_RES | IF1: FAQ5 | IG1: FAQ5_OUT | IH1: FAQ5_RES | II1: OwnerAdvantagePlan_OUT | IJ1: RentalCarDamagePlan_OUT | IK1: OwnerAdvantagePlan_VERIFY | IL1: RentalCarDamage_VERIFY
A2: bln678042 | B2: Y | C2: Y | D2: Y | E2: Y | F2: Chrome | G2: TC_678042 | H2: {=_xlfn.IFS(Global!B2="QA","https://owneradvantage.qa.insurancebytravelex.com/",Global!B2="UAT","https://owneradvantage.uat.insurancebytravelex.com/",Global!B2="PROD","https://owneradvantage.insurancebytravelex.com/")} -> https://owneradvantage.uat.insurancebytravelex.com/ | I2: =TODAY() -> 46266 | K2: Rental Car Coverage | L2: Rental Car Damage Plan | M2: Singapore | O2: Australia | AV2: =TEXT(I2+1,"mm/dd/yyyy") -> 09/02/2026 | AW2: =TEXT(I2+7,"mm/dd/yyyy") -> 09/08/2026 | AX2: =TEXT(I2+7,"mm/dd/yyyy") -> 09/08/2026 | AY2: =TEXT(AV2+89,"mm/dd/yyyy") -> 11/30/2026 | AZ2: =TEXT(AW2+14,"mm/dd/yyyy") -> 09/22/2026 | BA2: =TEXT(AV2+14,"mm/dd/yyyy") -> 09/16/2026 | BB2: =TEXT(I2-1,"mm/dd/yyyy") -> 08/31/2026 | BI2: California | BJ2: Nebraska | BK2: New York | DK2: 110 | DL2: 1000 | DM2: 100 | DN2: 18 | DO2: 1500 | DP2: ="QAFIRSTNAME"&CHAR(RANDBETWEEN(65,90))&CHAR(RANDBETWEEN(65,90)) -> QAFIRSTNAMETY | DQ2: ="QALASTNAME"&CHAR(RANDBETWEEN(65,90))&CHAR(RANDBETWEEN(65,90)) -> QALASTNAMEUX | DR2: =TEXT(DATE(YEAR(TODAY())-DS2,MONTH(TODAY()),DAY(TODAY())),"MM/DD/YYYY") -> 09/01/2026 | FG2: =TEXT(AX2,"mm/dd/yyyy") -> 09/08/2026 | FH2: =TEXT(AX2+1,"mm/dd/yyyy") -> 09/09/2026 | FI2: =TEXT(FH2+1,"mm/dd/yyyy") -> 09/10/2026 | FJ2: =TEXT(FI2+1,"mm/dd/yyyy") -> 09/11/2026 | FK2: =TEXT(FJ2+1,"mm/dd/yyyy") -> 09/12/2026 | FL2: =TEXT(FK2+1,"mm/dd/yyyy") -> 09/13/2026 | FM2: =TEXT(FL2+7,"mm/dd/yyyy") -> 09/20/2026 | FN2: =TEXT(FM2+1,"mm/dd/yyyy") -> 09/21/2026 | FO2: =TEXT(FN2+1,"mm/dd/yyyy") -> 09/22/2026 | FP2: =TEXT(FO2+1,"mm/dd/yyyy") -> 09/23/2026 | FQ2: ="QAFIRSTNAME"&CHAR(RANDBETWEEN(65,90))&CHAR(RANDBETWEEN(65,90)) -> QAFIRSTNAMEKA | FR2: ="QALASTNAME"&CHAR(RANDBETWEEN(65,90))&CHAR(RANDBETWEEN(65,90)) -> QALASTNAMEBG | FS2: =TEXT(DATE(YEAR(TODAY())-DK2,MONTH(TODAY()),DAY(TODAY())),"MM/DD/YYYY") -> 09/01/1916 | FU2: =TEXT(DATE(YEAR(TODAY())-DN2,MONTH(TODAY()),DAY(TODAY())),"MM/DD/YYYY") -> 09/01/2008 | FV2: QA213 COR246 | FW2: San Diego | FX2: 92101 | FY2: 12345 | FZ2: Omaha | GA2: 68102 | GB2: 1234567897 | GC2: 2222222222 | GD2: qa@travelexinsurance.com | GE2: qa@travelguard.com | GF2: qwertyuiopasdfgh | GG2: QA Test | GH2: 4111111111111111 | GJ2: 12 | GK2: 2030

Sheet PostDeparture
A1: blnExecute | B1: Step_Number | C1: Step_Name | D1: Status | E1: Error_Check | F1: breakpoint | G1: Test_Case | H1: Page | I1: FindBy | J1: FindBy_Value | K1: Index | L1: Method | M1: Value | N1: Output_Property | O1: Ignore_not_existing_object | P1: isDisabled | Q1: Timeout | R1: Expected_Value | S1: Output_Value | T1: Exact_Match | U1: Contains | V1: ITERATION_NO | W1: Notes | X1: Start_Time | Y1: End_Time | Z1: Duration
A2: Open Post Departure URL
A3: =IF(OR(Global!B25="N"),"N","bln680922") -> N | B3: =COUNTA($B$1:B2) -> 1 | C3: Open Browser | G3: Post Departure | L3: Wait | M3: 1 | O3: Y | R3: DT_URL
A4: =IF(OR(Global!B25="N"),"N","bln680922") -> N | B4: =COUNTA($B$1:B3) -> 2 | C4: Headless | G4: Post Departure | H4: DT_BrowserType | L4: Open | M4: ="URL:="&R3&";;HEADLESS:=TRUE" -> URL:=DT_URL;;HEADLESS:=TRUE | Q4: 60
A5: =IF(OR(Global!B25="Y"),"N","bln680922") -> bln680922 | B5: =COUNTA($B$1:B4) -> 3 | C5: Open Browser | G5: Post Departure | H5: DT_BrowserType | L5: Open | M5: DT_URL | Q5: 60
A6: N | B6: =COUNTA($B$1:B5) -> 4 | C6: Wait | G6: Post Departure | L6: Wait | M6: 5
A7: N | B7: =COUNTA($B$1:B6) -> 5 | C7: Zscaler Sign in Email | G7: Post Departure | I7: xpath | J7: //input[@id='okta-signin-username'] | K7: 0 | L7: Set | M7: DT_ZScalerUser | O7: Y | Q7: 5
A8: N | B8: =COUNTA($B$1:B7) -> 6 | C8: Zscaler Password | G8: Post Departure | I8: xpath | J8: //input[@id='okta-signin-password'] | K8: 0 | L8: Set | M8: DT_ZScalerPassword | O8: Y
A9: N | B9: =COUNTA($B$1:B8) -> 7 | C9: Click Sign in | G9: Post Departure | I9: xpath | J9: //input[@id='okta-signin-submit'] | K9: 0 | L9: Click | O9: Y
A10: N | B10: =COUNTA($B$1:B9) -> 8 | C10: Wait | G10: Post Departure | L10: Wait | M10: 5
A11: Quote - Home Page
A12: bln680922 | B12: =COUNTA($B$1:B11) -> 9 | C12: Switch to Frame | G12: Post Departure | L12: SWITCHTOFRAME | M12: aemFormFrame
A13: bln680922 | B13: =COUNTA($B$1:B12) -> 10 | C13: Check Exist | G13: Post Departure | I13: xpath | J13: //button[text()='Accept All Cookies'] | L13: Exist | O13: Y
A14: =IF($D$13="PASSED","bln680922","N") -> N | B14: =COUNTA($B$1:B13) -> 11 | C14: Output Cookie | G14: Post Departure | I14: xpath | J14: //button[text()='Accept All Cookies'] | L14: Output | N14: innertext | O14: Y | R14: Accept All Cookies
A15: =A14 -> N | B15: =COUNTA($B$1:B14) -> 12 | C15: Cookies | G15: Post Departure | I15: xpath | J15: //button[@id='onetrust-accept-btn-handler'] | L15: js_click | O15: Y
A16: bln680922 | B16: =COUNTA($B$1:B15) -> 13 | C16: Click Destination | G16: Post Departure | I16: xpath | J16: //input[@id='cmp-Input' and @placeholder='Select a country or region'] | K16: 0 | L16: Click
A17: bln680922 | B17: =COUNTA($B$1:B16) -> 14 | C17: Wait | G17: Post Departure | L17: Wait | M17: 2
A18: bln680922 | B18: =COUNTA($B$1:B17) -> 15 | C18: Write Destination | G18: Post Departure | I18: xpath | J18: //input[@id='cmp-Input' and @placeholder='Select a country or region'] | K18: 0 | L18: Write | M18: Destination
A19: bln680922 | B19: =COUNTA($B$1:B18) -> 16 | C19: Wait | G19: Post Departure | L19: Wait | M19: 2
A20: bln680922 | B20: =COUNTA($B$1:B19) -> 17 | C20: Click Destination | G20: Post Departure | I20: xpath | J20: ="//a[contains(.,'"&M18&"')]" -> //a[contains(.,'Destination')] | K20: 0 | L20: js_click
A21: bln680922 | B21: =COUNTA($B$1:B20) -> 18 | C21: Departure Date | G21: Post Departure | I21: xpath | J21: //input[@name='tripDepartureDate'] | K21: 0 | L21: Set | M21: DepDate
A22: bln680922 | B22: =COUNTA($B$1:B21) -> 19 | C22: Return Date | G22: Post Departure | I22: xpath | J22: //input[@name='tripReturnDate'] | K22: 0 | L22: Set | M22: RetDate
A23: bln680922 | B23: =COUNTA($B$1:B22) -> 20 | C23: Click State | G23: Post Departure | I23: xpath | J23: //input[@id='cmp-Input' and @placeholder='Select your state'] | K23: 0 | L23: Click
A24: bln680922 | B24: =COUNTA($B$1:B23) -> 21 | C24: Wait | G24: Post Departure | L24: Wait | M24: 2
A25: bln680922 | B25: =COUNTA($B$1:B24) -> 22 | C25: Write State | G25: Post Departure | I25: xpath | J25: //input[@id='cmp-Input' and @placeholder='Select your state'] | K25: 0 | L25: Write | M25: Residence
A26: bln680922 | B26: =COUNTA($B$1:B25) -> 23 | C26: Wait | G26: Post Departure | L26: Wait | M26: 2
A27: bln680922 | B27: =COUNTA($B$1:B26) -> 24 | C27: Click Destination | G27: Post Departure | I27: xpath | J27: ="//a[contains(.,'"&M25&"')]" -> //a[contains(.,'Residence')] | K27: 0 | L27: js_click
A28: bln680922 | B28: =COUNTA($B$1:B27) -> 25 | C28: Enter Age | G28: Post Departure | I28: xpath | J28: (//input[@name='insuredAge'])[1] | K28: 0 | L28: Set | M28: Age
A29: bln680922 | B29: =COUNTA($B$1:B28) -> 26 | C29: Click Submit button | G29: Post Departure | I29: xpath | J29: //button[@type='SUBMIT'] | K29: 0 | L29: js_click
A30: bln680922 | B30: =COUNTA($B$1:B29) -> 27 | C30: Wait | G30: Post Departure | L30: Wait | M30: 10
A31: Plan Option and Upgrades
A32: bln680922 | B32: =COUNTA($B$1:B31) -> 28 | C32: Check Exist | G32: Post Departure | I32: xpath | J32: //button[text()='Accept All Cookies'] | L32: Exist | O32: Y
A33: =IF($D$32="PASSED","bln680922","N") -> N | B33: =COUNTA($B$1:B32) -> 29 | C33: Output Cookie | G33: Post Departure | I33: xpath | J33: //button[text()='Accept All Cookies'] | L33: Output | N33: innertext | O33: Y | R33: Accept All Cookies
A34: =A33 -> N | B34: =COUNTA($B$1:B33) -> 30 | C34: Cookies | G34: Post Departure | I34: xpath | J34: //button[@id='onetrust-accept-btn-handler'] | L34: js_click | O34: Y
A35: bln680922 | B35: =COUNTA($B$1:B34) -> 31 | C35: Select Post Departure Plan | G35: Post Departure | I35: xpath | J35: //button[@name='selectPlan' and @value='MPDZ-0925'] | K35: 0 | L35: js_click
A36: bln680922 | B36: =COUNTA($B$1:B35) -> 32 | C36: Wait | G36: Post Departure | L36: Wait | M36: 2
A37: bln680922 | B37: =COUNTA($B$1:B36) -> 33 | C37: Select No Rental Car Damage | G37: Post Departure | I37: xpath | J37: //input[@name='RVD_addOn' and @value='No'] | K37: 0 | L37: js_click
A38: bln680922 | B38: =COUNTA($B$1:B37) -> 34 | C38: Click Submit button | G38: Post Departure | I38: xpath | J38: //button[@type='SUBMIT'] | K38: 0 | L38: js_click
A39: bln680922 | B39: =COUNTA($B$1:B38) -> 35 | C39: Wait | G39: Post Departure | L39: Wait | M39: 10
A40: Travelers Information
A41: bln680922 | B41: =COUNTA($B$1:B40) -> 36 | C41: Check Exist | G41: Post Departure | I41: xpath | J41: //button[text()='Accept All Cookies'] | L41: Exist | O41: Y
A42: =IF($D$41="PASSED","bln680922","N") -> N | B42: =COUNTA($B$1:B41) -> 37 | C42: Output Cookie | G42: Post Departure | I42: xpath | J42: //button[text()='Accept All Cookies'] | L42: Output | N42: innertext | O42: Y | R42: Accept All Cookies
A43: =A42 -> N | B43: =COUNTA($B$1:B42) -> 38 | C43: Cookies | G43: Post Departure | I43: xpath | J43: //button[@id='onetrust-accept-btn-handler'] | L43: js_click | O43: Y
A44: bln680922 | B44: =COUNTA($B$1:B43) -> 39 | C44: Enter First Name | G44: Post Departure | I44: xpath | J44: //input[@name='firstName'] | K44: 0 | L44: Set | M44: FirstName
A45: bln680922 | B45: =COUNTA($B$1:B44) -> 40 | C45: Enter Last Name | G45: Post Departure | I45: xpath | J45: //input[@name='lastName'] | K45: 0 | L45: Set | M45: LastName
A46: bln680922 | B46: =COUNTA($B$1:B45) -> 41 | C46: Enter Birth Date | G46: Post Departure | I46: xpath | J46: //input[@name='dateOfBirth'] | K46: 0 | L46: Set | M46: BirthDate
A47: bln680922 | B47: =COUNTA($B$1:B46) -> 42 | C47: Click tab | G47: Post Departure | L47: SendKeys | M47: {TAB}
A48: bln680922 | B48: =COUNTA($B$1:B47) -> 43 | C48: Wait | G48: Post Departure | L48: Wait | M48: 2
A49: bln680922 | B49: =COUNTA($B$1:B48) -> 44 | C49: Enter Address | G49: Post Departure | I49: xpath | J49: //input[@name='address1'] | K49: 0 | L49: Set | M49: Address
A50: bln680922 | B50: =COUNTA($B$1:B49) -> 45 | C50: Enter City | G50: Post Departure | I50: xpath | J50: //input[@name='city'] | K50: 0 | L50: Set | M50: City
A51: bln680922 | B51: =COUNTA($B$1:B50) -> 46 | C51: Enter Zip Code | G51: Post Departure | I51: xpath | J51: //input[@name='postalCode'] | K51: 0 | L51: Set | M51: Zip
A52: bln680922 | B52: =COUNTA($B$1:B51) -> 47 | C52: Enter Phone | G52: Post Departure | I52: xpath | J52: //input[@name='dayPhone'] | K52: 0 | L52: Set | M52: Phone
A53: bln680922 | B53: =COUNTA($B$1:B52) -> 48 | C53: Enter Email | G53: Post Departure | I53: xpath | J53: //input[@name='email'] | K53: 0 | L53: Set | M53: Email
A54: bln680922 | B54: =COUNTA($B$1:B53) -> 49 | C54: Enter Owner Number | G54: Post Departure | I54: xpath | J54: //input[@name='ownerNumber'] | K54: 0 | L54: Set | M54: OwnerPhone
A55: bln680922 | B55: =COUNTA($B$1:B54) -> 50 | C55: Click Submit button | G55: Post Departure | I55: xpath | J55: //button[@type='SUBMIT'] | K55: 0 | L55: js_click
A56: bln680922 | B56: =COUNTA($B$1:B55) -> 51 | C56: Wait | G56: Post Departure | L56: Wait | M56: 10
A57: Payment
A58: bln680922 | B58: =COUNTA($B$1:B57) -> 52 | C58: Enter Card Name | G58: Post Departure | I58: xpath | J58: //input[@name='cardName'] | K58: 0 | L58: Set | M58: CardName
A59: bln680922 | B59: =COUNTA($B$1:B58) -> 53 | C59: Change iFrame | G59: Post Departure | K59: 2 | L59: switchtoframe
A60: bln680922 | B60: =COUNTA($B$1:B59) -> 54 | C60: Enter Card Number | G60: Post Departure | I60: xpath | J60: //input[@name='tsep-cardNum'] | K60: 0 | L60: Set | M60: CardNumber
A61: bln680922 | B61: =COUNTA($B$1:B60) -> 55 | C61: Change iFrame | G61: Post Departure | K61: 0 | L61: switchtodefault
A62: bln680922 | B62: =COUNTA($B$1:B61) -> 56 | C62: Change iFrame | G62: Post Departure | K62: 2 | L62: switchtoframe
A63: N | B63: =COUNTA($B$1:B62) -> 57 | C63: Click tab | G63: Post Departure | L63: SendKeys | M63: {TAB}
A64: N | B64: =COUNTA($B$1:B63) -> 58 | C64: Enter Card Expiry Month | G64: Post Departure | L64: SendKeys | M64: ExpiryMonth
A65: N | B65: =COUNTA($B$1:B64) -> 59 | C65: Enter Card Expiry Year | G65: Post Departure | L65: SendKeys | M65: ExpiryYear
A66: bln680922 | B66: =COUNTA($B$1:B65) -> 60 | C66: Click Expiry Date | G66: Post Departure | I66: xpath | J66: //input[@name='tsep-datepicker'] | K66: 0 | L66: Click
A67: bln680922 | B67: =COUNTA($B$1:B66) -> 61 | C67: Wait | G67: Post Departure | L67: Wait | M67: 2
A68: bln680922 | B68: =COUNTA($B$1:B67) -> 62 | C68: Input Expiry Month | G68: Post Departure | I68: xpath | J68: //input[@name='tsep-datepicker'] | K68: 0 | L68: Type | M68: ExpiryMonth
A69: bln680922 | B69: =COUNTA($B$1:B68) -> 63 | C69: Input Expiry Year | G69: Post Departure | I69: xpath | J69: //input[@name='tsep-datepicker'] | K69: 0 | L69: Type | M69: ExpiryYear
A70: bln680922 | B70: =COUNTA($B$1:B69) -> 64 | C70: Wait | G70: Post Departure | L70: Wait | M70: 2
A71: bln680922 | B71: =COUNTA($B$1:B70) -> 65 | C71: Change iFrame | G71: Post Departure | K71: 0 | L71: switchtodefault
A72: bln680922 | B72: =COUNTA($B$1:B71) -> 66 | C72: Wait | G72: Post Departure | L72: Wait | M72: 2
A73: bln680922 | B73: =COUNTA($B$1:B72) -> 67 | C73: I Agree | G73: Post Departure | I73: xpath | J73: //input[@value='I agree'] | K73: 0 | L73: js_click
A74: bln680922 | B74: =COUNTA($B$1:B73) -> 68 | C74: Wait | G74: Post Departure | L74: Wait | M74: 2
A75: bln680922 | B75: =COUNTA($B$1:B74) -> 69 | C75: Click back button | G75: Post Departure | I75: xpath | J75: //a[contains(.,'Return to previous step')] | K75: 0 | L75: js_click
A76: bln680922 | B76: =COUNTA($B$1:B75) -> 70 | C76: Wait | G76: Post Departure | L76: Wait | M76: 3
A77: bln680922 | B77: =COUNTA($B$1:B76) -> 71 | C77: Click the dropdown next to the total premium | G77: Post Departure | I77: xpath | J77: (//button[@type="button"])[1] | K77: 0 | L77: js_click
A78: bln680922 | B78: =COUNTA($B$1:B77) -> 72 | C78: Wait | G78: Post Departure | L78: Wait | M78: 3
A79: Edit Quote/Restart
A80: bln680922 | B80: =COUNTA($B$1:B79) -> 73 | C80: Click Edit | G80: Post Departure | I80: xpath | J80: //a[@type="button"] | K80: 0 | L80: js_click
A81: bln680922 | B81: =COUNTA($B$1:B80) -> 74 | C81: Wait | G81: Post Departure | L81: Wait | M81: 5
A82: bln680922 | B82: =COUNTA($B$1:B81) -> 75 | C82: Click Destination | G82: Post Departure | I82: xpath | J82: (//input[@id='cmp-Input'])[1] | K82: 0 | L82: Click
A83: bln680922 | B83: =COUNTA($B$1:B82) -> 76 | C83: Wait | G83: Post Departure | L83: Wait | M83: 2
A84: bln680922 | B84: =COUNTA($B$1:B83) -> 77 | C84: Write Destination | G84: Post Departure | I84: xpath | J84: (//input[@id='cmp-Input' and @class='inputField'])[1] | K84: 0 | L84: Write | M84: Destination1
A85: bln680922 | B85: =COUNTA($B$1:B84) -> 78 | C85: Wait | G85: Post Departure | L85: Wait | M85: 2
A86: bln680922 | B86: =COUNTA($B$1:B85) -> 79 | C86: Click Destination | G86: Post Departure | I86: xpath | J86: ="//a[contains(.,'"&M84&"')]" -> //a[contains(.,'Destination1')] | K86: 0 | L86: js_click
A87: bln680922 | B87: =COUNTA($B$1:B86) -> 80 | C87: Departure Date | G87: Post Departure | I87: xpath | J87: //input[@name='tripDepartureDate'] | K87: 0 | L87: Set | M87: DepDate1
A88: bln680922 | B88: =COUNTA($B$1:B87) -> 81 | C88: Return Date | G88: Post Departure | I88: xpath | J88: //input[@name='tripReturnDate'] | K88: 0 | L88: Set | M88: RetDate1
A89: bln680922 | B89: =COUNTA($B$1:B88) -> 82 | C89: Click State | G89: Post Departure | I89: xpath | J89: (//input[@id='cmp-Input'])[2] | K89: 0 | L89: Click
A90: bln680922 | B90: =COUNTA($B$1:B89) -> 83 | C90: Wait | G90: Post Departure | L90: Wait | M90: 2
A91: bln680922 | B91: =COUNTA($B$1:B90) -> 84 | C91: Write State | G91: Post Departure | I91: xpath | J91: (//input[@id='cmp-Input' and @class='inputField'])[2] | K91: 0 | L91: Write | M91: Residence1
A92: bln680922 | B92: =COUNTA($B$1:B91) -> 85 | C92: Wait | G92: Post Departure | L92: Wait | M92: 2
A93: bln680922 | B93: =COUNTA($B$1:B92) -> 86 | C93: Click Destination | G93: Post Departure | I93: xpath | J93: ="//a[contains(.,'"&M91&"')]" -> //a[contains(.,'Residence1')] | K93: 0 | L93: js_click
A94: bln680922 | B94: =COUNTA($B$1:B93) -> 87 | C94: Enter Age | G94: Post Departure | I94: xpath | J94: (//input[@name='insuredAge'])[1] | K94: 0 | L94: Set | M94: Age1
A95: bln680922 | B95: =COUNTA($B$1:B94) -> 88 | C95: Click Submit button | G95: Post Departure | I95: xpath | J95: //button[@type='SUBMIT'] | K95: 0 | L95: js_click
A96: bln680922 | B96: =COUNTA($B$1:B95) -> 89 | C96: Wait | G96: Post Departure | L96: Wait | M96: 13
A97: Plan Option and Upgrades
A98: bln680922 | B98: =COUNTA($B$1:B97) -> 90 | C98: Click My Trip Summary Dropdown | G98: Post Departure | I98: xpath | J98: //button[@type='button' and @aria-controls='my-trip-accordion-item-85f740dcaf-panel'] | K98: 0 | L98: js_click
A99: bln680922 | B99: =COUNTA($B$1:B98) -> 91 | C99: Output Destination Country | G99: Post Departure | I99: xpath | J99: //span[@class='handlebar-recursive-replacement destinationCountry_multi_display'] | K99: 0 | L99: Output | N99: innertext | R99: =M84 -> Destination1 | T99: Y
A100: bln680922 | B100: =COUNTA($B$1:B99) -> 92 | C100: Output Travel (Departure) Dates | G100: Post Departure | I100: xpath | J100: //span[@class='handlebar-recursive-replacement tripDepartureDate'] | K100: 0 | L100: Output | N100: innertext | R100: =TEXT(M87,"mm/dd/yyyy") -> DepDate1 | T100: Y
...

Sheet Params_4
A1: Scenario | B1: blnExecute | C1: bln_TG | D1: blnQuit | E1: bln680922 | F1: DT_BrowserType | G1: Notes | H1: DT_URL | I1: DateToday | J1: PolicyNumber_OUT | K1: tripType | L1: Plan | M1: Destination | N1: Restricted | O1: Destination1 | P1: Destination2 | Q1: Destination3 | R1: Destination4 | S1: Destination5 | T1: Destination6 | U1: Destination7 | V1: Destination8 | W1: Destination9 | X1: Destination10 | Y1: Destination11 | Z1: Destination12 | AA1: Destination13 | AB1: Destination14 | AC1: Destination15 | AD1: Destination16 | AE1: Destination17 | AF1: Destination18 | AG1: Destination19 | AH1: Destination20 | AI1: Destination21 | AJ1: Destination22 | AK1: Destination23 | AL1: Destination24 | AM1: Destination25 | AN1: Destination26 | AO1: Destination27 | AP1: Destination28 | AQ1: Destination29 | AR1: Destination30 | AS1: Destination31 | AT1: Destination32 | AU1: Destination33 | AV1: DepDate | AW1: DepDate1 | AX1: DepDateValid | AY1: RetDate | AZ1: RetDate1 | BA1: RetDateValid | BB1: DepoDate | BC1: DepoYearInvalid | BD1: DepoYearValid | BE1: DepoMonthInvalid | BF1: DepoMonthValid | BG1: DepoDayInvalid | BH1: DepoDayValid | BI1: Residence | BJ1: Residence1 | BK1: Residence2 | BL1: Residence3 | BM1: Residence4 | BN1: Residence5 | BO1: Residence6 | BP1: Residence7 | BQ1: Residence8 | BR1: Residence9 | BS1: Residence10 | BT1: Residence11 | BU1: Residence12 | BV1: Residence13 | BW1: Residence14 | BX1: Residence15 | BY1: Residence16 | BZ1: Residence17 | CA1: Residence18 | CB1: Residence19 | CC1: Residence20 | CD1: Residence21 | CE1: Residence22 | CF1: Residence23 | CG1: Residence24 | CH1: Residence25 | CI1: Residence26 | CJ1: Residence27 | CK1: Residence28 | CL1: Residence29 | CM1: Residence30 | CN1: Residence31 | CO1: Residence32 | CP1: Residence33 | CQ1: Residence34 | CR1: Residence35 | CS1: Residence36 | CT1: Residence37 | CU1: Residence38 | CV1: Residence39 | CW1: Residence40 | CX1: Residence41 | CY1: Residence42 | CZ1: Residence43 | DA1: Residence44 | DB1: Residence45 | DC1: Residence46 | DD1: Residence47 | DE1: Residence48 | DF1: Residence49 | DG1: Residence50 | DH1: Residence51 | DI1: Residence52 | DJ1: Residence53 | DK1: Age | DL1: Cost | DM1: CostAllowed | DN1: Age1 | DO1: Cost1 | DP1: Trav_FirstName1 | DQ1: Trav_LastName1 | DR1: Trav_BirthDate1 | DS1: Age2 | DT1: Cost2 | DU1: Trav_FirstName2 | DV1: Trav_LastName2 | DW1: Trav_BirthDate2 | DX1: Age3 | DY1: Cost3 | DZ1: Trav_FirstName3 | EA1: Trav_LastName3 | EB1: Trav_BirthDate3 | EC1: Age4 | ED1: Cost4 | EE1: Trav_FirstName4 | EF1: Trav_LastName4 | EG1: Trav_BirthDate4 | EH1: Age5 | EI1: Cost5 | EJ1: Trav_FirstName5 | EK1: Trav_LastName5 | EL1: Trav_BirthDate5 | EM1: Age6 | EN1: Cost6 | EO1: Trav_FirstName6 | EP1: Trav_LastName6 | EQ1: Trav_BirthDate6 | ER1: Age7 | ES1: Cost7 | ET1: Trav_FirstName7 | EU1: Trav_LastName7 | EV1: Trav_BirthDate7 | EW1: Age8 | EX1: Cost8 | EY1: Trav_FirstName8 | EZ1: Trav_LastName8 | FA1: Trav_BirthDate8 | FB1: Age9 | FC1: Cost9 | FD1: Trav_FirstName9 | FE1: Trav_LastName9 | FF1: Trav_BirthDate9 | FG1: PickUpDate | FH1: DropOffDate | FI1: PickUpDate1 | FJ1: DropOffDate1 | FK1: PickUpDate2 | FL1: DropOffDate2 | FM1: PickUpDate3 | FN1: DropOffDate3 | FO1: PickUpDate4 | FP1: DropOffDate4 | FQ1: FirstName | FR1: LastName | FS1: BirthDate | FT1: BirthDateInvalid | FU1: BirthDate1 | FV1: Address | FW1: City | FX1: Zip | FY1: ZipX | FZ1: City1 | GA1: Zip1 | GB1: Phone | GC1: Phone1 | GD1: Email | GE1: Email1 | GF1: OwnerPhone | GG1: CardName | GH1: CardNumber | GI1: CardNumber1 | GJ1: ExpiryMonth | GK1: ExpiryYear | GL1: Cost_OUT | GM1: Cost_RES | GN1: Destination_OUT | GO1: Destination_RES | GP1: Plan | GQ1: Plan_OUT | GR1: Plan_RES | GS1: Plan1 | GT1: Plan1_OUT | GU1: Plan_RES | GV1: Plan2 | GW1: Plan2_OUT | GX1: Plan_RES | GY1: ErrorMessage | GZ1: ErrorMessage_OUT | HA1: ErrorMessage_RES | HB1: ErrorMessage1 | HC1: ErrorMessage1_OUT | HD1: ErrorMessage_RES | HE1: ErrorMessage2 | HF1: ErrorMessage2_OUT | HG1: ErrorMessage_RES | HH1: ErrorMessage3 | HI1: ErrorMessage3_OUT | HJ1: ErrorMessage_RES | HK1: Tooltip | HL1: Tooltip_OUT | HM1: Tooltip_RES | HN1: Tooltip1 | HO1: Tooltip1_OUT | HP1: Tooltip1_RES | HQ1: Tooltip2 | HR1: Tooltip2_OUT | HS1: Tooltip2_RES | HT1: FAQ1 | HU1: FAQ1_OUT | HV1: FAQ1_RES | HW1: FAQ2 | HX1: FAQ2_OUT | HY1: FAQ2_RES | HZ1: FAQ3 | IA1: FAQ3_OUT | IB1: FAQ3_RES | IC1: FAQ4 | ID1: FAQ4_OUT | IE1: FAQ4_RES | IF1: FAQ5 | IG1: FAQ5_OUT | IH1: FAQ5_RES | II1: OwnerAdvantagePlan_OUT | IJ1: RentalCarDamagePlan_OUT | IK1: OwnerAdvantagePlan_VERIFY | IL1: RentalCarDamage_VERIFY
A2: bln680922 | B2: Y | C2: Y | D2: Y | E2: Y | F2: Chrome | G2: TC_680922 | H2: {=_xlfn.IFS(Global!B2="QA","https://departure.qa.insurancebytravelex.com",Global!B2="UAT","https://departure.uat.insurancebytravelex.com",Global!B2="PROD","https://departure.insurancebytravelex.com/")} -> https://departure.uat.insurancebytravelex.com | I2: =TODAY() -> 46266 | L2: Post Departure Plan | M2: Singapore | O2: Australia | AV2: =TEXT(I2+1,"mm/dd/yyyy") -> 09/02/2026 | AW2: =TEXT(I2+7,"mm/dd/yyyy") -> 09/08/2026 | AX2: =TEXT(I2+7,"mm/dd/yyyy") -> 09/08/2026 | AY2: =TEXT(AV2+29,"mm/dd/yyyy") -> 10/01/2026 | AZ2: =TEXT(AW2+14,"mm/dd/yyyy") -> 09/22/2026 | BA2: =TEXT(AV2+14,"mm/dd/yyyy") -> 09/16/2026 | BB2: =TEXT(I2-1,"mm/dd/yyyy") -> 08/31/2026 | BI2: California | BJ2: Nebraska | BK2: New York | DK2: 110 | DL2: 1000 | DM2: 100 | DN2: 18 | DO2: 1500 | DP2: ="QAFIRSTNAME"&CHAR(RANDBETWEEN(65,90))&CHAR(RANDBETWEEN(65,90)) -> QAFIRSTNAMEDY | DQ2: ="QALASTNAME"&CHAR(RANDBETWEEN(65,90))&CHAR(RANDBETWEEN(65,90)) -> QALASTNAMEOH | DR2: =TEXT(DATE(YEAR(TODAY())-DS2,MONTH(TODAY()),DAY(TODAY())),"MM/DD/YYYY") -> 09/01/2000 | DS2: 26 | DT2: 1500 | DU2: ="QAFIRSTNAME"&CHAR(RANDBETWEEN(65,90))&CHAR(RANDBETWEEN(65,90)) -> QAFIRSTNAMEIE | DV2: ="QALASTNAME"&CHAR(RANDBETWEEN(65,90))&CHAR(RANDBETWEEN(65,90)) -> QALASTNAMENJ | DW2: 01/01/2000 | FG2: =TEXT(AX2,"mm/dd/yyyy") -> 09/08/2026 | FH2: =TEXT(AX2+1,"mm/dd/yyyy") -> 09/09/2026 | FI2: =TEXT(FH2+1,"mm/dd/yyyy") -> 09/10/2026 | FJ2: =TEXT(FI2+1,"mm/dd/yyyy") -> 09/11/2026 | FK2: =TEXT(FJ2+1,"mm/dd/yyyy") -> 09/12/2026 | FL2: =TEXT(FK2+1,"mm/dd/yyyy") -> 09/13/2026 | FM2: =TEXT(FL2+7,"mm/dd/yyyy") -> 09/20/2026 | FN2: =TEXT(FM2+1,"mm/dd/yyyy") -> 09/21/2026 | FO2: =TEXT(FN2+1,"mm/dd/yyyy") -> 09/22/2026 | FP2: =TEXT(FO2+1,"mm/dd/yyyy") -> 09/23/2026 | FQ2: ="QAFIRSTNAME"&CHAR(RANDBETWEEN(65,90))&CHAR(RANDBETWEEN(65,90)) -> QAFIRSTNAMERX | FR2: ="QALASTNAME"&CHAR(RANDBETWEEN(65,90))&CHAR(RANDBETWEEN(65,90)) -> QALASTNAMENF | FS2: =TEXT(DATE(YEAR(TODAY())-DK2,MONTH(TODAY()),DAY(TODAY())),"MM/DD/YYYY") -> 09/01/1916 | FU2: =TEXT(DATE(YEAR(TODAY())-DN2,MONTH(TODAY()),DAY(TODAY())),"MM/DD/YYYY") -> 09/01/2008 | FV2: QA213 COR246 | FW2: Los Angeles | FX2: 90001 | FY2: 12345 | FZ2: Omaha | GA2: 68102 | GB2: 1234567897 | GC2: 2222222222 | GD2: qa@travelexinsurance.com | GE2: qa@travelguard.com | GF2: qwertyuiopasdfgh | GG2: QA Test | GH2: 4111111111111111 | GJ2: 12 | GK2: 2030

Sheet Preview
A1: blnExecute | B1: Step_Number | C1: Step_Name | D1: Status | E1: Error_Check | F1: breakpoint | G1: Test_Case | H1: Page | I1: FindBy | J1: FindBy_Value | K1: Index | L1: Method | M1: Value | N1: Output_Property | O1: Ignore_not_existing_object | P1: isDisabled | Q1: Timeout | R1: Expected_Value | S1: Output_Value | T1: Exact_Match | U1: Contains | V1: ITERATION_NO | W1: Notes | X1: Start_Time | Y1: End_Time | Z1: Duration
A2: Open Preview URL
A3: =IF(OR(Global!B25="N"),"N","bln680759") -> N | B3: =COUNTA($B$1:B2) -> 1 | C3: Open Browser | G3: Preview | L3: Wait | M3: 1 | O3: Y | R3: DT_URL
A4: =IF(OR(Global!B25="N"),"N","bln680759") -> N | B4: =COUNTA($B$1:B3) -> 2 | C4: Headless | G4: Preview | H4: DT_BrowserType | L4: Open | M4: ="URL:="&R3&";;HEADLESS:=TRUE" -> URL:=DT_URL;;HEADLESS:=TRUE | Q4: 60
A5: =IF(OR(Global!B25="Y"),"N","bln680759") -> bln680759 | B5: =COUNTA($B$1:B4) -> 3 | C5: Open Browser | G5: Preview | H5: DT_BrowserType | L5: Open | M5: DT_URL | Q5: 60
A6: N | B6: =COUNTA($B$1:B5) -> 4 | C6: Wait | G6: Preview | L6: Wait | M6: 5
A7: N | B7: =COUNTA($B$1:B6) -> 5 | C7: Zscaler Sign in Email | G7: Preview | I7: xpath | J7: //input[@id='okta-signin-username'] | K7: 0 | L7: Set | M7: DT_ZScalerUser | O7: Y | Q7: 5
A8: N | B8: =COUNTA($B$1:B7) -> 6 | C8: Zscaler Password | G8: Preview | I8: xpath | J8: //input[@id='okta-signin-password'] | K8: 0 | L8: Set | M8: DT_ZScalerPassword | O8: Y
A9: N | B9: =COUNTA($B$1:B8) -> 7 | C9: Click Sign in | G9: Preview | I9: xpath | J9: //input[@id='okta-signin-submit'] | K9: 0 | L9: Click | O9: Y
A10: N | B10: =COUNTA($B$1:B9) -> 8 | C10: Wait | G10: Preview | L10: Wait | M10: 5
A11: Quote - Home Page
A12: bln680759 | B12: =COUNTA($B$1:B11) -> 9 | C12: Switch to Frame | G12: Preview | L12: SWITCHTOFRAME | M12: aemFormFrame
A13: bln680759 | B13: =COUNTA($B$1:B12) -> 10 | C13: Check Exist | G13: Preview | I13: xpath | J13: //button[text()='Accept All Cookies'] | L13: Exist | O13: Y
A14: =IF($D$13="PASSED","bln680759","N") -> N | B14: =COUNTA($B$1:B13) -> 11 | C14: Output Cookie | G14: Preview | I14: xpath | J14: //button[text()='Accept All Cookies'] | L14: Output | N14: innertext | O14: Y | R14: Accept All Cookies
A15: =A14 -> N | B15: =COUNTA($B$1:B14) -> 12 | C15: Cookies | G15: Preview | I15: xpath | J15: //button[@id='onetrust-accept-btn-handler'] | L15: js_click | O15: Y
A16: bln680759 | B16: =COUNTA($B$1:B15) -> 13 | C16: Click Destination | G16: Preview | I16: xpath | J16: //input[@id='cmp-Input' and @placeholder='Select a country or region'] | K16: 0 | L16: Click
A17: bln680759 | B17: =COUNTA($B$1:B16) -> 14 | C17: Wait | G17: Preview | L17: Wait | M17: 2
A18: bln680759 | B18: =COUNTA($B$1:B17) -> 15 | C18: Write Destination | G18: Preview | I18: xpath | J18: //input[@id='cmp-Input' and @placeholder='Select a country or region'] | K18: 0 | L18: Write | M18: Destination
A19: bln680759 | B19: =COUNTA($B$1:B18) -> 16 | C19: Wait | G19: Preview | L19: Wait | M19: 2
A20: bln680759 | B20: =COUNTA($B$1:B19) -> 17 | C20: Click Destination | G20: Preview | I20: xpath | J20: ="//a[contains(.,'"&M18&"')]" -> //a[contains(.,'Destination')] | K20: 0 | L20: js_click
A21: bln680759 | B21: =COUNTA($B$1:B20) -> 18 | C21: Departure Date | G21: Preview | I21: xpath | J21: //input[@name='tripDepartureDate'] | K21: 0 | L21: Set | M21: DepDate
A22: bln680759 | B22: =COUNTA($B$1:B21) -> 19 | C22: Return Date | G22: Preview | I22: xpath | J22: //input[@name='tripReturnDate'] | K22: 0 | L22: Set | M22: RetDate
A23: bln680759 | B23: =COUNTA($B$1:B22) -> 20 | C23: Deposit Date | G23: Preview | I23: xpath | J23: //input[@name='tripDepositDate'] | K23: 0 | L23: Set | M23: DepoDate
A24: bln680759 | B24: =COUNTA($B$1:B23) -> 21 | C24: Click State | G24: Preview | I24: xpath | J24: //input[@id='cmp-Input' and @placeholder='Select your state'] | K24: 0 | L24: Click
A25: bln680759 | B25: =COUNTA($B$1:B24) -> 22 | C25: Wait | G25: Preview | L25: Wait | M25: 2
A26: bln680759 | B26: =COUNTA($B$1:B25) -> 23 | C26: Write State | G26: Preview | I26: xpath | J26: //input[@id='cmp-Input' and @placeholder='Select your state'] | K26: 0 | L26: Write | M26: Residence
A27: bln680759 | B27: =COUNTA($B$1:B26) -> 24 | C27: Wait | G27: Preview | L27: Wait | M27: 2
A28: bln680759 | B28: =COUNTA($B$1:B27) -> 25 | C28: Click Destination | G28: Preview | I28: xpath | J28: ="//a[contains(.,'"&M26&"')]" -> //a[contains(.,'Residence')] | K28: 0 | L28: js_click
A29: bln680759 | B29: =COUNTA($B$1:B28) -> 26 | C29: Enter Age | G29: Preview | I29: xpath | J29: (//input[@name='insuredAge'])[1] | K29: 0 | L29: Set | M29: Age
A30: bln680759 | B30: =COUNTA($B$1:B29) -> 27 | C30: Enter Trip Cost | G30: Preview | I30: xpath | J30: //input[@name='display_tripCost'] | K30: 0 | L30: Set | M30: Cost
A31: bln680759 | B31: =COUNTA($B$1:B30) -> 28 | C31: Click Submit button | G31: Preview | I31: xpath | J31: //button[@type='SUBMIT'] | K31: 0 | L31: js_click
A32: bln680759 | B32: =COUNTA($B$1:B31) -> 29 | C32: Wait | G32: Preview | L32: Wait | M32: 10
A33: Plan Option and Upgrades
A34: bln680759 | B34: =COUNTA($B$1:B33) -> 30 | C34: Check Exist | G34: Preview | I34: xpath | J34: //button[text()='Accept All Cookies'] | L34: Exist | O34: Y
A35: =IF($D$34="PASSED","bln680759","N") -> N | B35: =COUNTA($B$1:B34) -> 31 | C35: Output Cookie | G35: Preview | I35: xpath | J35: //button[text()='Accept All Cookies'] | L35: Output | N35: innertext | O35: Y | R35: Accept All Cookies
A36: =A35 -> N | B36: =COUNTA($B$1:B35) -> 32 | C36: Cookies | G36: Preview | I36: xpath | J36: //button[@id='onetrust-accept-btn-handler'] | L36: js_click | O36: Y
A37: bln680759 | B37: =COUNTA($B$1:B36) -> 33 | C37: Select Preview Plan | G37: Preview | I37: xpath | J37: //button[@name='selectPlan' and @value='MPEZ-0925'] | K37: 0 | L37: js_click
A38: bln680759 | B38: =COUNTA($B$1:B37) -> 34 | C38: Wait | G38: Preview | L38: Wait | M38: 10
A39: bln680759 | B39: =COUNTA($B$1:B38) -> 35 | C39: Check Exist | G39: Preview | I39: xpath | J39: //button[text()='Accept All Cookies'] | L39: Exist | O39: Y
A40: =IF($D$34="PASSED","bln680759","N") -> N | B40: =COUNTA($B$1:B39) -> 36 | C40: Output Cookie | G40: Preview | I40: xpath | J40: //button[text()='Accept All Cookies'] | L40: Output | N40: innertext | O40: Y | R40: Accept All Cookies
A41: =A40 -> N | B41: =COUNTA($B$1:B40) -> 37 | C41: Cookies | G41: Preview | I41: xpath | J41: //button[@id='onetrust-accept-btn-handler'] | L41: js_click | O41: Y
A42: bln680759 | B42: =COUNTA($B$1:B41) -> 38 | C42: Select Yes Rental Car Damage | G42: Preview | I42: xpath | J42: //input[@name='RVD_addOn' and @value='Yes'] | K42: 0 | L42: js_click
A43: bln680759 | B43: =COUNTA($B$1:B42) -> 39 | C43: Pick Up Date | G43: Preview | I43: xpath | J43: //input[@name='pickupDate'] | K43: 0 | L43: Set | M43: PickUpDate
A44: bln680759 | B44: =COUNTA($B$1:B43) -> 40 | C44: Drop Off Date | G44: Preview | I44: xpath | J44: //input[@name='dropoffDate'] | K44: 0 | L44: Set | M44: DropOffDate
A45: bln680759 | B45: =COUNTA($B$1:B44) -> 41 | C45: Click tab | G45: Preview | L45: SendKeys | M45: {TAB}
A46: bln680759 | B46: =COUNTA($B$1:B45) -> 42 | C46: Click Add Dates | G46: Preview | I46: xpath | J46: //button[@id='RVD_addDates'] | K46: 0 | L46: js_click
A47: bln680759 | B47: =COUNTA($B$1:B46) -> 43 | C47: Verify Date added | G47: Preview | I47: xpath | J47: (//div[@id='text-eca6e55636'])[2] | L47: Output | N47: innertext | R47: =TEXT(M43,"mm/dd/yyyy") & " - " & TEXT(M44,"mm/dd/yyyy") -> PickUpDate - DropOffDate | T47: Y
A48: bln680759 | B48: =COUNTA($B$1:B47) -> 44 | C48: Pick Up Date | G48: Preview | I48: xpath | J48: //input[@name='pickupDate'] | K48: 0 | L48: Set | M48: PickUpDate1
A49: bln680759 | B49: =COUNTA($B$1:B48) -> 45 | C49: Drop Off Date | G49: Preview | I49: xpath | J49: //input[@name='dropoffDate'] | K49: 0 | L49: Set | M49: DropOffDate1
A50: bln680759 | B50: =COUNTA($B$1:B49) -> 46 | C50: Click tab | G50: Preview | L50: SendKeys | M50: {TAB}
A51: bln680759 | B51: =COUNTA($B$1:B50) -> 47 | C51: Click Add Dates | G51: Preview | I51: xpath | J51: //button[@id='RVD_addDates'] | K51: 0 | L51: js_click
A52: bln680759 | B52: =COUNTA($B$1:B51) -> 48 | C52: Verify Date added | G52: Preview | I52: xpath | J52: (//div[@id='text-eca6e55636'])[3] | L52: Output | N52: innertext | R52: =TEXT(M48,"mm/dd/yyyy") & " - " & TEXT(M49,"mm/dd/yyyy") -> PickUpDate1 - DropOffDate1 | T52: Y
A53: bln680759 | B53: =COUNTA($B$1:B52) -> 49 | C53: Pick Up Date | G53: Preview | I53: xpath | J53: //input[@name='pickupDate'] | K53: 0 | L53: Set | M53: PickUpDate2
A54: bln680759 | B54: =COUNTA($B$1:B53) -> 50 | C54: Drop Off Date | G54: Preview | I54: xpath | J54: //input[@name='dropoffDate'] | K54: 0 | L54: Set | M54: DropOffDate2
A55: bln680759 | B55: =COUNTA($B$1:B54) -> 51 | C55: Click tab | G55: Preview | L55: SendKeys | M55: {TAB}
A56: bln680759 | B56: =COUNTA($B$1:B55) -> 52 | C56: Click Add Dates | G56: Preview | I56: xpath | J56: //button[@id='RVD_addDates'] | K56: 0 | L56: js_click
A57: bln680759 | B57: =COUNTA($B$1:B56) -> 53 | C57: Verify Date added | G57: Preview | I57: xpath | J57: (//div[@id='text-eca6e55636'])[4] | L57: Output | N57: innertext | R57: =TEXT(M53,"mm/dd/yyyy") & " - " & TEXT(M54,"mm/dd/yyyy") -> PickUpDate2 - DropOffDate2 | T57: Y
A58: bln680759 | B58: =COUNTA($B$1:B57) -> 54 | C58: Click Submit button | G58: Preview | I58: xpath | J58: //button[@type='SUBMIT'] | K58: 0 | L58: js_click
A59: bln680759 | B59: =COUNTA($B$1:B58) -> 55 | C59: Wait | G59: Preview | L59: Wait | M59: 10
A60: Travelers Information
A61: bln680759 | B61: =COUNTA($B$1:B60) -> 56 | C61: Check Exist | G61: Preview | I61: xpath | J61: //button[text()='Accept All Cookies'] | L61: Exist | O61: Y
A62: =IF($D$61="PASSED","bln680759","N") -> N | B62: =COUNTA($B$1:B61) -> 57 | C62: Output Cookie | G62: Preview | I62: xpath | J62: //button[text()='Accept All Cookies'] | L62: Output | N62: innertext | O62: Y | R62: Accept All Cookies
A63: =A62 -> N | B63: =COUNTA($B$1:B62) -> 58 | C63: Cookies | G63: Preview | I63: xpath | J63: //button[@id='onetrust-accept-btn-handler'] | L63: js_click | O63: Y
A64: bln680759 | B64: =COUNTA($B$1:B63) -> 59 | C64: Enter First Name | G64: Preview | I64: xpath | J64: //input[@name='firstName'] | K64: 0 | L64: Set | M64: FirstName
A65: bln680759 | B65: =COUNTA($B$1:B64) -> 60 | C65: Enter Last Name | G65: Preview | I65: xpath | J65: //input[@name='lastName'] | K65: 0 | L65: Set | M65: LastName
A66: bln680759 | B66: =COUNTA($B$1:B65) -> 61 | C66: Enter Birth Date | G66: Preview | I66: xpath | J66: //input[@name='dateOfBirth'] | K66: 0 | L66: Set | M66: BirthDate
A67: bln680759 | B67: =COUNTA($B$1:B66) -> 62 | C67: Click tab | G67: Preview | L67: SendKeys | M67: {TAB}
A68: bln680759 | B68: =COUNTA($B$1:B67) -> 63 | C68: Wait | G68: Preview | L68: Wait | M68: 2
A69: bln680759 | B69: =COUNTA($B$1:B68) -> 64 | C69: Enter Address | G69: Preview | I69: xpath | J69: //input[@name='address1'] | K69: 0 | L69: Set | M69: Address
A70: bln680759 | B70: =COUNTA($B$1:B69) -> 65 | C70: Enter City | G70: Preview | I70: xpath | J70: //input[@name='city'] | K70: 0 | L70: Set | M70: City
A71: bln680759 | B71: =COUNTA($B$1:B70) -> 66 | C71: Enter Zip Code | G71: Preview | I71: xpath | J71: //input[@name='postalCode'] | K71: 0 | L71: Set | M71: Zip
A72: bln680759 | B72: =COUNTA($B$1:B71) -> 67 | C72: Enter Phone | G72: Preview | I72: xpath | J72: //input[@name='dayPhone'] | K72: 0 | L72: Set | M72: Phone
A73: bln680759 | B73: =COUNTA($B$1:B72) -> 68 | C73: Enter Email | G73: Preview | I73: xpath | J73: //input[@name='email'] | K73: 0 | L73: Set | M73: Email
A74: bln680759 | B74: =COUNTA($B$1:B73) -> 69 | C74: Enter Reservation Confirmation Number | G74: Preview | I74: xpath | J74: //input[@name='invoiceNumber'] | K74: 0 | L74: Set | M74: ReservationConfirmationNumber
A75: bln680759 | B75: =COUNTA($B$1:B74) -> 70 | C75: Click Submit button | G75: Preview | I75: xpath | J75: //button[@type='SUBMIT'] | K75: 0 | L75: js_click
A76: bln680759 | B76: =COUNTA($B$1:B75) -> 71 | C76: Wait | G76: Preview | L76: Wait | M76: 10
A77: Payment
A78: bln680759 | B78: =COUNTA($B$1:B77) -> 72 | C78: Check Exist | G78: Preview | I78: xpath | J78: //button[text()='Accept All Cookies'] | L78: Exist | O78: Y
A79: =IF($D$78="PASSED","bln680759","N") -> N | B79: =COUNTA($B$1:B78) -> 73 | C79: Output Cookie | G79: Preview | I79: xpath | J79: //button[text()='Accept All Cookies'] | L79: Output | N79: innertext | O79: Y | R79: Accept All Cookies
A80: =A79 -> N | B80: =COUNTA($B$1:B79) -> 74 | C80: Cookies | G80: Preview | I80: xpath | J80: //button[@id='onetrust-accept-btn-handler'] | L80: js_click | O80: Y
A81: bln680759 | B81: =COUNTA($B$1:B80) -> 75 | C81: Enter Card Name | G81: Preview | I81: xpath | J81: //input[@name='cardName'] | K81: 0 | L81: Set | M81: CardName
A82: bln680759 | B82: =COUNTA($B$1:B81) -> 76 | C82: Change iFrame | G82: Preview | I82: xpath | K82: 2 | L82: switchtoframe
A83: bln680759 | B83: =COUNTA($B$1:B82) -> 77 | C83: Check Exist | G83: Preview | I83: xpath | J83: //button[text()='Accept All Cookies'] | L83: Exist | O83: Y
A84: =IF($D$83="PASSED","bln680759","N") -> N | B84: =COUNTA($B$1:B83) -> 78 | C84: Output Cookie | G84: Preview | I84: xpath | J84: //button[text()='Accept All Cookies'] | L84: Output | N84: innertext | O84: Y | R84: Accept All Cookies
A85: =A84 -> N | B85: =COUNTA($B$1:B84) -> 79 | C85: Cookies | G85: Preview | I85: xpath | J85: //button[@id='onetrust-accept-btn-handler'] | L85: js_click | O85: Y
A86: bln680759 | B86: =COUNTA($B$1:B85) -> 80 | C86: Enter Card Number | G86: Preview | I86: xpath | J86: //input[@name='tsep-cardNum'] | K86: 0 | L86: Set | M86: CardNumber
A87: bln680759 | B87: =COUNTA($B$1:B86) -> 81 | C87: Change iFrame | G87: Preview | K87: 0 | L87: switchtodefault
A88: bln680759 | B88: =COUNTA($B$1:B87) -> 82 | C88: Change iFrame | G88: Preview | K88: 2 | L88: switchtoframe
A89: N | B89: =COUNTA($B$1:B88) -> 83 | C89: Click tab | G89: Preview | L89: SendKeys | M89: {TAB}
A90: N | B90: =COUNTA($B$1:B89) -> 84 | C90: Enter Card Expiry Month | G90: Preview | L90: SendKeys | M90: ExpiryMonth
A91: N | B91: =COUNTA($B$1:B90) -> 85 | C91: Enter Card Expiry Year | G91: Preview | L91: SendKeys | M91: ExpiryYear
A92: bln680759 | B92: =COUNTA($B$1:B91) -> 86 | C92: Click Expiry Date | G92: Preview | I92: xpath | J92: //input[@name='tsep-datepicker'] | K92: 0 | L92: Click
A93: bln680759 | B93: =COUNTA($B$1:B92) -> 87 | C93: Wait | G93: Preview | L93: Wait | M93: 2
A94: bln680759 | B94: =COUNTA($B$1:B93) -> 88 | C94: Input Expiry Month | G94: Preview | I94: xpath | J94: //input[@name='tsep-datepicker'] | K94: 0 | L94: Type | M94: ExpiryMonth
A95: bln680759 | B95: =COUNTA($B$1:B94) -> 89 | C95: Input Expiry Year | G95: Preview | I95: xpath | J95: //input[@name='tsep-datepicker'] | K95: 0 | L95: Type | M95: ExpiryYear
A96: bln680759 | B96: =COUNTA($B$1:B95) -> 90 | C96: Wait | G96: Preview | L96: Wait | M96: 2
A97: bln680759 | B97: =COUNTA($B$1:B96) -> 91 | C97: Change iFrame | G97: Preview | K97: 0 | L97: switchtodefault
A98: bln680759 | B98: =COUNTA($B$1:B97) -> 92 | C98: Wait | G98: Preview | L98: Wait | M98: 2
A99: bln680759 | B99: =COUNTA($B$1:B98) -> 93 | C99: I Agree | G99: Preview | I99: xpath | J99: //input[@value='I agree'] | K99: 0 | L99: js_click
A100: bln680759 | B100: =COUNTA($B$1:B99) -> 94 | C100: Wait | G100: Preview | L100: Wait | M100: 10
...

Sheet Params_5
A1: Scenario | B1: blnExecute | C1: bln_TG | D1: blnQuit | E1: bln680759 | F1: DT_BrowserType | G1: Notes | H1: DT_URL | I1: DateToday | J1: PolicyNumber_OUT | K1: tripType | L1: Plan | M1: Destination | N1: Restricted | O1: Destination1 | P1: Destination2 | Q1: Destination3 | R1: Destination4 | S1: Destination5 | T1: Destination6 | U1: Destination7 | V1: Destination8 | W1: Destination9 | X1: Destination10 | Y1: Destination11 | Z1: Destination12 | AA1: Destination13 | AB1: Destination14 | AC1: Destination15 | AD1: Destination16 | AE1: Destination17 | AF1: Destination18 | AG1: Destination19 | AH1: Destination20 | AI1: Destination21 | AJ1: Destination22 | AK1: Destination23 | AL1: Destination24 | AM1: Destination25 | AN1: Destination26 | AO1: Destination27 | AP1: Destination28 | AQ1: Destination29 | AR1: Destination30 | AS1: Destination31 | AT1: Destination32 | AU1: Destination33 | AV1: DepDate | AW1: DepDate1 | AX1: DepDateValid | AY1: RetDate | AZ1: RetDate1 | BA1: RetDateValid | BB1: DepoDate | BC1: DepoYearInvalid | BD1: DepoYearValid | BE1: DepoMonthInvalid | BF1: DepoMonthValid | BG1: DepoDayInvalid | BH1: DepoDayValid | BI1: Residence | BJ1: Residence1 | BK1: Residence2 | BL1: Residence3 | BM1: Residence4 | BN1: Residence5 | BO1: Residence6 | BP1: Residence7 | BQ1: Residence8 | BR1: Residence9 | BS1: Residence10 | BT1: Residence11 | BU1: Residence12 | BV1: Residence13 | BW1: Residence14 | BX1: Residence15 | BY1: Residence16 | BZ1: Residence17 | CA1: Residence18 | CB1: Residence19 | CC1: Residence20 | CD1: Residence21 | CE1: Residence22 | CF1: Residence23 | CG1: Residence24 | CH1: Residence25 | CI1: Residence26 | CJ1: Residence27 | CK1: Residence28 | CL1: Residence29 | CM1: Residence30 | CN1: Residence31 | CO1: Residence32 | CP1: Residence33 | CQ1: Residence34 | CR1: Residence35 | CS1: Residence36 | CT1: Residence37 | CU1: Residence38 | CV1: Residence39 | CW1: Residence40 | CX1: Residence41 | CY1: Residence42 | CZ1: Residence43 | DA1: Residence44 | DB1: Residence45 | DC1: Residence46 | DD1: Residence47 | DE1: Residence48 | DF1: Residence49 | DG1: Residence50 | DH1: Residence51 | DI1: Residence52 | DJ1: Residence53 | DK1: Age | DL1: Cost | DM1: CostAllowed | DN1: Age1 | DO1: Cost1 | DP1: Trav_FirstName1 | DQ1: Trav_LastName1 | DR1: Trav_BirthDate1 | DS1: Age2 | DT1: Cost2 | DU1: Trav_FirstName2 | DV1: Trav_LastName2 | DW1: Trav_BirthDate2 | DX1: Age3 | DY1: Cost3 | DZ1: Trav_FirstName3 | EA1: Trav_LastName3 | EB1: Trav_BirthDate3 | EC1: Age4 | ED1: Cost4 | EE1: Trav_FirstName4 | EF1: Trav_LastName4 | EG1: Trav_BirthDate4 | EH1: Age5 | EI1: Cost5 | EJ1: Trav_FirstName5 | EK1: Trav_LastName5 | EL1: Trav_BirthDate5 | EM1: Age6 | EN1: Cost6 | EO1: Trav_FirstName6 | EP1: Trav_LastName6 | EQ1: Trav_BirthDate6 | ER1: Age7 | ES1: Cost7 | ET1: Trav_FirstName7 | EU1: Trav_LastName7 | EV1: Trav_BirthDate7 | EW1: Age8 | EX1: Cost8 | EY1: Trav_FirstName8 | EZ1: Trav_LastName8 | FA1: Trav_BirthDate8 | FB1: Age9 | FC1: Cost9 | FD1: Trav_FirstName9 | FE1: Trav_LastName9 | FF1: Trav_BirthDate9 | FG1: PickUpDate | FH1: DropOffDate | FI1: PickUpDate1 | FJ1: DropOffDate1 | FK1: PickUpDate2 | FL1: DropOffDate2 | FM1: PickUpDate3 | FN1: DropOffDate3 | FO1: PickUpDate4 | FP1: DropOffDate4 | FQ1: FirstName | FR1: LastName | FS1: BirthDate | FT1: BirthDateInvalid | FU1: BirthDate1 | FV1: Address | FW1: City | FX1: Zip | FY1: ZipX | FZ1: City1 | GA1: Zip1 | GB1: Phone | GC1: Phone1 | GD1: Email | GE1: Email1 | GF1: OwnerPhone | GG1: ReservationConfirmationNumber | GH1: CardName | GI1: CardNumber | GJ1: CardNumber1 | GK1: ExpiryMonth | GL1: ExpiryYear | GM1: Cost_OUT | GN1: Cost_RES | GO1: Destination_OUT | GP1: Destination_RES | GQ1: Plan | GR1: Plan_OUT | GS1: Plan_RES | GT1: Plan1 | GU1: Plan1_OUT | GV1: Plan_RES | GW1: Plan2 | GX1: Plan2_OUT | GY1: Plan_RES | GZ1: ErrorMessage | HA1: ErrorMessage_OUT | HB1: ErrorMessage_RES | HC1: ErrorMessage1 | HD1: ErrorMessage1_OUT | HE1: ErrorMessage_RES | HF1: ErrorMessage2 | HG1: ErrorMessage2_OUT | HH1: ErrorMessage_RES | HI1: ErrorMessage3 | HJ1: ErrorMessage3_OUT | HK1: ErrorMessage_RES | HL1: Tooltip | HM1: Tooltip_OUT | HN1: Tooltip_RES | HO1: Tooltip1 | HP1: Tooltip1_OUT | HQ1: Tooltip1_RES | HR1: Tooltip2 | HS1: Tooltip2_OUT | HT1: Tooltip2_RES | HU1: FAQ1 | HV1: FAQ1_OUT | HW1: FAQ1_RES | HX1: FAQ2 | HY1: FAQ2_OUT | HZ1: FAQ2_RES | IA1: FAQ3 | IB1: FAQ3_OUT | IC1: FAQ3_RES | ID1: FAQ4 | IE1: FAQ4_OUT | IF1: FAQ4_RES | IG1: FAQ5 | IH1: FAQ5_OUT | II1: FAQ5_RES | IJ1: OwnerAdvantagePlan_OUT | IK1: RentalCarDamagePlan_OUT | IL1: OwnerAdvantagePlan_VERIFY | IM1: RentalCarDamage_VERIFY
A2: bln680759 | B2: Y | C2: Y | D2: Y | E2: Y | F2: Chrome | G2: TC_680759 | H2: {=_xlfn.IFS(Global!B2="QA","https://preview.qa.insurancebytravelex.com",Global!B2="UAT","https://preview.uat.insurancebytravelex.com",Global!B2="PROD","https://preview.insurancebytravelex.com/")} -> https://preview.uat.insurancebytravelex.com | I2: =TODAY() -> 46266 | L2: Preview Plan | M2: Singapore | O2: Australia | AV2: =TEXT(I2+1,"mm/dd/yyyy") -> 09/02/2026 | AW2: =TEXT(I2+7,"mm/dd/yyyy") -> 09/08/2026 | AX2: =TEXT(I2+7,"mm/dd/yyyy") -> 09/08/2026 | AY2: =TEXT(AV2+89,"mm/dd/yyyy") -> 11/30/2026 | AZ2: =TEXT(AW2+14,"mm/dd/yyyy") -> 09/22/2026 | BA2: =TEXT(AV2+14,"mm/dd/yyyy") -> 09/16/2026 | BB2: =TEXT(I2-1,"mm/dd/yyyy") -> 08/31/2026 | BI2: California | BJ2: Nebraska | BK2: New York | DK2: 110 | DL2: 1000 | DM2: 100 | DN2: 18 | DO2: 1500 | DP2: ="QAFIRSTNAME"&CHAR(RANDBETWEEN(65,90))&CHAR(RANDBETWEEN(65,90)) -> QAFIRSTNAMEFT | DQ2: ="QALASTNAME"&CHAR(RANDBETWEEN(65,90))&CHAR(RANDBETWEEN(65,90)) -> QALASTNAMESQ | DR2: =TEXT(DATE(YEAR(TODAY())-DS2,MONTH(TODAY()),DAY(TODAY())),"MM/DD/YYYY") -> 09/01/2026 | FG2: =TEXT(AV2,"mm/dd/yyyy") -> 09/02/2026 | FH2: =TEXT(AV2+1,"mm/dd/yyyy") -> 09/03/2026 | FI2: =TEXT(FH2+1,"mm/dd/yyyy") -> 09/04/2026 | FJ2: =TEXT(FI2+1,"mm/dd/yyyy") -> 09/05/2026 | FK2: =TEXT(FJ2+1,"mm/dd/yyyy") -> 09/06/2026 | FL2: =TEXT(FK2+1,"mm/dd/yyyy") -> 09/07/2026 | FM2: =TEXT(FL2+7,"mm/dd/yyyy") -> 09/14/2026 | FN2: =TEXT(FM2+1,"mm/dd/yyyy") -> 09/15/2026 | FO2: =TEXT(FN2+1,"mm/dd/yyyy") -> 09/16/2026 | FP2: =TEXT(FO2+1,"mm/dd/yyyy") -> 09/17/2026 | FQ2: ="QAFIRSTNAME"&CHAR(RANDBETWEEN(65,90))&CHAR(RANDBETWEEN(65,90)) -> QAFIRSTNAMELO | FR2: ="QALASTNAME"&CHAR(RANDBETWEEN(65,90))&CHAR(RANDBETWEEN(65,90)) -> QALASTNAMEAN | FS2: =TEXT(DATE(YEAR(TODAY())-DK2,MONTH(TODAY()),DAY(TODAY())),"MM/DD/YYYY") -> 09/01/1916 | FU2: =TEXT(DATE(YEAR(TODAY())-DN2,MONTH(TODAY()),DAY(TODAY())),"MM/DD/YYYY") -> 09/01/2008 | FV2: QA213 COR246 | FW2: Los Angeles | FX2: 90001 | FY2: 12345 | FZ2: Omaha | GA2: 68102 | GB2: 1234567897 | GC2: 2222222222 | GD2: qa@travelexinsurance.com | GE2: qa@travelguard.com | GF2: qwertyuiopasdfgh | GG2: qwertyuiopasdfgh | GH2: QA Test | GI2: 4111111111111111 | GK2: 12 | GL2: 2030 | GN2: =IF(DL2=GM2,"PASSED","FAILED") -> FAILED

Sheet Travelkore
A1: blnExecute | B1: Step_Number | C1: Step_Name | D1: Status | E1: Error_Check | F1: breakpoint | G1: Test_Case | H1: Page | I1: FindBy | J1: FindBy_Value | K1: Index | L1: Method | M1: Value | N1: Output_Property | O1: Ignore_not_existing_object | P1: isDisabled | Q1: Timeout | R1: Expected_Value | S1: Output_Value | T1: Exact_Match | U1: Contains | V1: ITERATION_NO | W1: Notes | X1: Start_Time | Y1: End_Time | Z1: Duration
A2: Open Travelkore URL
A3: =IF(OR(Global!B25="N"),"N","bln687809") -> N | B3: =COUNTA($B$1:B2) -> 1 | C3: Open Browser | G3: Travelkore | L3: Wait | M3: 1 | O3: Y | R3: DT_URL
A4: =IF(OR(Global!B25="N"),"N","bln687809") -> N | B4: =COUNTA($B$1:B3) -> 2 | C4: Headless | G4: Travelkore | H4: DT_BrowserType | L4: Open | M4: ="URL:="&R3&";;HEADLESS:=TRUE" -> URL:=DT_URL;;HEADLESS:=TRUE | Q4: 60
A5: =IF(OR(Global!B25="Y"),"N","bln687809") -> bln687809 | B5: =COUNTA($B$1:B4) -> 3 | C5: Open Browser | G5: Travelkore | H5: DT_BrowserType | L5: Open | M5: DT_URL | Q5: 60
A6: N | B6: =COUNTA($B$1:B5) -> 4 | C6: Wait | G6: Travelkore | L6: Wait | M6: 5
A7: N | B7: =COUNTA($B$1:B6) -> 5 | C7: Zscaler Sign in Email | G7: Travelkore | I7: xpath | J7: //input[@id='okta-signin-username'] | K7: 0 | L7: Set | M7: DT_ZScalerUser | O7: Y | Q7: 5
A8: N | B8: =COUNTA($B$1:B7) -> 6 | C8: Zscaler Password | G8: Travelkore | I8: xpath | J8: //input[@id='okta-signin-password'] | K8: 0 | L8: Set | M8: DT_ZScalerPassword | O8: Y
A9: N | B9: =COUNTA($B$1:B8) -> 7 | C9: Click Sign in | G9: Travelkore | I9: xpath | J9: //input[@id='okta-signin-submit'] | K9: 0 | L9: Click | O9: Y
A10: bln687809 | B10: =COUNTA($B$1:B9) -> 8 | C10: Wait | G10: Travelkore | L10: Wait | M10: 5
A11: Quote - Home Page
A12: bln687809 | B12: =COUNTA($B$1:B11) -> 9 | C12: Switch to Frame | G12: Travelkore | L12: SWITCHTOFRAME | M12: aemFormFrame
A13: bln687809 | B13: =COUNTA($B$1:B12) -> 10 | C13: Check Exist | G13: Travelkore | I13: xpath | J13: //button[text()='Accept All Cookies'] | L13: Exist | O13: Y
A14: =IF($D$13="PASSED","bln687809","N") -> N | B14: =COUNTA($B$1:B13) -> 11 | C14: Output Cookie | G14: Travelkore | I14: xpath | J14: //button[text()='Accept All Cookies'] | L14: Output | N14: innertext | O14: Y | R14: Accept All Cookies
A15: =A14 -> N | B15: =COUNTA($B$1:B14) -> 12 | C15: Cookies | G15: Travelkore | I15: xpath | J15: //button[@id='onetrust-accept-btn-handler'] | L15: js_click | O15: Y
A16: bln687809 | B16: =COUNTA($B$1:B15) -> 13 | C16: Wait | G16: Travelkore | L16: Wait | M16: 5
A17: =IF(OR(Global!B2="QA",Global!B2="UAT"),"bln687809","N") -> bln687809 | B17: =COUNTA($B$1:B16) -> 14 | C17: Verify Default Destination displays Mexico | G17: Travelkore | I17: xpath | J17: //span[@selectedcountrycode='1404' and @aria-hidden='true'] | K17: 0 | L17: Output | N17: innertext
A18: =A17 -> bln687809 | B18: =COUNTA($B$1:B17) -> 15 | C18: Save SS | G18: Travelkore | L18: SCREENSHOT | M18: =Global!B3 & "TravelkoreDefaultDestination_Mexico.png" -> L:\Regression\Test Results\Temp_Results\AEM Regression\Travelex\UAT\Travel EX Migration_AEM Regression_UAT01Sep26101238\TravelkoreDefaultDestination_Mexico.png
A19: =IF(Global!B2="PROD","Y","N") -> N | B19: =COUNTA($B$1:B18) -> 16 | C19: Click Destination | G19: Travelkore | I19: xpath | J19: //input[@id='cmp-Input' and @class='inputField'] | K19: 0 | L19: Click
A20: =A19 -> N | B20: =COUNTA($B$1:B19) -> 17 | C20: Wait | G20: Travelkore | L20: Wait | M20: 2
A21: =A20 -> N | B21: =COUNTA($B$1:B20) -> 18 | C21: Write Destination | G21: Travelkore | I21: xpath | J21: //input[@id='cmp-Input' and @class='inputField'] | K21: 0 | L21: Write | M21: Destination
A22: =A21 -> N | B22: =COUNTA($B$1:B21) -> 19 | C22: Wait | G22: Travelkore | L22: Wait | M22: 2
A23: =A22 -> N | B23: =COUNTA($B$1:B22) -> 20 | C23: Click Destination | G23: Travelkore | I23: xpath | J23: ="//a[contains(.,'"&M21&"')]" -> //a[contains(.,'Destination')] | K23: 0 | L23: js_click
A24: bln687809 | B24: =COUNTA($B$1:B23) -> 21 | C24: Departure Date | G24: Travelkore | I24: xpath | J24: //input[@name='tripDepartureDate'] | K24: 0 | L24: Set | M24: DepDate
A25: bln687809 | B25: =COUNTA($B$1:B24) -> 22 | C25: Return Date | G25: Travelkore | I25: xpath | J25: //input[@name='tripReturnDate'] | K25: 0 | L25: Set | M25: RetDate
A26: bln687809 | B26: =COUNTA($B$1:B25) -> 23 | C26: Deposit Date | G26: Travelkore | I26: xpath | J26: //input[@name='tripDepositDate'] | K26: 0 | L26: Set | M26: DepoDate
A27: bln687809 | B27: =COUNTA($B$1:B26) -> 24 | C27: Click State | G27: Travelkore | I27: xpath | J27: //input[@id='cmp-Input' and @placeholder='Select your state'] | K27: 0 | L27: Click
A28: bln687809 | B28: =COUNTA($B$1:B27) -> 25 | C28: Wait | G28: Travelkore | L28: Wait | M28: 2
A29: bln687809 | B29: =COUNTA($B$1:B28) -> 26 | C29: Write State | G29: Travelkore | I29: xpath | J29: //input[@id='cmp-Input' and @placeholder='Select your state'] | K29: 0 | L29: Write | M29: Residence
A30: bln687809 | B30: =COUNTA($B$1:B29) -> 27 | C30: Wait | G30: Travelkore | L30: Wait | M30: 2
A31: bln687809 | B31: =COUNTA($B$1:B30) -> 28 | C31: Click Destination | G31: Travelkore | I31: xpath | J31: ="//a[contains(.,'"&M29&"')]" -> //a[contains(.,'Residence')] | K31: 0 | L31: js_click
A32: bln687809 | B32: =COUNTA($B$1:B31) -> 29 | C32: Enter Age | G32: Travelkore | I32: xpath | J32: (//input[@name='insuredAge'])[1] | K32: 0 | L32: Set | M32: Age
A33: bln687809 | B33: =COUNTA($B$1:B32) -> 30 | C33: Click Submit button | G33: Travelkore | I33: xpath | J33: //button[@type='SUBMIT'] | K33: 0 | L33: js_click
A34: bln687809 | B34: =COUNTA($B$1:B33) -> 31 | C34: Wait | G34: Travelkore | L34: Wait | M34: 10
A35: Plan Option and Upgrades
A36: bln687809 | B36: =COUNTA($B$1:B35) -> 32 | C36: Check Exist | G36: Travelkore | I36: xpath | J36: //button[text()='Accept All Cookies'] | L36: Exist | O36: Y
A37: =IF($D$36="PASSED","bln687809","N") -> N | B37: =COUNTA($B$1:B36) -> 33 | C37: Output Cookie | G37: Travelkore | I37: xpath | J37: //button[text()='Accept All Cookies'] | L37: Output | N37: innertext | O37: Y | R37: Accept All Cookies
A38: =A37 -> N | B38: =COUNTA($B$1:B37) -> 34 | C38: Cookies | G38: Travelkore | I38: xpath | J38: //button[@id='onetrust-accept-btn-handler'] | L38: js_click | O38: Y
A39: =IF(Global!B2="QA","Y","N") -> N | B39: =COUNTA($B$1:B38) -> 35 | C39: Verify that the Plan displayed is Travel Med Go | G39: Travelkore | I39: xpath | J39: //span[@class='handlebar-recursive-replacement productName'] | K39: 1 | L39: Output | N39: innertext | R39: Travel Med Go | T39: Y
A40: =IF(OR(Global!B2="UAT",Global!B2="PROD"),"bln687809","N") -> bln687809 | B40: =COUNTA($B$1:B39) -> 36 | C40: Verify that the Plan displayed is Travel Med Go | G40: Travelkore | I40: xpath | J40: //div[@id='title-66463e0db5']/h2/span | K40: 0 | L40: Output | N40: innertext | R40: Travel Med Go | T40: Y
A41: bln687809 | B41: =COUNTA($B$1:B40) -> 37 | C41: Select Travel Med Go | G41: Travelkore | I41: xpath | J41: //button[@name='selectPlan' and @value='TMGZ-1224'] | K41: 0 | L41: js_click
A42: bln687809 | B42: =COUNTA($B$1:B41) -> 38 | C42: Wait | G42: Travelkore | L42: Wait | M42: 10
A43: bln687809 | B43: =COUNTA($B$1:B42) -> 39 | C43: Check Exist | G43: Travelkore | I43: xpath | J43: //button[text()='Accept All Cookies'] | L43: Exist | O43: Y
A44: =IF($D$43="PASSED","bln687809","N") -> N | B44: =COUNTA($B$1:B43) -> 40 | C44: Output Cookie | G44: Travelkore | I44: xpath | J44: //button[text()='Accept All Cookies'] | L44: Output | N44: innertext | O44: Y | R44: Accept All Cookies
A45: =A44 -> N | B45: =COUNTA($B$1:B44) -> 41 | C45: Cookies | G45: Travelkore | I45: xpath | J45: //button[@id='onetrust-accept-btn-handler'] | L45: js_click | O45: Y
A46: bln687809 | B46: =COUNTA($B$1:B45) -> 42 | C46: Accidental Death for Air Travel | G46: Travelkore | I46: xpath | J46: //input[@name='AOAD_addOn' and @value='Yes'] | K46: 0 | L46: js_click
A47: bln687809 | B47: =COUNTA($B$1:B46) -> 43 | C47: Select AOAD Upgrade Options | G47: Travelkore | I47: xpath | J47: //select[@name='aoad-options'] | K47: 0 | L47: Select | M47: AOAD3
A48: bln687809 | B48: =COUNTA($B$1:B47) -> 44 | C48: Wait | G48: Travelkore | L48: Wait | M48: 3
A49: bln687809 | B49: =COUNTA($B$1:B48) -> 45 | C49: Verify AOAD Total has been updated | G49: Travelkore | I49: xpath | J49: //p[contains(.,'$')] | K49: 3 | L49: Output | N49: innertext
A50: bln687809 | B50: =COUNTA($B$1:B49) -> 46 | C50: Click My Trip Panel dropdown | G50: Travelkore | I50: xpath | J50: (//button[@type='button'])[1] | K50: 0 | L50: js_click
A51: bln687809 | B51: =COUNTA($B$1:B50) -> 47 | C51: Wait | G51: Travelkore | L51: Wait | M51: 3
A52: bln687809 | B52: =COUNTA($B$1:B51) -> 48 | C52: Compare AOAD Premium in My Trip Panel | G52: Travelkore | I52: xpath | J52: //p[contains(.,'$')] | K52: 1 | L52: Output | N52: innertext | R52: =S49 -> 0 | T52: Y
A53: bln687809 | B53: =COUNTA($B$1:B52) -> 49 | C53: Click Submit button | G53: Travelkore | I53: xpath | J53: //button[@type='SUBMIT'] | K53: 0 | L53: js_click
A54: bln687809 | B54: =COUNTA($B$1:B53) -> 50 | C54: Wait | G54: Travelkore | L54: Wait | M54: 10
A55: Travelers
A56: bln687809 | B56: =COUNTA($B$1:B55) -> 51 | C56: Check Exist | G56: Travelkore | I56: xpath | J56: //button[text()='Accept All Cookies'] | L56: Exist | O56: Y
A57: =IF($D$56="PASSED","bln687809","N") -> N | B57: =COUNTA($B$1:B56) -> 52 | C57: Output Cookie | G57: Travelkore | I57: xpath | J57: //button[text()='Accept All Cookies'] | L57: Output | N57: innertext | O57: Y | R57: Accept All Cookies
A58: =A57 -> N | B58: =COUNTA($B$1:B57) -> 53 | C58: Cookies | G58: Travelkore | I58: xpath | J58: //button[@id='onetrust-accept-btn-handler'] | L58: js_click | O58: Y
A59: bln687809 | B59: =COUNTA($B$1:B58) -> 54 | C59: Click My Trip Panel dropdown | G59: Travelkore | I59: xpath | J59: //button[@type='button'] | K59: 0 | L59: js_click
A60: bln687809 | B60: =COUNTA($B$1:B59) -> 55 | C60: Wait | G60: Travelkore | L60: Wait | M60: 3
A61: bln687809 | B61: =COUNTA($B$1:B60) -> 56 | C61: Verify AOAD Premium is updated | G61: Travelkore | I61: xpath | J61: //p[contains(.,'$')] | K61: 1 | L61: Output | N61: innertext | R61: =S52 -> 0 | T61: Y
A62: bln687809 | B62: =COUNTA($B$1:B61) -> 57 | C62: Enter a birth date that does not match the age entered on the GAQ page. | G62: Travelkore | I62: xpath | J62: //input[@name='dateOfBirth'] | K62: 0 | L62: Set | M62: BirthDate1
A63: bln687809 | B63: =COUNTA($B$1:B62) -> 58 | C63: Click tab | G63: Travelkore | L63: SendKeys | M63: {TAB}
A64: bln687809 | B64: =COUNTA($B$1:B63) -> 59 | C64: Wait | G64: Travelkore | L64: Wait | M64: 10
A65: bln687809 | B65: =COUNTA($B$1:B64) -> 60 | C65: Click Close | G65: Travelkore | I65: xpath | J65: //button[@class='cmp-button'] | K65: 0 | L65: js_click
A66: bln687809 | B66: =COUNTA($B$1:B65) -> 61 | C66: Wait | G66: Travelkore | L66: Wait | M66: 5
A67: bln687809 | B67: =COUNTA($B$1:B66) -> 62 | C67: Go Back to Upgrades for Verification | G67: Travelkore | I67: xpath | J67: //a[@href='/add-ons'] | K67: 0 | L67: js_click
A68: =IF(OR(Global!B2="QA"),"bln687809","N") -> N | B68: =COUNTA($B$1:B67) -> 63 | C68: Compare AOAD Premium from previous quote (QA) | G68: Travelkore | I68: xpath | J68: //p[contains(.,'$')] | K68: 3 | L68: Output | N68: innertext | R68: =S49 -> 0 | T68: Y
A69: =IF(OR(Global!B2="PROD",Global!B2="UAT"),"bln687809","N") -> bln687809 | B69: =COUNTA($B$1:B68) -> 64 | C69: Compare AOAD Premium from previous quote (UAT/PROD) | G69: Travelkore | I69: xpath | J69: //p[contains(.,'$')] | K69: 3 | L69: Output | N69: innertext | R69: =S49 -> 0 | T69: Y
A70: bln687809 | B70: =COUNTA($B$1:B69) -> 65 | C70: Verify AOAD Amount is the same as previously selected | G70: Travelkore | I70: xpath | J70: //option[@data-cmp-claimantid='3'] | K70: 0 | L70: Output | N70: innertext | R70: =M47 -> AOAD3 | T70: Y
A71: bln687809 | B71: =COUNTA($B$1:B70) -> 66 | C71: Click My Trip Panel dropdown | G71: Travelkore | I71: xpath | J71: (//button[@type='button'])[1] | K71: 0 | L71: js_click
A72: bln687809 | B72: =COUNTA($B$1:B71) -> 67 | C72: Wait | G72: Travelkore | L72: Wait | M72: 3
A73: bln687809 | B73: =COUNTA($B$1:B72) -> 68 | C73: Compare AOAD Premium in My Trip Panel from previuous quote | G73: Travelkore | I73: xpath | J73: //p[contains(.,'$')] | K73: 1 | L73: Output | N73: innertext | R73: =S52 -> 0 | T73: Y
A74: bln687809 | B74: =COUNTA($B$1:B73) -> 69 | C74: Click Submit button | G74: Travelkore | I74: xpath | J74: //button[@type='SUBMIT'] | K74: 0 | L74: js_click
A75: bln687809 | B75: =COUNTA($B$1:B74) -> 70 | C75: Wait | G75: Travelkore | L75: Wait | M75: 10
A76: bln687809 | B76: =COUNTA($B$1:B75) -> 71 | C76: Enter First Name | G76: Travelkore | I76: xpath | J76: //input[@name='firstName'] | K76: 0 | L76: Set | M76: FirstName
A77: bln687809 | B77: =COUNTA($B$1:B76) -> 72 | C77: Enter Last Name | G77: Travelkore | I77: xpath | J77: //input[@name='lastName'] | K77: 0 | L77: Set | M77: LastName
A78: bln687809 | B78: =COUNTA($B$1:B77) -> 73 | C78: Enter Birth Date | G78: Travelkore | I78: xpath | J78: //input[@name='dateOfBirth'] | K78: 0 | L78: Set | M78: BirthDate1
A79: bln687809 | B79: =COUNTA($B$1:B78) -> 74 | C79: Click tab | G79: Travelkore | L79: SendKeys | M79: {TAB}
A80: bln687809 | B80: =COUNTA($B$1:B79) -> 75 | C80: Wait | G80: Travelkore | L80: Wait | M80: 2
A81: bln687809 | B81: =COUNTA($B$1:B80) -> 76 | C81: Enter Address | G81: Travelkore | I81: xpath | J81: //input[@name='address1'] | K81: 0 | L81: Set | M81: Address
A82: bln687809 | B82: =COUNTA($B$1:B81) -> 77 | C82: Enter City | G82: Travelkore | I82: xpath | J82: //input[@name='city'] | K82: 0 | L82: Set | M82: City
A83: bln687809 | B83: =COUNTA($B$1:B82) -> 78 | C83: Enter Zip Code | G83: Travelkore | I83: xpath | J83: //input[@name='postalCode'] | K83: 0 | L83: Set | M83: Zip
A84: bln687809 | B84: =COUNTA($B$1:B83) -> 79 | C84: Enter Phone | G84: Travelkore | I84: xpath | J84: //input[@name='dayPhone'] | K84: 0 | L84: Set | M84: Phone
A85: bln687809 | B85: =COUNTA($B$1:B84) -> 80 | C85: Enter Email | G85: Travelkore | I85: xpath | J85: //input[@name='email'] | K85: 0 | L85: Set | M85: Email
A86: bln687809 | B86: =COUNTA($B$1:B85) -> 81 | C86: Click Submit button | G86: Travelkore | I86: xpath | J86: //button[@type='SUBMIT'] | K86: 0 | L86: js_click
A87: bln687809 | B87: =COUNTA($B$1:B86) -> 82 | C87: Wait | G87: Travelkore | L87: Wait | M87: 10
A88: Payment
A89: bln687809 | B89: =COUNTA($B$1:B88) -> 83 | C89: Check Exist | G89: Travelkore | I89: xpath | J89: //button[text()='Accept All Cookies'] | L89: Exist | O89: Y
A90: =IF($D$89="PASSED","bln687809","N") -> N | B90: =COUNTA($B$1:B89) -> 84 | C90: Output Cookie | G90: Travelkore | I90: xpath | J90: //button[text()='Accept All Cookies'] | L90: Output | N90: innertext | O90: Y | R90: Accept All Cookies
A91: =A90 -> N | B91: =COUNTA($B$1:B90) -> 85 | C91: Cookies | G91: Travelkore | I91: xpath | J91: //button[@id='onetrust-accept-btn-handler'] | L91: js_click | O91: Y
A92: bln687809 | B92: =COUNTA($B$1:B91) -> 86 | C92: Enter Card Name | G92: Travelkore | I92: xpath | J92: //input[@name='cardName'] | K92: 0 | L92: Set | M92: CardName
A93: bln687809 | B93: =COUNTA($B$1:B92) -> 87 | C93: Change iFrame | G93: Travelkore | I93: xpath | K93: 0 | L93: switchtoframe
A94: bln687809 | B94: =COUNTA($B$1:B93) -> 88 | C94: Check Exist | G94: Travelkore | I94: xpath | J94: //button[text()='Accept All Cookies'] | L94: Exist | O94: Y
A95: =IF($D$94="PASSED","bln687809","N") -> N | B95: =COUNTA($B$1:B94) -> 89 | C95: Output Cookie | G95: Travelkore | I95: xpath | J95: //button[text()='Accept All Cookies'] | L95: Output | N95: innertext | O95: Y | R95: Accept All Cookies
A96: =A95 -> N | B96: =COUNTA($B$1:B95) -> 90 | C96: Cookies | G96: Travelkore | I96: xpath | J96: //button[@id='onetrust-accept-btn-handler'] | L96: js_click | O96: Y
A97: bln687809 | B97: =COUNTA($B$1:B96) -> 91 | C97: Enter Card Number | G97: Travelkore | I97: xpath | J97: //input[@name='tsep-cardNum'] | K97: 0 | L97: Set | M97: CardNumber
A98: bln687809 | B98: =COUNTA($B$1:B97) -> 92 | C98: Change iFrame | G98: Travelkore | K98: 0 | L98: switchtodefault
A99: bln687809 | B99: =COUNTA($B$1:B98) -> 93 | C99: Change iFrame | G99: Travelkore | K99: 0 | L99: switchtoframe
A100: N | B100: =COUNTA($B$1:B99) -> 94 | C100: Click tab | G100: Travelkore | L100: SendKeys | M100: {TAB}
...

Sheet Params_6
A1: Scenario | B1: blnExecute | C1: bln_TG | D1: blnQuit | E1: bln687809 | F1: DT_BrowserType | G1: Notes | H1: DT_URL | I1: DateToday | J1: PolicyNumber_OUT | K1: tripType | L1: Plan | M1: Destination | N1: Restricted | O1: Destination1 | P1: Destination2 | Q1: Destination3 | R1: Destination4 | S1: Destination5 | T1: Destination6 | U1: Destination7 | V1: Destination8 | W1: Destination9 | X1: Destination10 | Y1: Destination11 | Z1: Destination12 | AA1: Destination13 | AB1: Destination14 | AC1: Destination15 | AD1: Destination16 | AE1: Destination17 | AF1: Destination18 | AG1: Destination19 | AH1: Destination20 | AI1: Destination21 | AJ1: Destination22 | AK1: Destination23 | AL1: Destination24 | AM1: Destination25 | AN1: Destination26 | AO1: Destination27 | AP1: Destination28 | AQ1: Destination29 | AR1: Destination30 | AS1: Destination31 | AT1: Destination32 | AU1: Destination33 | AV1: DepDate | AW1: DepDate1 | AX1: DepDateValid | AY1: RetDate | AZ1: RetDate1 | BA1: RetDateValid | BB1: DepoDate | BC1: DepoYearInvalid | BD1: DepoYearValid | BE1: DepoMonthInvalid | BF1: DepoMonthValid | BG1: DepoDayInvalid | BH1: DepoDayValid | BI1: Residence | BJ1: Residence1 | BK1: Residence2 | BL1: Residence3 | BM1: Residence4 | BN1: Residence5 | BO1: Residence6 | BP1: Residence7 | BQ1: Residence8 | BR1: Residence9 | BS1: Residence10 | BT1: Residence11 | BU1: Residence12 | BV1: Residence13 | BW1: Residence14 | BX1: Residence15 | BY1: Residence16 | BZ1: Residence17 | CA1: Residence18 | CB1: Residence19 | CC1: Residence20 | CD1: Residence21 | CE1: Residence22 | CF1: Residence23 | CG1: Residence24 | CH1: Residence25 | CI1: Residence26 | CJ1: Residence27 | CK1: Residence28 | CL1: Residence29 | CM1: Residence30 | CN1: Residence31 | CO1: Residence32 | CP1: Residence33 | CQ1: Residence34 | CR1: Residence35 | CS1: Residence36 | CT1: Residence37 | CU1: Residence38 | CV1: Residence39 | CW1: Residence40 | CX1: Residence41 | CY1: Residence42 | CZ1: Residence43 | DA1: Residence44 | DB1: Residence45 | DC1: Residence46 | DD1: Residence47 | DE1: Residence48 | DF1: Residence49 | DG1: Residence50 | DH1: Residence51 | DI1: Residence52 | DJ1: Residence53 | DK1: Age | DL1: Cost | DM1: CostAllowed | DN1: Age1 | DO1: Cost1 | DP1: Trav_FirstName1 | DQ1: Trav_LastName1 | DR1: Trav_BirthDate1 | DS1: Age2 | DT1: Cost2 | DU1: Trav_FirstName2 | DV1: Trav_LastName2 | DW1: Trav_BirthDate2 | DX1: Age3 | DY1: Cost3 | DZ1: Trav_FirstName3 | EA1: Trav_LastName3 | EB1: Trav_BirthDate3 | EC1: Age4 | ED1: Cost4 | EE1: Trav_FirstName4 | EF1: Trav_LastName4 | EG1: Trav_BirthDate4 | EH1: Age5 | EI1: Cost5 | EJ1: Trav_FirstName5 | EK1: Trav_LastName5 | EL1: Trav_BirthDate5 | EM1: Age6 | EN1: Cost6 | EO1: Trav_FirstName6 | EP1: Trav_LastName6 | EQ1: Trav_BirthDate6 | ER1: Age7 | ES1: Cost7 | ET1: Trav_FirstName7 | EU1: Trav_LastName7 | EV1: Trav_BirthDate7 | EW1: Age8 | EX1: Cost8 | EY1: Trav_FirstName8 | EZ1: Trav_LastName8 | FA1: Trav_BirthDate8 | FB1: Age9 | FC1: Cost9 | FD1: Trav_FirstName9 | FE1: Trav_LastName9 | FF1: Trav_BirthDate9 | FG1: AOAD1 | FH1: AOAD2 | FI1: AOAD3 | FJ1: PickUpDate | FK1: DropOffDate | FL1: PickUpDate1 | FM1: DropOffDate1 | FN1: PickUpDate2 | FO1: DropOffDate2 | FP1: PickUpDate3 | FQ1: DropOffDate3 | FR1: PickUpDate4 | FS1: DropOffDate4 | FT1: FirstName | FU1: LastName | FV1: BirthDate | FW1: BirthDate2 | FX1: BirthDate1 | FY1: Address | FZ1: City | GA1: Zip | GB1: ZipX | GC1: City1 | GD1: Zip1 | GE1: Phone | GF1: Phone1 | GG1: Email | GH1: Email1 | GI1: OwnerPhone | GJ1: CardName | GK1: CardNumber | GL1: CardNumber1 | GM1: ExpiryMonth | GN1: ExpiryYear | GO1: Cost_OUT | GP1: Cost_RES | GQ1: Destination_OUT | GR1: Destination_RES | GS1: Plan | GT1: Plan_OUT | GU1: Plan_RES | GV1: Plan1 | GW1: Plan1_OUT | GX1: Plan_RES | GY1: Plan2 | GZ1: Plan2_OUT | HA1: Plan_RES | HB1: ErrorMessage | HC1: ErrorMessage_OUT | HD1: ErrorMessage_RES | HE1: ErrorMessage1 | HF1: ErrorMessage1_OUT | HG1: ErrorMessage_RES | HH1: ErrorMessage2 | HI1: ErrorMessage2_OUT | HJ1: ErrorMessage_RES | HK1: ErrorMessage3 | HL1: ErrorMessage3_OUT | HM1: ErrorMessage_RES | HN1: Tooltip | HO1: Tooltip_OUT | HP1: Tooltip_RES | HQ1: Tooltip1 | HR1: Tooltip1_OUT | HS1: Tooltip1_RES | HT1: Tooltip2 | HU1: Tooltip2_OUT | HV1: Tooltip2_RES | HW1: FAQ1 | HX1: FAQ1_OUT | HY1: FAQ1_RES | HZ1: FAQ2 | IA1: FAQ2_OUT | IB1: FAQ2_RES | IC1: FAQ3 | ID1: FAQ3_OUT | IE1: FAQ3_RES | IF1: FAQ4 | IG1: FAQ4_OUT | IH1: FAQ4_RES | II1: FAQ5 | IJ1: FAQ5_OUT | IK1: FAQ5_RES | IL1: OwnerAdvantagePlan_OUT | IM1: RentalCarDamagePlan_OUT | IN1: OwnerAdvantagePlan_VERIFY | IO1: RentalCarDamage_VERIFY
A2: bln687809 | B2: Y | C2: Y | D2: Y | E2: Y | F2: Chrome | G2: TC_687809 | H2: {=_xlfn.IFS(Global!B2="QA","https://travelkore.qa.insurancebytravelex.com",Global!B2="UAT","https://travelkore.uat.insurancebytravelex.com",Global!B2="PROD","https://travelkore.insurancebytravelex.com/")} -> https://travelkore.uat.insurancebytravelex.com | I2: =TODAY() -> 46266 | L2: Travel Med Go | M2: Mexico | O2: Australia | AV2: =TEXT(I2+1,"mm/dd/yyyy") -> 09/02/2026 | AW2: =TEXT(I2+7,"mm/dd/yyyy") -> 09/08/2026 | AX2: =TEXT(I2+7,"mm/dd/yyyy") -> 09/08/2026 | AY2: =TEXT(AV2+59,"mm/dd/yyyy") -> 10/31/2026 | AZ2: =TEXT(AW2+14,"mm/dd/yyyy") -> 09/22/2026 | BA2: =TEXT(AV2+14,"mm/dd/yyyy") -> 09/16/2026 | BB2: =TEXT(I2-1,"mm/dd/yyyy") -> 08/31/2026 | BI2: California | BJ2: Nebraska | BK2: New York | DK2: 110 | DL2: 1000 | DM2: 100 | DN2: 18 | DO2: 1500 | DP2: ="QAFIRSTNAME"&CHAR(RANDBETWEEN(65,90))&CHAR(RANDBETWEEN(65,90)) -> QAFIRSTNAMEUE | DQ2: ="QALASTNAME"&CHAR(RANDBETWEEN(65,90))&CHAR(RANDBETWEEN(65,90)) -> QALASTNAMESN | DR2: =TEXT(DATE(YEAR(TODAY())-DS2,MONTH(TODAY()),DAY(TODAY())),"MM/DD/YYYY") -> 09/01/1971 | DS2: 55 | FG2: $200,000 | FH2: $500,000 | FI2: $1,000,000 | FJ2: =TEXT(AX2,"mm/dd/yyyy") -> 09/08/2026 | FK2: =TEXT(AX2+1,"mm/dd/yyyy") -> 09/09/2026 | FL2: =TEXT(FK2+1,"mm/dd/yyyy") -> 09/10/2026 | FM2: =TEXT(FL2+1,"mm/dd/yyyy") -> 09/11/2026 | FN2: =TEXT(FM2+1,"mm/dd/yyyy") -> 09/12/2026 | FO2: =TEXT(FN2+1,"mm/dd/yyyy") -> 09/13/2026 | FP2: =TEXT(FO2+7,"mm/dd/yyyy") -> 09/20/2026 | FQ2: =TEXT(FP2+1,"mm/dd/yyyy") -> 09/21/2026 | FR2: =TEXT(FQ2+1,"mm/dd/yyyy") -> 09/22/2026 | FS2: =TEXT(FR2+1,"mm/dd/yyyy") -> 09/23/2026 | FT2: ="QAFIRSTNAME"&CHAR(RANDBETWEEN(65,90))&CHAR(RANDBETWEEN(65,90)) -> QAFIRSTNAMEER | FU2: ="QALASTNAME"&CHAR(RANDBETWEEN(65,90))&CHAR(RANDBETWEEN(65,90)) -> QALASTNAMEGN | FV2: =TEXT(DATE(YEAR(TODAY())-DK2,MONTH(TODAY()),DAY(TODAY())),"MM/DD/YYYY") -> 09/01/1916 | FW2: =TEXT(DATE(YEAR(TODAY())-DS2,MONTH(TODAY()),DAY(TODAY())),"MM/DD/YYYY") -> 09/01/1971 | FX2: =TEXT(DATE(YEAR(TODAY())-DN2,MONTH(TODAY()),DAY(TODAY())),"MM/DD/YYYY") -> 09/01/2008 | FY2: QA213 COR246 | FZ2: Los Angeles | GA2: 90001 | GB2: 12345 | GC2: Omaha | GD2: 68102 | GE2: 1234567897 | GF2: 2222222222 | GG2: qa@travelexinsurance.com | GH2: qa@travelguard.com | GI2: qwertyuiopasdfgh | GJ2: QA Test | GK2: 4111111111111111 | GM2: 12 | GN2: 2030

Sheet ANZ
A1: blnExecute | B1: Step_Number | C1: Step_Name | D1: Status | E1: Error_Check | F1: breakpoint | G1: Test_Case | H1: Page | I1: FindBy | J1: FindBy_Value | K1: Index | L1: Method | M1: Value | N1: Output_Property | O1: Ignore_not_existing_object | P1: isDisabled | Q1: Timeout | R1: Expected_Value | S1: Output_Value | T1: Exact_Match | U1: Contains | V1: ITERATION_NO | W1: Notes | X1: Start_Time | Y1: End_Time | Z1: Duration
A2: Open Air New Zealand URL
A3: =IF(OR(Global!B25="N"),"N","bln694769") -> N | B3: =COUNTA($B$1:B2) -> 1 | C3: Open Browser | G3: Air New Zealand | L3: Wait | M3: 1 | O3: Y | R3: DT_URL
A4: =IF(OR(Global!B25="N"),"N","bln694769") -> N | B4: =COUNTA($B$1:B3) -> 2 | C4: Headless | G4: Air New Zealand | H4: DT_BrowserType | L4: Open | M4: ="URL:="&R3&";;HEADLESS:=TRUE" -> URL:=DT_URL;;HEADLESS:=TRUE | Q4: 60
A5: =IF(OR(Global!B25="Y"),"N","bln694769") -> bln694769 | B5: =COUNTA($B$1:B4) -> 3 | C5: Open Browser | G5: Air New Zealand | H5: DT_BrowserType | L5: Open | M5: DT_URL | Q5: 60
A6: N | B6: =COUNTA($B$1:B5) -> 4 | C6: Wait | G6: Air New Zealand | L6: Wait | M6: 5
A7: N | B7: =COUNTA($B$1:B6) -> 5 | C7: Zscaler Sign in Email | G7: Air New Zealand | I7: xpath | J7: //input[@id='okta-signin-username'] | K7: 0 | L7: Set | M7: DT_ZScalerUser | O7: Y | Q7: 5
A8: N | B8: =COUNTA($B$1:B7) -> 6 | C8: Zscaler Password | G8: Air New Zealand | I8: xpath | J8: //input[@id='okta-signin-password'] | K8: 0 | L8: Set | M8: DT_ZScalerPassword | O8: Y
A9: N | B9: =COUNTA($B$1:B8) -> 7 | C9: Click Sign in | G9: Air New Zealand | I9: xpath | J9: //input[@id='okta-signin-submit'] | K9: 0 | L9: Click | O9: Y
A10: N | B10: =COUNTA($B$1:B9) -> 8 | C10: Wait | G10: Air New Zealand | L10: Wait | M10: 5
A11: Home Page - GAQ
A12: bln694769 | B12: =COUNTA($B$1:B11) -> 9 | C12: Switch to Frame | G12: Air New Zealand | L12: SWITCHTOFRAME | M12: aemFormFrame
A13: bln694769 | B13: =COUNTA($B$1:B12) -> 10 | C13: Check Exist | G13: Air New Zealand | I13: xpath | J13: //button[text()='Accept All Cookies'] | L13: Exist | O13: Y
A14: bln694769 | B14: =COUNTA($B$1:B13) -> 11 | C14: Output Cookie | G14: Air New Zealand | I14: xpath | J14: //button[text()='Accept All Cookies'] | L14: Output | N14: innertext | O14: Y | R14: Accept All Cookies
A15: bln694769 | B15: =COUNTA($B$1:B14) -> 12 | C15: Cookies | G15: Air New Zealand | I15: xpath | J15: //button[@id='onetrust-accept-btn-handler'] | L15: js_click | O15: Y
A16: bln694769 | B16: =COUNTA($B$1:B15) -> 13 | C16: Click Destination | G16: Air New Zealand | I16: xpath | J16: //input[@id='cmp-Input' and @placeholder='Select a country or region'] | K16: 0 | L16: Click
A17: bln694769 | B17: =COUNTA($B$1:B16) -> 14 | C17: Wait | G17: Air New Zealand | L17: Wait | M17: 2
A18: bln694769 | B18: =COUNTA($B$1:B17) -> 15 | C18: Write Destination | G18: Air New Zealand | I18: xpath | J18: //input[@id='cmp-Input' and @placeholder='Select a country or region'] | K18: 0 | L18: Write | M18: Destination
A19: bln694769 | B19: =COUNTA($B$1:B18) -> 16 | C19: Wait | G19: Air New Zealand | L19: Wait | M19: 2
A20: bln694769 | B20: =COUNTA($B$1:B19) -> 17 | C20: Click Destination | G20: Air New Zealand | I20: xpath | J20: ="//a[contains(.,'"&M18&"')]" -> //a[contains(.,'Destination')] | K20: 0 | L20: js_click
A21: bln694769 | B21: =COUNTA($B$1:B20) -> 18 | C21: Departure Date | G21: Air New Zealand | I21: xpath | J21: //input[@name='tripDepartureDate'] | K21: 0 | L21: Set | M21: DepDate
A22: bln694769 | B22: =COUNTA($B$1:B21) -> 19 | C22: Return Date | G22: Air New Zealand | I22: xpath | J22: //input[@name='tripReturnDate'] | K22: 0 | L22: Set | M22: RetDate
A23: bln694769 | B23: =COUNTA($B$1:B22) -> 20 | C23: Deposit Date | G23: Air New Zealand | I23: xpath | J23: //input[@name='tripDepositDate'] | K23: 0 | L23: Set | M23: DepoDate
A24: bln694769 | B24: =COUNTA($B$1:B23) -> 21 | C24: Click State | G24: Air New Zealand | I24: xpath | J24: //input[@id='cmp-Input' and @placeholder='Select your state'] | K24: 0 | L24: Click
A25: bln694769 | B25: =COUNTA($B$1:B24) -> 22 | C25: Wait | G25: Air New Zealand | L25: Wait | M25: 2
A26: bln694769 | B26: =COUNTA($B$1:B25) -> 23 | C26: Write State | G26: Air New Zealand | I26: xpath | J26: //input[@id='cmp-Input' and @placeholder='Select your state'] | K26: 0 | L26: Write | M26: Residence
A27: bln694769 | B27: =COUNTA($B$1:B26) -> 24 | C27: Wait | G27: Air New Zealand | L27: Wait | M27: 2
A28: bln694769 | B28: =COUNTA($B$1:B27) -> 25 | C28: Click Residence | G28: Air New Zealand | I28: xpath | J28: ="//a[contains(.,'"&M26&"')]" -> //a[contains(.,'Residence')] | K28: 0 | L28: js_click
A29: bln694769 | B29: =COUNTA($B$1:B28) -> 26 | C29: Enter Age | G29: Air New Zealand | I29: xpath | J29: (//input[@name='insuredAge'])[1] | K29: 0 | L29: Set | M29: Age
A30: bln694769 | B30: =COUNTA($B$1:B29) -> 27 | C30: Enter Trip Cost | G30: Air New Zealand | I30: xpath | J30: (//input[@name='display_tripCost'])[1] | K30: 0 | L30: Set | M30: Cost
A31: bln694769 | B31: =COUNTA($B$1:B30) -> 28 | C31: Click Submit button | G31: Air New Zealand | I31: xpath | J31: //button[@type='SUBMIT'] | K31: 0 | L31: js_click
A32: Plan Options
A33: bln694769 | B33: =COUNTA($B$1:B32) -> 29 | C33: Wait | G33: Air New Zealand | L33: Wait | M33: 10
A34: bln694769 | B34: =COUNTA($B$1:B33) -> 30 | C34: Check Exist | G34: Air New Zealand | I34: xpath | J34: //button[text()='Accept All Cookies'] | L34: Exist | O34: Y
A35: bln694769 | B35: =COUNTA($B$1:B34) -> 31 | C35: Output Cookie | G35: Air New Zealand | I35: xpath | J35: //button[text()='Accept All Cookies'] | L35: Output | N35: innertext | O35: Y | R35: Accept All Cookies
A36: bln694769 | B36: =COUNTA($B$1:B35) -> 32 | C36: Cookies | G36: Air New Zealand | I36: xpath | J36: //button[@id='onetrust-accept-btn-handler'] | L36: js_click | O36: Y
A37: bln694769 | B37: =COUNTA($B$1:B36) -> 33 | C37: Click the My Trip dropdown | G37: Air New Zealand | I37: xpath | J37: (//button[@type='button'])[2] | L37: Wait | M37: 5
A38: bln694769 | B38: =COUNTA($B$1:B37) -> 34 | C38: Travel Protection Plan | G38: Air New Zealand | I38: xpath | J38: //button[@name='selectPlan' and @value='805ZA-0224'] | K38: 0 | L38: js_click
A39: bln694769 | B39: =COUNTA($B$1:B38) -> 35 | C39: Wait | G39: Air New Zealand | L39: Wait | M39: 10
A40: Travelers Information
A41: bln694769 | B41: =COUNTA($B$1:B40) -> 36 | C41: Check Exist | G41: Air New Zealand | I41: xpath | J41: //button[text()='Accept All Cookies'] | L41: Exist | O41: Y
A42: bln694769 | B42: =COUNTA($B$1:B41) -> 37 | C42: Output Cookie | G42: Air New Zealand | I42: xpath | J42: //button[text()='Accept All Cookies'] | L42: Output | N42: innertext | O42: Y | R42: Accept All Cookies
A43: bln694769 | B43: =COUNTA($B$1:B42) -> 38 | C43: Cookies | G43: Air New Zealand | I43: xpath | J43: //button[@id='onetrust-accept-btn-handler'] | L43: js_click | O43: Y
A44: bln694769 | B44: =COUNTA($B$1:B43) -> 39 | C44: Click the My Trip dropdown | G44: Air New Zealand | I44: xpath | J44: (//button[@type='button'])[1] | L44: Wait | M44: 5
A45: bln694769 | B45: =COUNTA($B$1:B44) -> 40 | C45: Enter First Name | G45: Air New Zealand | I45: xpath | J45: //input[@name='firstName'] | K45: 0 | L45: Set | M45: FirstName
A46: bln694769 | B46: =COUNTA($B$1:B45) -> 41 | C46: Enter Last Name | G46: Air New Zealand | I46: xpath | J46: //input[@name='lastName'] | K46: 0 | L46: Set | M46: LastName
A47: bln694769 | B47: =COUNTA($B$1:B46) -> 42 | C47: Enter Birth Date | G47: Air New Zealand | I47: xpath | J47: //input[@name='dateOfBirth'] | K47: 0 | L47: Set | M47: BirthDate
A48: bln694769 | B48: =COUNTA($B$1:B47) -> 43 | C48: Click tab | G48: Air New Zealand | L48: SendKeys | M48: {TAB}
A49: bln694769 | B49: =COUNTA($B$1:B48) -> 44 | C49: Wait | G49: Air New Zealand | L49: Wait | M49: 3
A50: bln694769 | B50: =COUNTA($B$1:B49) -> 45 | C50: Enter Address | G50: Air New Zealand | I50: xpath | J50: //input[@name='address1'] | K50: 0 | L50: Set | M50: Address
A51: bln694769 | B51: =COUNTA($B$1:B50) -> 46 | C51: Enter City | G51: Air New Zealand | I51: xpath | J51: //input[@name='city'] | K51: 0 | L51: Set | M51: City
A52: bln694769 | B52: =COUNTA($B$1:B51) -> 47 | C52: Enter Zip Code | G52: Air New Zealand | I52: xpath | J52: //input[@name='postalCode'] | K52: 0 | L52: Set | M52: Zip
A53: bln694769 | B53: =COUNTA($B$1:B52) -> 48 | C53: Enter Phone | G53: Air New Zealand | I53: xpath | J53: //input[@name='dayPhone'] | K53: 0 | L53: Set | M53: Phone
A54: bln694769 | B54: =COUNTA($B$1:B53) -> 49 | C54: Enter Email | G54: Air New Zealand | I54: xpath | J54: //input[@name='email'] | K54: 0 | L54: Set | M54: Email
A55: bln694769 | B55: =COUNTA($B$1:B54) -> 50 | C55: Enter Koru Membership Number | G55: Air New Zealand | I55: xpath | J55: //input[@name='ownerNumber'] | K55: 0 | L55: Set | M55: KoruMembershipNumber
A56: bln694769 | B56: =COUNTA($B$1:B55) -> 51 | C56: Click Submit button | G56: Air New Zealand | I56: xpath | J56: //button[@type='SUBMIT'] | K56: 0 | L56: js_click
A57: bln694769 | B57: =COUNTA($B$1:B56) -> 52 | C57: Wait | G57: Air New Zealand | L57: Wait | M57: 10
A58: Payment
A59: bln694769 | B59: =COUNTA($B$1:B58) -> 53 | C59: Check Exist | G59: Air New Zealand | I59: xpath | J59: //button[text()='Accept All Cookies'] | L59: Exist | O59: Y
A60: bln694769 | B60: =COUNTA($B$1:B59) -> 54 | C60: Output Cookie | G60: Air New Zealand | I60: xpath | J60: //button[text()='Accept All Cookies'] | L60: Output | N60: innertext | O60: Y | R60: Accept All Cookies
A61: bln694769 | B61: =COUNTA($B$1:B60) -> 55 | C61: Cookies | G61: Air New Zealand | I61: xpath | J61: //button[@id='onetrust-accept-btn-handler'] | L61: js_click | O61: Y
A62: bln694769 | B62: =COUNTA($B$1:B61) -> 56 | C62: Enter Card Name | G62: Air New Zealand | I62: xpath | J62: //input[@name='cardName'] | K62: 0 | L62: Set | M62: CardName
A63: bln694769 | B63: =COUNTA($B$1:B62) -> 57 | C63: Change iFrame | G63: Air New Zealand | I63: xpath | K63: 0 | L63: switchtoframe
A64: bln694769 | B64: =COUNTA($B$1:B63) -> 58 | C64: Check Exist | G64: Air New Zealand | I64: xpath | J64: //button[text()='Accept All Cookies'] | L64: Exist | O64: Y
A65: bln694769 | B65: =COUNTA($B$1:B64) -> 59 | C65: Output Cookie | G65: Air New Zealand | I65: xpath | J65: //button[text()='Accept All Cookies'] | L65: Output | N65: innertext | O65: Y | R65: Accept All Cookies
A66: bln694769 | B66: =COUNTA($B$1:B65) -> 60 | C66: Cookies | G66: Air New Zealand | I66: xpath | J66: //button[@id='onetrust-accept-btn-handler'] | L66: js_click | O66: Y
A67: bln694769 | B67: =COUNTA($B$1:B66) -> 61 | C67: Enter Card Number | G67: Air New Zealand | I67: xpath | J67: //input[@name='tsep-cardNum'] | K67: 0 | L67: Set | M67: CardNumber
A68: bln694769 | B68: =COUNTA($B$1:B67) -> 62 | C68: Change iFrame | G68: Air New Zealand | K68: 0 | L68: switchtodefault
A69: bln694769 | B69: =COUNTA($B$1:B68) -> 63 | C69: Change iFrame | G69: Air New Zealand | K69: 0 | L69: switchtoframe
A70: N | B70: =COUNTA($B$1:B69) -> 64 | C70: Click tab | G70: Air New Zealand | L70: SendKeys | M70: {TAB}
A71: N | B71: =COUNTA($B$1:B70) -> 65 | C71: Enter Card Expiry Month | G71: Air New Zealand | L71: SendKeys | M71: ExpiryMonth
A72: N | B72: =COUNTA($B$1:B71) -> 66 | C72: Enter Card Expiry Year | G72: Air New Zealand | L72: SendKeys | M72: ExpiryYear
A73: bln694769 | B73: =COUNTA($B$1:B72) -> 67 | C73: Click Expiry Date | G73: Air New Zealand | I73: xpath | J73: //input[@name='tsep-datepicker'] | K73: 0 | L73: Click
A74: bln694769 | B74: =COUNTA($B$1:B73) -> 68 | C74: Wait | G74: Air New Zealand | L74: Wait | M74: 2
A75: bln694769 | B75: =COUNTA($B$1:B74) -> 69 | C75: Input Expiry Month | G75: Air New Zealand | I75: xpath | J75: //input[@name='tsep-datepicker'] | K75: 0 | L75: Type | M75: ExpiryMonth
A76: bln694769 | B76: =COUNTA($B$1:B75) -> 70 | C76: Input Expiry Year | G76: Air New Zealand | I76: xpath | J76: //input[@name='tsep-datepicker'] | K76: 0 | L76: Type | M76: ExpiryYear
A77: bln694769 | B77: =COUNTA($B$1:B76) -> 71 | C77: Wait | G77: Air New Zealand | L77: Wait | M77: 2
A78: bln694769 | B78: =COUNTA($B$1:B77) -> 72 | C78: Change iFrame | G78: Air New Zealand | K78: 0 | L78: switchtodefault
A79: bln694769 | B79: =COUNTA($B$1:B78) -> 73 | C79: Wait | G79: Air New Zealand | L79: Wait | M79: 2
A80: bln694769 | B80: =COUNTA($B$1:B79) -> 74 | C80: I Agree | G80: Air New Zealand | I80: xpath | J80: //input[@value='I agree'] | K80: 0 | L80: Tick
A81: bln694769 | B81: =COUNTA($B$1:B80) -> 75 | C81: Wait | G81: Air New Zealand | L81: Wait | M81: 2
A82: Home Page - GAQ Edit/Restart
A83: bln694769 | B83: =COUNTA($B$1:B81) -> 76 | C83: Click Get a Quote | G83: Air New Zealand | I83: xpath | J83: //a[contains(.,'Get Quote')] | K83: 0 | L83: js_click
A84: bln694769 | B84: =COUNTA($B$1:B83) -> 77 | C84: Wait | G84: Air New Zealand | L84: Wait | M84: 3
A85: bln694769 | B85: =COUNTA($B$1:B84) -> 78 | C85: Click Destination | G85: Air New Zealand | I85: xpath | J85: (//input[@id='cmp-Input'])[1] | K85: 0 | L85: Click
A86: bln694769 | B86: =COUNTA($B$1:B85) -> 79 | C86: Wait | G86: Air New Zealand | L86: Wait | M86: 2
A87: bln694769 | B87: =COUNTA($B$1:B86) -> 80 | C87: Write Destination | G87: Air New Zealand | I87: xpath | J87: (//input[@id='cmp-Input' and @class='inputField'])[1] | K87: 0 | L87: Write | M87: Destination1
A88: bln694769 | B88: =COUNTA($B$1:B87) -> 81 | C88: Wait | G88: Air New Zealand | L88: Wait | M88: 2
A89: bln694769 | B89: =COUNTA($B$1:B88) -> 82 | C89: Click Destination | G89: Air New Zealand | I89: xpath | J89: ="//a[contains(.,'"&M87&"')]" -> //a[contains(.,'Destination1')] | K89: 0 | L89: js_click
A90: bln694769 | B90: =COUNTA($B$1:B89) -> 83 | C90: Departure Date | G90: Air New Zealand | I90: xpath | J90: //input[@name='tripDepartureDate'] | K90: 0 | L90: Set | M90: DepDate1
A91: bln694769 | B91: =COUNTA($B$1:B90) -> 84 | C91: Return Date | G91: Air New Zealand | I91: xpath | J91: //input[@name='tripReturnDate'] | K91: 0 | L91: Set | M91: RetDate1
A92: bln694769 | B92: =COUNTA($B$1:B91) -> 85 | C92: Click State | G92: Air New Zealand | I92: xpath | J92: (//input[@id='cmp-Input'])[2] | K92: 0 | L92: Click
A93: bln694769 | B93: =COUNTA($B$1:B92) -> 86 | C93: Wait | G93: Air New Zealand | L93: Wait | M93: 2
A94: bln694769 | B94: =COUNTA($B$1:B93) -> 87 | C94: Write State | G94: Air New Zealand | I94: xpath | J94: (//input[@id='cmp-Input' and @class='inputField'])[2] | K94: 0 | L94: Write | M94: Residence1
A95: bln694769 | B95: =COUNTA($B$1:B94) -> 88 | C95: Wait | G95: Air New Zealand | L95: Wait | M95: 2
A96: bln694769 | B96: =COUNTA($B$1:B95) -> 89 | C96: Click Residence | G96: Air New Zealand | I96: xpath | J96: ="//a[contains(.,'"&M94&"')]" -> //a[contains(.,'Residence1')] | K96: 0 | L96: js_click
A97: bln694769 | B97: =COUNTA($B$1:B96) -> 90 | C97: Enter Age | G97: Air New Zealand | I97: xpath | J97: //input[@name='insuredAge'] | K97: 0 | L97: Set | M97: Age
A98: bln694769 | B98: =COUNTA($B$1:B97) -> 91 | C98: Enter Trip Cost | G98: Air New Zealand | I98: xpath | J98: (//input[@name='display_tripCost'])[1] | K98: 0 | L98: Set | M98: Cost | T98: Y
A99: bln694769 | B99: =COUNTA($B$1:B98) -> 92 | C99: Click Add | G99: Air New Zealand | I99: xpath | J99: //button[@type='button'and @aria-label='addButtonBelow'] | K99: 0 | L99: js_click
A100: bln694769 | B100: =COUNTA($B$1:B99) -> 93 | C100: Enter Age 1 | G100: Air New Zealand | I100: xpath | J100: (//input[@name='insuredAge'])[2] | K100: 0 | L100: Set | M100: Age1 | T100: Y
...

Sheet Params_7
A1: Scenario | B1: blnExecute | C1: bln_TG | D1: blnQuit | E1: bln694769 | F1: DT_BrowserType | G1: Notes | H1: DT_URL | I1: DateToday | J1: PolicyNumber_OUT | K1: tripType | L1: Plan | M1: Destination | N1: Restricted | O1: Destination1 | P1: Destination2 | Q1: Destination3 | R1: Destination4 | S1: Destination5 | T1: Destination6 | U1: Destination7 | V1: Destination8 | W1: Destination9 | X1: Destination10 | Y1: Destination11 | Z1: Destination12 | AA1: Destination13 | AB1: Destination14 | AC1: Destination15 | AD1: Destination16 | AE1: Destination17 | AF1: Destination18 | AG1: Destination19 | AH1: Destination20 | AI1: Destination21 | AJ1: Destination22 | AK1: Destination23 | AL1: Destination24 | AM1: Destination25 | AN1: Destination26 | AO1: Destination27 | AP1: Destination28 | AQ1: Destination29 | AR1: Destination30 | AS1: Destination31 | AT1: Destination32 | AU1: Destination33 | AV1: DepDate | AW1: DepDate1 | AX1: DepDateValid | AY1: RetDate | AZ1: RetDate1 | BA1: RetDateValid | BB1: DepoDate | BC1: DepoYearInvalid | BD1: DepoYearValid | BE1: DepoMonthInvalid | BF1: DepoMonthValid | BG1: DepoDayInvalid | BH1: DepoDayValid | BI1: Residence | BJ1: Residence1 | BK1: Residence2 | BL1: Residence3 | BM1: Residence4 | BN1: Residence5 | BO1: Residence6 | BP1: Residence7 | BQ1: Residence8 | BR1: Residence9 | BS1: Residence10 | BT1: Residence11 | BU1: Residence12 | BV1: Residence13 | BW1: Residence14 | BX1: Residence15 | BY1: Residence16 | BZ1: Residence17 | CA1: Residence18 | CB1: Residence19 | CC1: Residence20 | CD1: Residence21 | CE1: Residence22 | CF1: Residence23 | CG1: Residence24 | CH1: Residence25 | CI1: Residence26 | CJ1: Residence27 | CK1: Residence28 | CL1: Residence29 | CM1: Residence30 | CN1: Residence31 | CO1: Residence32 | CP1: Residence33 | CQ1: Residence34 | CR1: Residence35 | CS1: Residence36 | CT1: Residence37 | CU1: Residence38 | CV1: Residence39 | CW1: Residence40 | CX1: Residence41 | CY1: Residence42 | CZ1: Residence43 | DA1: Residence44 | DB1: Residence45 | DC1: Residence46 | DD1: Residence47 | DE1: Residence48 | DF1: Residence49 | DG1: Residence50 | DH1: Residence51 | DI1: Residence52 | DJ1: Residence53 | DK1: Age | DL1: Cost | DM1: CostAllowed | DN1: Age1 | DO1: Cost1 | DP1: Trav_FirstName1 | DQ1: Trav_LastName1 | DR1: Trav_BirthDate1 | DS1: Age2 | DT1: Cost2 | DU1: Trav_FirstName2 | DV1: Trav_LastName2 | DW1: Trav_BirthDate2 | DX1: Age3 | DY1: Cost3 | DZ1: Trav_FirstName3 | EA1: Trav_LastName3 | EB1: Trav_BirthDate3 | EC1: Age4 | ED1: Cost4 | EE1: Trav_FirstName4 | EF1: Trav_LastName4 | EG1: Trav_BirthDate4 | EH1: Age5 | EI1: Cost5 | EJ1: Trav_FirstName5 | EK1: Trav_LastName5 | EL1: Trav_BirthDate5 | EM1: Age6 | EN1: Cost6 | EO1: Trav_FirstName6 | EP1: Trav_LastName6 | EQ1: Trav_BirthDate6 | ER1: Age7 | ES1: Cost7 | ET1: Trav_FirstName7 | EU1: Trav_LastName7 | EV1: Trav_BirthDate7 | EW1: Age8 | EX1: Cost8 | EY1: Trav_FirstName8 | EZ1: Trav_LastName8 | FA1: Trav_BirthDate8 | FB1: Age9 | FC1: Cost9 | FD1: Trav_FirstName9 | FE1: Trav_LastName9 | FF1: Trav_BirthDate9 | FG1: PickUpDate | FH1: DropOffDate | FI1: PickUpDate1 | FJ1: DropOffDate1 | FK1: PickUpDate2 | FL1: DropOffDate2 | FM1: PickUpDate3 | FN1: DropOffDate3 | FO1: PickUpDate4 | FP1: DropOffDate4 | FQ1: FirstName | FR1: LastName | FS1: BirthDate | FT1: BirthDateInvalid | FU1: BirthDate1 | FV1: Address | FW1: City | FX1: Zip | FY1: ZipX | FZ1: City1 | GA1: Zip1 | GB1: Phone | GC1: Phone1 | GD1: Email | GE1: Email1 | GF1: OwnerPhone | GG1: ReservationConfirmationNumber | GH1: CardName | GI1: CardNumber | GJ1: CardNumber1 | GK1: ExpiryMonth | GL1: ExpiryYear | GM1: Cost_OUT | GN1: Cost_RES | GO1: Destination_OUT | GP1: Destination_RES | GQ1: Plan | GR1: Plan_OUT | GS1: Plan_RES | GT1: Plan1 | GU1: Plan1_OUT | GV1: Plan_RES | GW1: Plan2 | GX1: Plan2_OUT | GY1: Plan_RES | GZ1: ErrorMessage | HA1: ErrorMessage_OUT | HB1: ErrorMessage_RES | HC1: ErrorMessage1 | HD1: ErrorMessage1_OUT | HE1: ErrorMessage_RES | HF1: ErrorMessage2 | HG1: ErrorMessage2_OUT | HH1: ErrorMessage_RES | HI1: ErrorMessage3 | HJ1: ErrorMessage3_OUT | HK1: ErrorMessage_RES | HL1: Tooltip | HM1: Tooltip_OUT | HN1: Tooltip_RES | HO1: Tooltip1 | HP1: Tooltip1_OUT | HQ1: Tooltip1_RES | HR1: Tooltip2 | HS1: Tooltip2_OUT | HT1: Tooltip2_RES | HU1: FAQ1 | HV1: FAQ1_OUT | HW1: FAQ1_RES | HX1: FAQ2 | HY1: FAQ2_OUT | HZ1: FAQ2_RES | IA1: FAQ3 | IB1: FAQ3_OUT | IC1: FAQ3_RES | ID1: FAQ4 | IE1: FAQ4_OUT | IF1: FAQ4_RES | IG1: FAQ5 | IH1: FAQ5_OUT | II1: FAQ5_RES | IJ1: OwnerAdvantagePlan_OUT | IK1: RentalCarDamagePlan_OUT | IL1: OwnerAdvantagePlan_VERIFY | IM1: RentalCarDamage_VERIFY
A2: bln694769 | B2: Y | C2: Y | D2: Y | E2: Y | F2: Chrome | G2: TC_694769 | H2: {=_xlfn.IFS(Global!B2="QA","https://flightinsurance.qa.travelexinsurance.net/",Global!B2="UAT","https://flightinsurance.uat.travelexinsurance.net/",Global!B2="PROD","https://flightinsurance.travelexinsurance.com/")} -> https://flightinsurance.uat.travelexinsurance.net/ | I2: =TODAY() -> 46266 | L2: Travel Protection Plan | M2: Singapore | O2: Australia | AV2: =TEXT(I2+1,"mm/dd/yyyy") -> 09/02/2026 | AW2: =TEXT(I2+7,"mm/dd/yyyy") -> 09/08/2026 | AX2: =TEXT(I2+7,"mm/dd/yyyy") -> 09/08/2026 | AY2: =TEXT(AV2+89,"mm/dd/yyyy") -> 11/30/2026 | AZ2: =TEXT(AW2+14,"mm/dd/yyyy") -> 09/22/2026 | BA2: =TEXT(AV2+14,"mm/dd/yyyy") -> 09/16/2026 | BB2: =TEXT(I2-1,"mm/dd/yyyy") -> 08/31/2026 | BI2: California | BJ2: Nebraska | BK2: New York | DK2: 110 | DL2: 1000 | DM2: 100 | DN2: 18 | DO2: 1500 | DP2: ="QAFIRSTNAME"&CHAR(RANDBETWEEN(65,90))&CHAR(RANDBETWEEN(65,90)) -> QAFIRSTNAMEED | DQ2: ="QALASTNAME"&CHAR(RANDBETWEEN(65,90))&CHAR(RANDBETWEEN(65,90)) -> QALASTNAMEUP | DR2: =TEXT(DATE(YEAR(TODAY())-DN2,MONTH(TODAY()),DAY(TODAY())),"MM/DD/YYYY") -> 09/01/2008 | FG2: =TEXT(AV2,"mm/dd/yyyy") -> 09/02/2026 | FH2: =TEXT(AV2+1,"mm/dd/yyyy") -> 09/03/2026 | FI2: =TEXT(FH2+1,"mm/dd/yyyy") -> 09/04/2026 | FJ2: =TEXT(FI2+1,"mm/dd/yyyy") -> 09/05/2026 | FK2: =TEXT(FJ2+1,"mm/dd/yyyy") -> 09/06/2026 | FL2: =TEXT(FK2+1,"mm/dd/yyyy") -> 09/07/2026 | FM2: =TEXT(FL2+7,"mm/dd/yyyy") -> 09/14/2026 | FN2: =TEXT(FM2+1,"mm/dd/yyyy") -> 09/15/2026 | FO2: =TEXT(FN2+1,"mm/dd/yyyy") -> 09/16/2026 | FP2: =TEXT(FO2+1,"mm/dd/yyyy") -> 09/17/2026 | FQ2: ="QAFIRSTNAME"&CHAR(RANDBETWEEN(65,90))&CHAR(RANDBETWEEN(65,90)) -> QAFIRSTNAMEUG | FR2: ="QALASTNAME"&CHAR(RANDBETWEEN(65,90))&CHAR(RANDBETWEEN(65,90)) -> QALASTNAMEME | FS2: =TEXT(DATE(YEAR(TODAY())-DK2,MONTH(TODAY()),DAY(TODAY())),"MM/DD/YYYY") -> 09/01/1916 | FU2: =TEXT(DATE(YEAR(TODAY())-DN2,MONTH(TODAY()),DAY(TODAY())),"MM/DD/YYYY") -> 09/01/2008 | FV2: QA213 COR246 | FW2: Los Angeles | FX2: 90001 | FY2: 12345 | FZ2: Omaha | GA2: 68102 | GB2: 1234567897 | GC2: 2222222222 | GD2: qa@travelexinsurance.com | GE2: qa@travelguard.com | GF2: qwertyuiopasdfgh | GG2: qwertyuiopasdfgh | GH2: QA Test | GI2: 4111111111111111 | GK2: 12 | GL2: 2030 | GN2: =IF(DL2=GM2,"PASSED","FAILED") -> FAILED

Sheet CW
A1: blnExecute | B1: Step_Number | C1: Step_Name | D1: Status | E1: Error_Check | F1: breakpoint | G1: Test_Case | H1: Page | I1: FindBy | J1: FindBy_Value | K1: Index | L1: Method | M1: Value | N1: Output_Property | O1: Ignore_not_existing_object | P1: isDisabled | Q1: Timeout | R1: Expected_Value | S1: Output_Value | T1: Exact_Match | U1: Contains | V1: ITERATION_NO | W1: Notes | X1: Start_Time | Y1: End_Time | Z1: Duration
A2: Open Club Wyndham URL
A3: =IF(OR(Global!B25="N"),"N","bln696157") -> N | B3: =COUNTA($B$1:B2) -> 1 | C3: Open Browser | G3: Club Wyndham | L3: Wait | M3: 1 | O3: Y | R3: DT_URL
A4: =IF(OR(Global!B25="N"),"N","bln696157") -> N | B4: =COUNTA($B$1:B3) -> 2 | C4: Headless | G4: Club Wyndham | H4: DT_BrowserType | L4: Open | M4: ="URL:="&R3&";;HEADLESS:=TRUE" -> URL:=DT_URL;;HEADLESS:=TRUE | Q4: 60
A5: =IF(OR(Global!B25="Y"),"N","bln696157") -> bln696157 | B5: =COUNTA($B$1:B4) -> 3 | C5: Open Browser | G5: Club Wyndham | H5: DT_BrowserType | L5: Open | M5: DT_URL | Q5: 60
A6: N | B6: =COUNTA($B$1:B5) -> 4 | C6: Wait | G6: Club Wyndham | L6: Wait | M6: 5
A7: N | B7: =COUNTA($B$1:B6) -> 5 | C7: Zscaler Sign in Email | G7: Club Wyndham | I7: xpath | J7: //input[@id='okta-signin-username'] | K7: 0 | L7: Set | M7: DT_ZScalerUser | O7: Y | Q7: 5
A8: N | B8: =COUNTA($B$1:B7) -> 6 | C8: Zscaler Password | G8: Club Wyndham | I8: xpath | J8: //input[@id='okta-signin-password'] | K8: 0 | L8: Set | M8: DT_ZScalerPassword | O8: Y
A9: N | B9: =COUNTA($B$1:B8) -> 7 | C9: Click Sign in | G9: Club Wyndham | I9: xpath | J9: //input[@id='okta-signin-submit'] | K9: 0 | L9: Click | O9: Y
A10: N | B10: =COUNTA($B$1:B9) -> 8 | C10: Wait | G10: Club Wyndham | L10: Wait | M10: 5
A11: Home Page - GAQ
A12: bln696157 | B12: =COUNTA($B$1:B11) -> 9 | C12: Switch to Frame | G12: Club Wyndham | L12: SWITCHTOFRAME | M12: aemFormFrame
A13: bln696157 | B13: =COUNTA($B$1:B12) -> 10 | C13: Check Exist | G13: Club Wyndham | I13: xpath | J13: //button[text()='Accept All Cookies'] | L13: Exist | O13: Y
A14: bln696157 | B14: =COUNTA($B$1:B13) -> 11 | C14: Output Cookie | G14: Club Wyndham | I14: xpath | J14: //button[text()='Accept All Cookies'] | L14: Output | N14: innertext | O14: Y | R14: Accept All Cookies
A15: bln696157 | B15: =COUNTA($B$1:B14) -> 12 | C15: Cookies | G15: Club Wyndham | I15: xpath | J15: //button[@id='onetrust-accept-btn-handler'] | L15: js_click | O15: Y
A16: bln696157 | B16: =COUNTA($B$1:B15) -> 13 | C16: Click Destination | G16: Club Wyndham | I16: xpath | J16: //input[@id='cmp-Input' and @placeholder='Select a country or region'] | K16: 0 | L16: Click
A17: bln696157 | B17: =COUNTA($B$1:B16) -> 14 | C17: Wait | G17: Club Wyndham | L17: Wait | M17: 2
A18: bln696157 | B18: =COUNTA($B$1:B17) -> 15 | C18: Write Destination | G18: Club Wyndham | I18: xpath | J18: //input[@id='cmp-Input' and @placeholder='Select a country or region'] | K18: 0 | L18: Write | M18: Destination
A19: bln696157 | B19: =COUNTA($B$1:B18) -> 16 | C19: Wait | G19: Club Wyndham | L19: Wait | M19: 2
A20: bln696157 | B20: =COUNTA($B$1:B19) -> 17 | C20: Click Destination | G20: Club Wyndham | I20: xpath | J20: ="//a[contains(.,'"&M18&"')]" -> //a[contains(.,'Destination')] | K20: 0 | L20: js_click
A21: bln696157 | B21: =COUNTA($B$1:B20) -> 18 | C21: Departure Date | G21: Club Wyndham | I21: xpath | J21: //input[@name='tripDepartureDate'] | K21: 0 | L21: Set | M21: DepDate
A22: bln696157 | B22: =COUNTA($B$1:B21) -> 19 | C22: Return Date | G22: Club Wyndham | I22: xpath | J22: //input[@name='tripReturnDate'] | K22: 0 | L22: Set | M22: RetDate
A23: bln696157 | B23: =COUNTA($B$1:B22) -> 20 | C23: Click State | G23: Club Wyndham | I23: xpath | J23: //input[@id='cmp-Input' and @placeholder='Select your state'] | K23: 0 | L23: Click
A24: bln696157 | B24: =COUNTA($B$1:B23) -> 21 | C24: Wait | G24: Club Wyndham | L24: Wait | M24: 2
A25: bln696157 | B25: =COUNTA($B$1:B24) -> 22 | C25: Write State | G25: Club Wyndham | I25: xpath | J25: //input[@id='cmp-Input' and @placeholder='Select your state'] | K25: 0 | L25: Write | M25: Residence
A26: bln696157 | B26: =COUNTA($B$1:B25) -> 23 | C26: Wait | G26: Club Wyndham | L26: Wait | M26: 2
A27: bln696157 | B27: =COUNTA($B$1:B26) -> 24 | C27: Click State | G27: Club Wyndham | I27: xpath | J27: ="//a[contains(.,'"&M25&"')]" -> //a[contains(.,'Residence')] | K27: 0 | L27: js_click
A28: bln696157 | B28: =COUNTA($B$1:B27) -> 25 | C28: Click Submit button | G28: Club Wyndham | I28: xpath | J28: //button[@type='SUBMIT'] | K28: 0 | L28: js_click
A29: Plan Options
A30: bln696157 | B30: =COUNTA($B$1:B29) -> 26 | C30: Wait | G30: Club Wyndham | L30: Wait | M30: 10
A31: bln696157 | B31: =COUNTA($B$1:B30) -> 27 | C31: Check Exist | G31: Club Wyndham | I31: xpath | J31: //button[text()='Accept All Cookies'] | L31: Exist | O31: Y
A32: bln696157 | B32: =COUNTA($B$1:B31) -> 28 | C32: Output Cookie | G32: Club Wyndham | I32: xpath | J32: //button[text()='Accept All Cookies'] | L32: Output | N32: innertext | O32: Y | R32: Accept All Cookies
A33: bln696157 | B33: =COUNTA($B$1:B32) -> 29 | C33: Cookies | G33: Club Wyndham | I33: xpath | J33: //button[@id='onetrust-accept-btn-handler'] | L33: js_click | O33: Y
A34: bln696157 | B34: =COUNTA($B$1:B33) -> 30 | C34: Click the My Trip dropdown | G34: Club Wyndham | I34: xpath | J34: (//button[@type='button'])[2] | L34: Wait | M34: 5
A35: bln696157 | B35: =COUNTA($B$1:B34) -> 31 | C35: Travel Protection Plan | G35: Club Wyndham | I35: xpath | J35: //button[@name='selectPlan' and @value='914ZA-0824'] | K35: 0 | L35: js_click
A36: bln696157 | B36: =COUNTA($B$1:B35) -> 32 | C36: Wait | G36: Club Wyndham | L36: Wait | M36: 10
A37: Travelers Information
A38: bln696157 | B38: =COUNTA($B$1:B37) -> 33 | C38: Check Exist | G38: Club Wyndham | I38: xpath | J38: //button[text()='Accept All Cookies'] | L38: Exist | O38: Y
A39: bln696157 | B39: =COUNTA($B$1:B38) -> 34 | C39: Output Cookie | G39: Club Wyndham | I39: xpath | J39: //button[text()='Accept All Cookies'] | L39: Output | N39: innertext | O39: Y | R39: Accept All Cookies
A40: bln696157 | B40: =COUNTA($B$1:B39) -> 35 | C40: Cookies | G40: Club Wyndham | I40: xpath | J40: //button[@id='onetrust-accept-btn-handler'] | L40: js_click | O40: Y
A41: bln696157 | B41: =COUNTA($B$1:B40) -> 36 | C41: Click the My Trip dropdown | G41: Club Wyndham | I41: xpath | J41: (//button[@type='button'])[1] | L41: Wait | M41: 5
A42: bln696157 | B42: =COUNTA($B$1:B41) -> 37 | C42: Enter First Name | G42: Club Wyndham | I42: xpath | J42: //input[@name='firstName'] | K42: 0 | L42: Set | M42: FirstName
A43: bln696157 | B43: =COUNTA($B$1:B42) -> 38 | C43: Enter Last Name | G43: Club Wyndham | I43: xpath | J43: //input[@name='lastName'] | K43: 0 | L43: Set | M43: LastName
A44: bln696157 | B44: =COUNTA($B$1:B43) -> 39 | C44: Enter Address | G44: Club Wyndham | I44: xpath | J44: //input[@name='address1'] | K44: 0 | L44: Set | M44: Address
A45: bln696157 | B45: =COUNTA($B$1:B44) -> 40 | C45: Enter City | G45: Club Wyndham | I45: xpath | J45: //input[@name='city'] | K45: 0 | L45: Set | M45: City
A46: bln696157 | B46: =COUNTA($B$1:B45) -> 41 | C46: Enter Zip Code | G46: Club Wyndham | I46: xpath | J46: //input[@name='postalCode'] | K46: 0 | L46: Set | M46: Zip
A47: bln696157 | B47: =COUNTA($B$1:B46) -> 42 | C47: Enter Phone | G47: Club Wyndham | I47: xpath | J47: //input[@name='dayPhone'] | K47: 0 | L47: Set | M47: Phone
A48: bln696157 | B48: =COUNTA($B$1:B47) -> 43 | C48: Enter Email | G48: Club Wyndham | I48: xpath | J48: //input[@name='email'] | K48: 0 | L48: Set | M48: Email
A49: bln696157 | B49: =COUNTA($B$1:B48) -> 44 | C49: Click Submit button | G49: Club Wyndham | I49: xpath | J49: //button[@type='SUBMIT'] | K49: 0 | L49: js_click
A50: bln696157 | B50: =COUNTA($B$1:B49) -> 45 | C50: Wait | G50: Club Wyndham | L50: Wait | M50: 10
A51: Payment
A52: bln696157 | B52: =COUNTA($B$1:B51) -> 46 | C52: Check Exist | G52: Club Wyndham | I52: xpath | J52: //button[text()='Accept All Cookies'] | L52: Exist | O52: Y
A53: bln696157 | B53: =COUNTA($B$1:B52) -> 47 | C53: Output Cookie | G53: Club Wyndham | I53: xpath | J53: //button[text()='Accept All Cookies'] | L53: Output | N53: innertext | O53: Y | R53: Accept All Cookies
A54: bln696157 | B54: =COUNTA($B$1:B53) -> 48 | C54: Cookies | G54: Club Wyndham | I54: xpath | J54: //button[@id='onetrust-accept-btn-handler'] | L54: js_click | O54: Y
A55: bln696157 | B55: =COUNTA($B$1:B54) -> 49 | C55: Enter Card Name | G55: Club Wyndham | I55: xpath | J55: //input[@name='cardName'] | K55: 0 | L55: Set | M55: CardName
A56: bln696157 | B56: =COUNTA($B$1:B55) -> 50 | C56: Change iFrame | G56: Club Wyndham | I56: xpath | K56: 0 | L56: switchtoframe
A57: bln696157 | B57: =COUNTA($B$1:B56) -> 51 | C57: Check Exist | G57: Club Wyndham | I57: xpath | J57: //button[text()='Accept All Cookies'] | L57: Exist | O57: Y
A58: bln696157 | B58: =COUNTA($B$1:B57) -> 52 | C58: Output Cookie | G58: Club Wyndham | I58: xpath | J58: //button[text()='Accept All Cookies'] | L58: Output | N58: innertext | O58: Y | R58: Accept All Cookies
A59: bln696157 | B59: =COUNTA($B$1:B58) -> 53 | C59: Cookies | G59: Club Wyndham | I59: xpath | J59: //button[@id='onetrust-accept-btn-handler'] | L59: js_click | O59: Y
A60: bln696157 | B60: =COUNTA($B$1:B59) -> 54 | C60: Enter Card Number | G60: Club Wyndham | I60: xpath | J60: //input[@name='tsep-cardNum'] | K60: 0 | L60: Set | M60: CardNumber
A61: bln696157 | B61: =COUNTA($B$1:B60) -> 55 | C61: Change iFrame | G61: Club Wyndham | K61: 0 | L61: switchtodefault
A62: bln696157 | B62: =COUNTA($B$1:B61) -> 56 | C62: Change iFrame | G62: Club Wyndham | K62: 0 | L62: switchtoframe
A63: N | B63: =COUNTA($B$1:B62) -> 57 | C63: Click tab | G63: Club Wyndham | L63: SendKeys | M63: {TAB}
A64: N | B64: =COUNTA($B$1:B63) -> 58 | C64: Enter Card Expiry Month | G64: Club Wyndham | L64: SendKeys | M64: ExpiryMonth
A65: N | B65: =COUNTA($B$1:B64) -> 59 | C65: Enter Card Expiry Year | G65: Club Wyndham | L65: SendKeys | M65: ExpiryYear
A66: bln696157 | B66: =COUNTA($B$1:B65) -> 60 | C66: Click Expiry Date | G66: Club Wyndham | I66: xpath | J66: //input[@name='tsep-datepicker'] | K66: 0 | L66: Click
A67: bln696157 | B67: =COUNTA($B$1:B66) -> 61 | C67: Wait | G67: Club Wyndham | L67: Wait | M67: 2
A68: bln696157 | B68: =COUNTA($B$1:B67) -> 62 | C68: Input Expiry Month | G68: Club Wyndham | I68: xpath | J68: //input[@name='tsep-datepicker'] | K68: 0 | L68: Type | M68: ExpiryMonth
A69: bln696157 | B69: =COUNTA($B$1:B68) -> 63 | C69: Input Expiry Year | G69: Club Wyndham | I69: xpath | J69: //input[@name='tsep-datepicker'] | K69: 0 | L69: Type | M69: ExpiryYear
A70: bln696157 | B70: =COUNTA($B$1:B69) -> 64 | C70: Wait | G70: Club Wyndham | L70: Wait | M70: 2
A71: bln696157 | B71: =COUNTA($B$1:B70) -> 65 | C71: Change iFrame | G71: Club Wyndham | K71: 0 | L71: switchtodefault
A72: bln696157 | B72: =COUNTA($B$1:B71) -> 66 | C72: Wait | G72: Club Wyndham | L72: Wait | M72: 2
A73: bln696157 | B73: =COUNTA($B$1:B72) -> 67 | C73: Move to Element | G73: Club Wyndham | I73: xpath | J73: //input[@value='I agree'] | K73: 0 | L73: MOVETOELEMENT
A74: bln696157 | B74: =COUNTA($B$1:B73) -> 68 | C74: I Agree | G74: Club Wyndham | I74: xpath | J74: //input[@value='I agree'] | K74: 0 | L74: Tick
A75: bln696157 | B75: =COUNTA($B$1:B74) -> 69 | C75: Wait | G75: Club Wyndham | L75: Wait | M75: 2
A76: Home Page - GAQ Edit/Restart
A77: bln696157 | B77: =COUNTA($B$1:B75) -> 70 | C77: Click Get a Quote | G77: Club Wyndham | I77: xpath | J77: //a[contains(.,'Get Quote')] | K77: 0 | L77: js_click
A78: bln696157 | B78: =COUNTA($B$1:B77) -> 71 | C78: Wait | G78: Club Wyndham | L78: Wait | M78: 3
A79: bln696157 | B79: =COUNTA($B$1:B78) -> 72 | C79: Click Destination | G79: Club Wyndham | I79: xpath | J79: (//input[@id='cmp-Input'])[1] | K79: 0 | L79: Click
A80: bln696157 | B80: =COUNTA($B$1:B79) -> 73 | C80: Wait | G80: Club Wyndham | L80: Wait | M80: 2
A81: bln696157 | B81: =COUNTA($B$1:B80) -> 74 | C81: Write Destination | G81: Club Wyndham | I81: xpath | J81: (//input[@id='cmp-Input' and @class='inputField'])[1] | K81: 0 | L81: Write | M81: Destination1
A82: bln696157 | B82: =COUNTA($B$1:B81) -> 75 | C82: Wait | G82: Club Wyndham | L82: Wait | M82: 2
A83: bln696157 | B83: =COUNTA($B$1:B82) -> 76 | C83: Click Destination | G83: Club Wyndham | I83: xpath | J83: ="//a[contains(.,'"&M81&"')]" -> //a[contains(.,'Destination1')] | K83: 0 | L83: js_click
A84: bln696157 | B84: =COUNTA($B$1:B83) -> 77 | C84: Departure Date | G84: Club Wyndham | I84: xpath | J84: //input[@name='tripDepartureDate'] | K84: 0 | L84: Set | M84: DepDate1
A85: bln696157 | B85: =COUNTA($B$1:B84) -> 78 | C85: Return Date | G85: Club Wyndham | I85: xpath | J85: //input[@name='tripReturnDate'] | K85: 0 | L85: Set | M85: RetDate1
A86: bln696157 | B86: =COUNTA($B$1:B85) -> 79 | C86: Click State | G86: Club Wyndham | I86: xpath | J86: (//input[@id='cmp-Input'])[2] | K86: 0 | L86: Click
A87: bln696157 | B87: =COUNTA($B$1:B86) -> 80 | C87: Wait | G87: Club Wyndham | L87: Wait | M87: 2
A88: bln696157 | B88: =COUNTA($B$1:B87) -> 81 | C88: Write State | G88: Club Wyndham | I88: xpath | J88: (//input[@id='cmp-Input' and @class='inputField'])[2] | K88: 0 | L88: Write | M88: Residence1
A89: bln696157 | B89: =COUNTA($B$1:B88) -> 82 | C89: Wait | G89: Club Wyndham | L89: Wait | M89: 2
A90: bln696157 | B90: =COUNTA($B$1:B89) -> 83 | C90: Click Residence | G90: Club Wyndham | I90: xpath | J90: ="//a[contains(.,'"&M88&"')]" -> //a[contains(.,'Residence1')] | K90: 0 | L90: js_click
A91: bln696157 | B91: =COUNTA($B$1:B90) -> 84 | C91: Click Get a Quote button | G91: Club Wyndham | I91: xpath | J91: //button[@type='SUBMIT'] | K91: 0 | L91: js_click
A92: bln696157 | B92: =COUNTA($B$1:B91) -> 85 | C92: Wait | G92: Club Wyndham | L92: Wait | M92: 10
A93: Plan Options
A94: bln696157 | B94: =COUNTA($B$1:B93) -> 86 | C94: Click My Trip Summary Dropdown | G94: Club Wyndham | I94: xpath | J94: //button[@type='button' and @aria-controls='my-trip-accordion-item-85f740dcaf-panel'] | K94: 0 | L94: js_click
A95: bln696157 | B95: =COUNTA($B$1:B94) -> 87 | C95: Output Destination Country | G95: Club Wyndham | I95: xpath | J95: //span[@class='handlebar-recursive-replacement destinationCountry_multi_display'] | K95: 0 | L95: Output | N95: innertext | R95: =M81 -> Destination1 | T95: Y
A96: bln696157 | B96: =COUNTA($B$1:B95) -> 88 | C96: Output Travel (Departure) Dates | G96: Club Wyndham | I96: xpath | J96: //span[@class='handlebar-recursive-replacement tripDepartureDate'] | K96: 0 | L96: Output | N96: innertext | R96: =TEXT(M84,"mm/dd/yyyy") -> DepDate1 | T96: Y
A97: bln696157 | B97: =COUNTA($B$1:B96) -> 89 | C97: Output Travel (Return) Dates | G97: Club Wyndham | I97: xpath | J97: //span[@class='handlebar-recursive-replacement tripReturnDate'] | K97: 0 | L97: Output | N97: innertext | R97: =TEXT(M85,"mm/dd/yyyy") -> RetDate1 | T97: Y
A98: bln696157 | B98: =COUNTA($B$1:B97) -> 90 | C98: Travel Protection Plan | G98: Club Wyndham | I98: xpath | J98: //button[@name='selectPlan' and @value='914ZA-0824'] | K98: 0 | L98: js_click
A99: bln696157 | B99: =COUNTA($B$1:B98) -> 91 | C99: Wait | G99: Club Wyndham | L99: Wait | M99: 10
A100: Travelers Information
...

Sheet Params_8
A1: Scenario | B1: blnExecute | C1: bln_TG | D1: blnQuit | E1: bln696157 | F1: DT_BrowserType | G1: Notes | H1: DT_URL | I1: DateToday | J1: PolicyNumber_OUT | K1: tripType | L1: Plan | M1: Destination | N1: Restricted | O1: Destination1 | P1: Destination2 | Q1: Destination3 | R1: Destination4 | S1: Destination5 | T1: Destination6 | U1: Destination7 | V1: Destination8 | W1: Destination9 | X1: Destination10 | Y1: Destination11 | Z1: Destination12 | AA1: Destination13 | AB1: Destination14 | AC1: Destination15 | AD1: Destination16 | AE1: Destination17 | AF1: Destination18 | AG1: Destination19 | AH1: Destination20 | AI1: Destination21 | AJ1: Destination22 | AK1: Destination23 | AL1: Destination24 | AM1: Destination25 | AN1: Destination26 | AO1: Destination27 | AP1: Destination28 | AQ1: Destination29 | AR1: Destination30 | AS1: Destination31 | AT1: Destination32 | AU1: Destination33 | AV1: DepDate | AW1: DepDate1 | AX1: DepDateValid | AY1: RetDate | AZ1: RetDate1 | BA1: RetDateValid | BB1: DepoDate | BC1: DepoYearInvalid | BD1: DepoYearValid | BE1: DepoMonthInvalid | BF1: DepoMonthValid | BG1: DepoDayInvalid | BH1: DepoDayValid | BI1: Residence | BJ1: Residence1 | BK1: Residence2 | BL1: Residence3 | BM1: Residence4 | BN1: Residence5 | BO1: Residence6 | BP1: Residence7 | BQ1: Residence8 | BR1: Residence9 | BS1: Residence10 | BT1: Residence11 | BU1: Residence12 | BV1: Residence13 | BW1: Residence14 | BX1: Residence15 | BY1: Residence16 | BZ1: Residence17 | CA1: Residence18 | CB1: Residence19 | CC1: Residence20 | CD1: Residence21 | CE1: Residence22 | CF1: Residence23 | CG1: Residence24 | CH1: Residence25 | CI1: Residence26 | CJ1: Residence27 | CK1: Residence28 | CL1: Residence29 | CM1: Residence30 | CN1: Residence31 | CO1: Residence32 | CP1: Residence33 | CQ1: Residence34 | CR1: Residence35 | CS1: Residence36 | CT1: Residence37 | CU1: Residence38 | CV1: Residence39 | CW1: Residence40 | CX1: Residence41 | CY1: Residence42 | CZ1: Residence43 | DA1: Residence44 | DB1: Residence45 | DC1: Residence46 | DD1: Residence47 | DE1: Residence48 | DF1: Residence49 | DG1: Residence50 | DH1: Residence51 | DI1: Residence52 | DJ1: Residence53 | DK1: Age | DL1: Cost | DM1: CostAllowed | DN1: Age1 | DO1: Cost1 | DP1: Trav_FirstName1 | DQ1: Trav_LastName1 | DR1: Trav_BirthDate1 | DS1: Age2 | DT1: Cost2 | DU1: Trav_FirstName2 | DV1: Trav_LastName2 | DW1: Trav_BirthDate2 | DX1: Age3 | DY1: Cost3 | DZ1: Trav_FirstName3 | EA1: Trav_LastName3 | EB1: Trav_BirthDate3 | EC1: Age4 | ED1: Cost4 | EE1: Trav_FirstName4 | EF1: Trav_LastName4 | EG1: Trav_BirthDate4 | EH1: Age5 | EI1: Cost5 | EJ1: Trav_FirstName5 | EK1: Trav_LastName5 | EL1: Trav_BirthDate5 | EM1: Age6 | EN1: Cost6 | EO1: Trav_FirstName6 | EP1: Trav_LastName6 | EQ1: Trav_BirthDate6 | ER1: Age7 | ES1: Cost7 | ET1: Trav_FirstName7 | EU1: Trav_LastName7 | EV1: Trav_BirthDate7 | EW1: Age8 | EX1: Cost8 | EY1: Trav_FirstName8 | EZ1: Trav_LastName8 | FA1: Trav_BirthDate8 | FB1: Age9 | FC1: Cost9 | FD1: Trav_FirstName9 | FE1: Trav_LastName9 | FF1: Trav_BirthDate9 | FG1: PickUpDate | FH1: DropOffDate | FI1: PickUpDate1 | FJ1: DropOffDate1 | FK1: PickUpDate2 | FL1: DropOffDate2 | FM1: PickUpDate3 | FN1: DropOffDate3 | FO1: PickUpDate4 | FP1: DropOffDate4 | FQ1: FirstName | FR1: LastName | FS1: BirthDate | FT1: BirthDateInvalid | FU1: BirthDate1 | FV1: Address | FW1: City | FX1: Zip | FY1: ZipX | FZ1: City1 | GA1: Zip1 | GB1: Phone | GC1: Phone1 | GD1: Email | GE1: Email1 | GF1: OwnerPhone | GG1: ReservationConfirmationNumber | GH1: CardName | GI1: CardNumber | GJ1: CardNumber1 | GK1: ExpiryMonth | GL1: ExpiryYear | GM1: Cost_OUT | GN1: Cost_RES | GO1: Destination_OUT | GP1: Destination_RES | GQ1: Plan | GR1: Plan_OUT | GS1: Plan_RES | GT1: Plan1 | GU1: Plan1_OUT | GV1: Plan_RES | GW1: Plan2 | GX1: Plan2_OUT | GY1: Plan_RES | GZ1: ErrorMessage | HA1: ErrorMessage_OUT | HB1: ErrorMessage_RES | HC1: ErrorMessage1 | HD1: ErrorMessage1_OUT | HE1: ErrorMessage_RES | HF1: ErrorMessage2 | HG1: ErrorMessage2_OUT | HH1: ErrorMessage_RES | HI1: ErrorMessage3 | HJ1: ErrorMessage3_OUT | HK1: ErrorMessage_RES | HL1: Tooltip | HM1: Tooltip_OUT | HN1: Tooltip_RES | HO1: Tooltip1 | HP1: Tooltip1_OUT | HQ1: Tooltip1_RES | HR1: Tooltip2 | HS1: Tooltip2_OUT | HT1: Tooltip2_RES | HU1: FAQ1 | HV1: FAQ1_OUT | HW1: FAQ1_RES | HX1: FAQ2 | HY1: FAQ2_OUT | HZ1: FAQ2_RES | IA1: FAQ3 | IB1: FAQ3_OUT | IC1: FAQ3_RES | ID1: FAQ4 | IE1: FAQ4_OUT | IF1: FAQ4_RES | IG1: FAQ5 | IH1: FAQ5_OUT | II1: FAQ5_RES | IJ1: OwnerAdvantagePlan_OUT | IK1: RentalCarDamagePlan_OUT | IL1: OwnerAdvantagePlan_VERIFY | IM1: RentalCarDamage_VERIFY
A2: bln696157 | B2: Y | C2: Y | D2: Y | E2: Y | F2: Chrome | G2: TC_696157 | H2: {=_xlfn.IFS(Global!B2="QA","https://cw.qa.travelexinsurance.net/",Global!B2="UAT","https://cw.uat.travelexinsurance.net/",Global!B2="PROD","https://cw.travelexinsurance.com")} -> https://cw.uat.travelexinsurance.net/ | I2: =TODAY() -> 46266 | L2: Travel Protection Plan | M2: United States | O2: United Kingdom | AV2: =TEXT(I2+1,"mm/dd/yyyy") -> 09/02/2026 | AW2: =TEXT(I2+7,"mm/dd/yyyy") -> 09/08/2026 | AX2: =TEXT(I2+7,"mm/dd/yyyy") -> 09/08/2026 | AY2: =TEXT(AV2+89,"mm/dd/yyyy") -> 11/30/2026 | AZ2: =TEXT(AW2+14,"mm/dd/yyyy") -> 09/22/2026 | BA2: =TEXT(AV2+14,"mm/dd/yyyy") -> 09/16/2026 | BB2: =TEXT(I2-1,"mm/dd/yyyy") -> 08/31/2026 | BI2: California | BJ2: North Carolina | BK2: Nebraska | DK2: 110 | DL2: 1000 | DM2: 100 | DN2: 18 | DO2: 1500 | DP2: ="QAFIRSTNAME"&CHAR(RANDBETWEEN(65,90))&CHAR(RANDBETWEEN(65,90)) -> QAFIRSTNAMEAI | DQ2: ="QALASTNAME"&CHAR(RANDBETWEEN(65,90))&CHAR(RANDBETWEEN(65,90)) -> QALASTNAMEPV | DR2: =TEXT(DATE(YEAR(TODAY())-DN2,MONTH(TODAY()),DAY(TODAY())),"MM/DD/YYYY") -> 09/01/2008 | FG2: =TEXT(AV2,"mm/dd/yyyy") -> 09/02/2026 | FH2: =TEXT(AV2+1,"mm/dd/yyyy") -> 09/03/2026 | FI2: =TEXT(FH2+1,"mm/dd/yyyy") -> 09/04/2026 | FJ2: =TEXT(FI2+1,"mm/dd/yyyy") -> 09/05/2026 | FK2: =TEXT(FJ2+1,"mm/dd/yyyy") -> 09/06/2026 | FL2: =TEXT(FK2+1,"mm/dd/yyyy") -> 09/07/2026 | FM2: =TEXT(FL2+7,"mm/dd/yyyy") -> 09/14/2026 | FN2: =TEXT(FM2+1,"mm/dd/yyyy") -> 09/15/2026 | FO2: =TEXT(FN2+1,"mm/dd/yyyy") -> 09/16/2026 | FP2: =TEXT(FO2+1,"mm/dd/yyyy") -> 09/17/2026 | FQ2: ="QAFIRSTNAME"&CHAR(RANDBETWEEN(65,90))&CHAR(RANDBETWEEN(65,90)) -> QAFIRSTNAMEWE | FR2: ="QALASTNAME"&CHAR(RANDBETWEEN(65,90))&CHAR(RANDBETWEEN(65,90)) -> QALASTNAMELZ | FS2: =TEXT(DATE(YEAR(TODAY())-DK2,MONTH(TODAY()),DAY(TODAY())),"MM/DD/YYYY") -> 09/01/1916 | FU2: =TEXT(DATE(YEAR(TODAY())-DN2,MONTH(TODAY()),DAY(TODAY())),"MM/DD/YYYY") -> 09/01/2008 | FV2: QA213 COR246 | FW2: Los Angeles | FX2: 90001 | FY2: 12345 | FZ2: Charlotte | GA2: 28202 | GB2: 1234567897 | GC2: 2222222222 | GD2: qa@travelexinsurance.com | GE2: qa@travelguard.com | GF2: qwertyuiopasdfgh | GG2: qwertyuiopasdfgh | GH2: QA Test | GI2: 4111111111111111 | GK2: 12 | GL2: 2030 | GN2: =IF(DL2=GM2,"PASSED","FAILED") -> FAILED
H3: {=_xlfn.IFS(Global!B2="QA","https://cw.qa.travelexinsurance.net/",Global!B2="UAT","https://cw.uat.travelexinsurance.net/",Global!B2="PROD","https://cw.travelexinsurance.com")} -> https://cw.uat.travelexinsurance.net/

Sheet WM
A1: blnExecute | B1: Step_Number | C1: Step_Name | D1: Status | E1: Error_Check | F1: breakpoint | G1: Test_Case | H1: Page | I1: FindBy | J1: FindBy_Value | K1: Index | L1: Method | M1: Value | N1: Output_Property | O1: Ignore_not_existing_object | P1: isDisabled | Q1: Timeout | R1: Expected_Value | S1: Output_Value | T1: Exact_Match | U1: Contains | V1: ITERATION_NO | W1: Notes | X1: Start_Time | Y1: End_Time | Z1: Duration
A2: Open World Mark URL
A3: =IF(OR(Global!B25="N"),"N","bln696153") -> N | B3: =COUNTA($B$1:B2) -> 1 | C3: Open Browser | G3: World Mark | L3: Wait | M3: 1 | O3: Y | R3: DT_URL
A4: =IF(OR(Global!B25="N"),"N","bln696153") -> N | B4: =COUNTA($B$1:B3) -> 2 | C4: Headless | G4: World Mark | H4: DT_BrowserType | L4: Open | M4: ="URL:="&R3&";;HEADLESS:=TRUE" -> URL:=DT_URL;;HEADLESS:=TRUE | Q4: 60
A5: =IF(OR(Global!B25="Y"),"N","bln696153") -> bln696153 | B5: =COUNTA($B$1:B4) -> 3 | C5: Open Browser | G5: World Mark | H5: DT_BrowserType | L5: Open | M5: DT_URL | Q5: 60
A6: N | B6: =COUNTA($B$1:B5) -> 4 | C6: Wait | G6: World Mark | L6: Wait | M6: 5
A7: N | B7: =COUNTA($B$1:B6) -> 5 | C7: Zscaler Sign in Email | G7: World Mark | I7: xpath | J7: //input[@id='okta-signin-username'] | K7: 0 | L7: Set | M7: DT_ZScalerUser | O7: Y | Q7: 5
A8: N | B8: =COUNTA($B$1:B7) -> 6 | C8: Zscaler Password | G8: World Mark | I8: xpath | J8: //input[@id='okta-signin-password'] | K8: 0 | L8: Set | M8: DT_ZScalerPassword | O8: Y
A9: N | B9: =COUNTA($B$1:B8) -> 7 | C9: Click Sign in | G9: World Mark | I9: xpath | J9: //input[@id='okta-signin-submit'] | K9: 0 | L9: Click | O9: Y
A10: N | B10: =COUNTA($B$1:B9) -> 8 | C10: Wait | G10: World Mark | L10: Wait | M10: 5
A11: Home Page - GAQ
A12: bln696153 | B12: =COUNTA($B$1:B11) -> 9 | C12: Switch to Frame | G12: World Mark | L12: SWITCHTOFRAME | M12: aemFormFrame
A13: bln696153 | B13: =COUNTA($B$1:B12) -> 10 | C13: Check Exist | G13: World Mark | I13: xpath | J13: //button[text()='Accept All Cookies'] | L13: Exist | O13: Y
A14: bln696153 | B14: =COUNTA($B$1:B13) -> 11 | C14: Output Cookie | G14: World Mark | I14: xpath | J14: //button[text()='Accept All Cookies'] | L14: Output | N14: innertext | O14: Y | R14: Accept All Cookies
A15: bln696153 | B15: =COUNTA($B$1:B14) -> 12 | C15: Cookies | G15: World Mark | I15: xpath | J15: //button[@id='onetrust-accept-btn-handler'] | L15: js_click | O15: Y
A16: bln696153 | B16: =COUNTA($B$1:B15) -> 13 | C16: Click Destination | G16: World Mark | I16: xpath | J16: //input[@id='cmp-Input' and @placeholder='Select a country or region'] | K16: 0 | L16: Click
A17: bln696153 | B17: =COUNTA($B$1:B16) -> 14 | C17: Wait | G17: World Mark | L17: Wait | M17: 2
A18: bln696153 | B18: =COUNTA($B$1:B17) -> 15 | C18: Write Destination | G18: World Mark | I18: xpath | J18: //input[@id='cmp-Input' and @placeholder='Select a country or region'] | K18: 0 | L18: Write | M18: Destination
A19: bln696153 | B19: =COUNTA($B$1:B18) -> 16 | C19: Wait | G19: World Mark | L19: Wait | M19: 2
A20: bln696153 | B20: =COUNTA($B$1:B19) -> 17 | C20: Click Destination | G20: World Mark | I20: xpath | J20: ="//a[contains(.,'"&M18&"')]" -> //a[contains(.,'Destination')] | K20: 0 | L20: js_click
A21: bln696153 | B21: =COUNTA($B$1:B20) -> 18 | C21: Departure Date | G21: World Mark | I21: xpath | J21: //input[@name='tripDepartureDate'] | K21: 0 | L21: Set | M21: DepDate
A22: bln696153 | B22: =COUNTA($B$1:B21) -> 19 | C22: Return Date | G22: World Mark | I22: xpath | J22: //input[@name='tripReturnDate'] | K22: 0 | L22: Set | M22: RetDate
A23: bln696153 | B23: =COUNTA($B$1:B22) -> 20 | C23: Click State | G23: World Mark | I23: xpath | J23: //input[@id='cmp-Input' and @placeholder='Select your state'] | K23: 0 | L23: Click
A24: bln696153 | B24: =COUNTA($B$1:B23) -> 21 | C24: Wait | G24: World Mark | L24: Wait | M24: 2
A25: bln696153 | B25: =COUNTA($B$1:B24) -> 22 | C25: Write State | G25: World Mark | I25: xpath | J25: //input[@id='cmp-Input' and @placeholder='Select your state'] | K25: 0 | L25: Write | M25: Residence
A26: bln696153 | B26: =COUNTA($B$1:B25) -> 23 | C26: Wait | G26: World Mark | L26: Wait | M26: 2
A27: bln696153 | B27: =COUNTA($B$1:B26) -> 24 | C27: Click State | G27: World Mark | I27: xpath | J27: ="//a[contains(.,'"&M25&"')]" -> //a[contains(.,'Residence')] | K27: 0 | L27: js_click
A28: bln696153 | B28: =COUNTA($B$1:B27) -> 25 | C28: Click Submit button | G28: World Mark | I28: xpath | J28: //button[@type='SUBMIT'] | K28: 0 | L28: js_click
A29: Plan Options
A30: bln696153 | B30: =COUNTA($B$1:B29) -> 26 | C30: Wait | G30: World Mark | L30: Wait | M30: 10
A31: bln696153 | B31: =COUNTA($B$1:B30) -> 27 | C31: Check Exist | G31: World Mark | I31: xpath | J31: //button[text()='Accept All Cookies'] | L31: Exist | O31: Y
A32: bln696153 | B32: =COUNTA($B$1:B31) -> 28 | C32: Output Cookie | G32: World Mark | I32: xpath | J32: //button[text()='Accept All Cookies'] | L32: Output | N32: innertext | O32: Y | R32: Accept All Cookies
A33: bln696153 | B33: =COUNTA($B$1:B32) -> 29 | C33: Cookies | G33: World Mark | I33: xpath | J33: //button[@id='onetrust-accept-btn-handler'] | L33: js_click | O33: Y
A34: bln696153 | B34: =COUNTA($B$1:B33) -> 30 | C34: Click the My Trip dropdown | G34: World Mark | I34: xpath | J34: (//button[@type='button'])[2] | L34: Wait | M34: 5
A35: bln696153 | B35: =COUNTA($B$1:B34) -> 31 | C35: Travel Protection Plan | G35: World Mark | I35: xpath | J35: //button[@name='selectPlan' and @value='913ZA-0824'] | K35: 0 | L35: js_click
A36: bln696153 | B36: =COUNTA($B$1:B35) -> 32 | C36: Wait | G36: World Mark | L36: Wait | M36: 10
A37: Travelers Information
A38: bln696153 | B38: =COUNTA($B$1:B37) -> 33 | C38: Check Exist | G38: World Mark | I38: xpath | J38: //button[text()='Accept All Cookies'] | L38: Exist | O38: Y
A39: bln696153 | B39: =COUNTA($B$1:B38) -> 34 | C39: Output Cookie | G39: World Mark | I39: xpath | J39: //button[text()='Accept All Cookies'] | L39: Output | N39: innertext | O39: Y | R39: Accept All Cookies
A40: bln696153 | B40: =COUNTA($B$1:B39) -> 35 | C40: Cookies | G40: World Mark | I40: xpath | J40: //button[@id='onetrust-accept-btn-handler'] | L40: js_click | O40: Y
A41: bln696153 | B41: =COUNTA($B$1:B40) -> 36 | C41: Click the My Trip dropdown | G41: World Mark | I41: xpath | J41: (//button[@type='button'])[1] | L41: Wait | M41: 5
A42: bln696153 | B42: =COUNTA($B$1:B41) -> 37 | C42: Enter First Name | G42: World Mark | I42: xpath | J42: //input[@name='firstName'] | K42: 0 | L42: Set | M42: FirstName
A43: bln696153 | B43: =COUNTA($B$1:B42) -> 38 | C43: Enter Last Name | G43: World Mark | I43: xpath | J43: //input[@name='lastName'] | K43: 0 | L43: Set | M43: LastName
A44: bln696153 | B44: =COUNTA($B$1:B43) -> 39 | C44: Enter Address | G44: World Mark | I44: xpath | J44: //input[@name='address1'] | K44: 0 | L44: Set | M44: Address
A45: bln696153 | B45: =COUNTA($B$1:B44) -> 40 | C45: Enter City | G45: World Mark | I45: xpath | J45: //input[@name='city'] | K45: 0 | L45: Set | M45: City
A46: bln696153 | B46: =COUNTA($B$1:B45) -> 41 | C46: Enter Zip Code | G46: World Mark | I46: xpath | J46: //input[@name='postalCode'] | K46: 0 | L46: Set | M46: Zip
A47: bln696153 | B47: =COUNTA($B$1:B46) -> 42 | C47: Enter Phone | G47: World Mark | I47: xpath | J47: //input[@name='dayPhone'] | K47: 0 | L47: Set | M47: Phone
A48: bln696153 | B48: =COUNTA($B$1:B47) -> 43 | C48: Enter Email | G48: World Mark | I48: xpath | J48: //input[@name='email'] | K48: 0 | L48: Set | M48: Email
A49: bln696153 | B49: =COUNTA($B$1:B48) -> 44 | C49: Click Submit button | G49: World Mark | I49: xpath | J49: //button[@type='SUBMIT'] | K49: 0 | L49: js_click
A50: bln696153 | B50: =COUNTA($B$1:B49) -> 45 | C50: Wait | G50: World Mark | L50: Wait | M50: 10
A51: Payment
A52: bln696153 | B52: =COUNTA($B$1:B51) -> 46 | C52: Check Exist | G52: World Mark | I52: xpath | J52: //button[text()='Accept All Cookies'] | L52: Exist | O52: Y
A53: bln696153 | B53: =COUNTA($B$1:B52) -> 47 | C53: Output Cookie | G53: World Mark | I53: xpath | J53: //button[text()='Accept All Cookies'] | L53: Output | N53: innertext | O53: Y | R53: Accept All Cookies
A54: bln696153 | B54: =COUNTA($B$1:B53) -> 48 | C54: Cookies | G54: World Mark | I54: xpath | J54: //button[@id='onetrust-accept-btn-handler'] | L54: js_click | O54: Y
A55: bln696153 | B55: =COUNTA($B$1:B54) -> 49 | C55: Enter Card Name | G55: World Mark | I55: xpath | J55: //input[@name='cardName'] | K55: 0 | L55: Set | M55: CardName
A56: bln696153 | B56: =COUNTA($B$1:B55) -> 50 | C56: Change iFrame | G56: World Mark | I56: xpath | K56: 0 | L56: switchtoframe
A57: bln696153 | B57: =COUNTA($B$1:B56) -> 51 | C57: Check Exist | G57: World Mark | I57: xpath | J57: //button[text()='Accept All Cookies'] | L57: Exist | O57: Y
A58: bln696153 | B58: =COUNTA($B$1:B57) -> 52 | C58: Output Cookie | G58: World Mark | I58: xpath | J58: //button[text()='Accept All Cookies'] | L58: Output | N58: innertext | O58: Y | R58: Accept All Cookies
A59: bln696153 | B59: =COUNTA($B$1:B58) -> 53 | C59: Cookies | G59: World Mark | I59: xpath | J59: //button[@id='onetrust-accept-btn-handler'] | L59: js_click | O59: Y
A60: bln696153 | B60: =COUNTA($B$1:B59) -> 54 | C60: Enter Card Number | G60: World Mark | I60: xpath | J60: //input[@name='tsep-cardNum'] | K60: 0 | L60: Set | M60: CardNumber
A61: bln696153 | B61: =COUNTA($B$1:B60) -> 55 | C61: Change iFrame | G61: World Mark | K61: 0 | L61: switchtodefault
A62: bln696153 | B62: =COUNTA($B$1:B61) -> 56 | C62: Change iFrame | G62: World Mark | K62: 0 | L62: switchtoframe
A63: N | B63: =COUNTA($B$1:B62) -> 57 | C63: Click tab | G63: World Mark | L63: SendKeys | M63: {TAB}
A64: N | B64: =COUNTA($B$1:B63) -> 58 | C64: Enter Card Expiry Month | G64: World Mark | L64: SendKeys | M64: ExpiryMonth
A65: N | B65: =COUNTA($B$1:B64) -> 59 | C65: Enter Card Expiry Year | G65: World Mark | L65: SendKeys | M65: ExpiryYear
A66: bln696153 | B66: =COUNTA($B$1:B65) -> 60 | C66: Click Expiry Date | G66: World Mark | I66: xpath | J66: //input[@name='tsep-datepicker'] | K66: 0 | L66: Click
A67: bln696153 | B67: =COUNTA($B$1:B66) -> 61 | C67: Wait | G67: World Mark | L67: Wait | M67: 2
A68: bln696153 | B68: =COUNTA($B$1:B67) -> 62 | C68: Input Expiry Month | G68: World Mark | I68: xpath | J68: //input[@name='tsep-datepicker'] | K68: 0 | L68: Type | M68: ExpiryMonth
A69: bln696153 | B69: =COUNTA($B$1:B68) -> 63 | C69: Input Expiry Year | G69: World Mark | I69: xpath | J69: //input[@name='tsep-datepicker'] | K69: 0 | L69: Type | M69: ExpiryYear
A70: bln696153 | B70: =COUNTA($B$1:B69) -> 64 | C70: Wait | G70: World Mark | L70: Wait | M70: 2
A71: bln696153 | B71: =COUNTA($B$1:B70) -> 65 | C71: Change iFrame | G71: World Mark | K71: 0 | L71: switchtodefault
A72: bln696153 | B72: =COUNTA($B$1:B71) -> 66 | C72: Wait | G72: World Mark | L72: Wait | M72: 2
A73: bln696153 | B73: =COUNTA($B$1:B72) -> 67 | C73: I Agree | G73: World Mark | I73: xpath | J73: //input[@value='I agree'] | K73: 0 | L73: Tick
A74: bln696153 | B74: =COUNTA($B$1:B73) -> 68 | C74: Wait | G74: World Mark | L74: Wait | M74: 2
A75: Home Page - GAQ Edit/Restart
A76: bln696153 | B76: =COUNTA($B$1:B74) -> 69 | C76: Click Get a Quote | G76: World Mark | I76: xpath | J76: //a[contains(.,'Get Quote')] | K76: 0 | L76: js_click
A77: bln696153 | B77: =COUNTA($B$1:B76) -> 70 | C77: Wait | G77: World Mark | L77: Wait | M77: 3
A78: bln696153 | B78: =COUNTA($B$1:B77) -> 71 | C78: Click Destination | G78: World Mark | I78: xpath | J78: (//input[@id='cmp-Input'])[1] | K78: 0 | L78: Click
A79: bln696153 | B79: =COUNTA($B$1:B78) -> 72 | C79: Wait | G79: World Mark | L79: Wait | M79: 2
A80: bln696153 | B80: =COUNTA($B$1:B79) -> 73 | C80: Write Destination | G80: World Mark | I80: xpath | J80: (//input[@id='cmp-Input' and @class='inputField'])[1] | K80: 0 | L80: Write | M80: Destination1
A81: bln696153 | B81: =COUNTA($B$1:B80) -> 74 | C81: Wait | G81: World Mark | L81: Wait | M81: 2
A82: bln696153 | B82: =COUNTA($B$1:B81) -> 75 | C82: Click Destination | G82: World Mark | I82: xpath | J82: ="//a[contains(.,'"&M80&"')]" -> //a[contains(.,'Destination1')] | K82: 0 | L82: js_click
A83: bln696153 | B83: =COUNTA($B$1:B82) -> 76 | C83: Departure Date | G83: World Mark | I83: xpath | J83: //input[@name='tripDepartureDate'] | K83: 0 | L83: Set | M83: DepDate1
A84: bln696153 | B84: =COUNTA($B$1:B83) -> 77 | C84: Return Date | G84: World Mark | I84: xpath | J84: //input[@name='tripReturnDate'] | K84: 0 | L84: Set | M84: RetDate1
A85: bln696153 | B85: =COUNTA($B$1:B84) -> 78 | C85: Click State | G85: World Mark | I85: xpath | J85: (//input[@id='cmp-Input'])[2] | K85: 0 | L85: Click
A86: bln696153 | B86: =COUNTA($B$1:B85) -> 79 | C86: Wait | G86: World Mark | L86: Wait | M86: 2
A87: bln696153 | B87: =COUNTA($B$1:B86) -> 80 | C87: Write State | G87: World Mark | I87: xpath | J87: (//input[@id='cmp-Input' and @class='inputField'])[2] | K87: 0 | L87: Write | M87: Residence1
A88: bln696153 | B88: =COUNTA($B$1:B87) -> 81 | C88: Wait | G88: World Mark | L88: Wait | M88: 2
A89: bln696153 | B89: =COUNTA($B$1:B88) -> 82 | C89: Click Residence | G89: World Mark | I89: xpath | J89: ="//a[contains(.,'"&M87&"')]" -> //a[contains(.,'Residence1')] | K89: 0 | L89: js_click
A90: bln696153 | B90: =COUNTA($B$1:B89) -> 83 | C90: Click Get a Quote button | G90: World Mark | I90: xpath | J90: //button[@type='SUBMIT'] | K90: 0 | L90: js_click
A91: bln696153 | B91: =COUNTA($B$1:B90) -> 84 | C91: Wait | G91: World Mark | L91: Wait | M91: 10
A92: Plan Options
